Workbook
Name AAD: BILAN!$I$11
Name AAI: BILAN!$I$16
Name AAP: BILAN!$I$22
Name AAQ: BILAN!$I$23
Name ABK: BILAN!$I$33
Name ABT: BILAN!$I$37
Name ABU: BILAN!$I$38
Name ad: BILAN!$H$11
Name AI: BILAN!$H$16
Name AP: BILAN!$H$22
Name AQ: BILAN!$H$23
Name BK: BILAN!$H$33
Name BT: BILAN!$H$37
Name BU: BILAN!$H$38
Name ECEN: 'Table TFT'!$G$25
Name ECH: 'Table TFT'!$P$26
Name ECHN: 'Table TFT'!$G$26
Name ECN: 'Table TFT'!$P$25
Name EPA: 'Table TFT'!$Q$27
Name EPB: 'Table TFT'!$Q$28
Name EPH: 'Table TFT'!$H$28
Name EPN: 'Table TFT'!$H$27
Name Forme: FormeJuridique[Forme]

Sheet Referentiels
A1: TABLEAU | B1: FR1 | C1: FR2A | G1: FR1 & FR2B | H1: NOTE3B | I1: NOTE13B | K1: FR2C | L1: NOTE4B
A2: CHAMP | B2: ZS | C2: ZX | D2: ZY | E2: ZZ1 | F2: Contrôle de l'Entité | G2: Code nomenclature d'activité | H2: NATURE DU CONTRAT | I2: Nationalité & Pays de résidence | J2: NATURE DES ACTIONS OU PARTS | K2: Unité de mesure de l'activité | L2: Année du dernier exercice filiale
A3: LIBELLES | B3: Oui | C3: 00 | D3: 1 | E3: 01 | F3: Entité sous contrôle public | G3: A0101 | H3: I | I3: Afghanistan | J3: Ordinaires | K3: Chiffre d'affaires HT (CA HT) | L3: N
B4: Non | C4: 01 | D4: 2 | E4: 02 | F4: Entité sous contrôle privé national | G4: A010101 | H4: M | I4: Afrique du Sud | J4: Préférences | K4: Valeur ajoutée (VA) | L4: N-1
C5: 02 | D5: 3 | E5: 03 | F5: Entité sous contrôle privé étranger | G5: A010102 | H5: A | I5: Albanie
C6: 03 | D6: 4 | E6: 04 | G6: A010103 | I6: Algérie
C7: 04 | E7: 05 | G7: A010104 | I7: Allemagne
C8: 05 | E8: 06 | G8: A0102 | I8: Andorre
C9: 06 | E9: 07 | G9: A010201 | I9: Angola
C10: 07 | E10: 08 | G10: A010202 | I10: Anguilla
C11: 08 | E11: 09 | G11: A010203 | I11: Antarctique
C12: 09 | E12: 10 | G12: A010204 | I12: Antigua-et-Barbuda
C13: 10 | E13: 11 | G13: A010205 | I13: Antilles Néerlandaises
C14: 11 | E14: 12 | G14: A010206 | I14: Arabie Saoudite
C15: 12 | E15: 13 | G15: A010207 | I15: Argentine
C16: 13 | E16: 14 | G16: A010208 | I16: Arménie
C17: 14 | E17: 15 | G17: A010209 | I17: Aruba
C18: 15 | E18: 16 | G18: A010210 | I18: Australie
C19: 16 | E19: 20 | G19: A0103 | I19: Autriche
C20: 17 | E20: 21 | G20: A010301 | I20: Azerbaïdjan
C21: 18 | E21: 22 | G21: A010302 | I21: Bahamas
C22: 19 | E22: 23 | G22: A0104 | I22: Bahreïn
E23: 39 | G23: A010401 | I23: Bangladesh
E24: 40 | G24: A010402 | I24: Barbade
E25: 41 | G25: A010403 | I25: Bélarus
E26: 43 | G26: A0201 | I26: Belgique
E27: 49 | G27: A020101 | I27: Belize
E28: 50 | G28: A020102 | I28: Bénin
E29: 52 | G29: A020103 | I29: Bermudes
E30: 53 | G30: A020200 | I30: Bhoutan
E31: 59 | G31: A0203 | I31: Bolivie
E32: 60 | G32: A020300 | I32: Bosnie-Herzégovine
E33: 99 | G33: A0301 | I33: Botswana
G34: A030101 | I34: Brésil
G35: A030102 | I35: Brunéi Darussalam
G36: A0302 | I36: Bulgarie
G37: A030201 | I37: Burkina Faso
G38: A030202 | I38: Burundi
G39: B0500 | I39: Cambodge
G40: B050000 | I40: Cameroun
G41: B06 | I41: Canada
G42: B0600 | I42: Cap-vert
G43: B060001 | I43: Chili
G44: B060002 | I44: Chine
G45: B07 | I45: Chypre
... G246: G460201 | I246: Zimbabwe
G247: G460202
G248: G460203
G249: G4603
G250: G460301
G251: G460302
G252: G460303
G253: G4604
G254: G460401
G255: G460402
G256: G460403
G257: G460404
G258: G4605
... G457: U990000

Sheet Export XML
A1: GENERER LE FICHIER XML POUR E-IMPOTS
A5: IMPORTANT : veillez à bien activer les modifications et appliquer les macros ("activer le contenu") à l'ouverture pour pouvoir utiliser ce fichier
D10: Type de liasse | G10: NO
D11: NCC | G11: =SUBSTITUTE(Sommaire!$D$45," ","") | J11: =IF(Q11=0,"Veuillez respecter le format 1234567A, sans espace.","") | Q11: =IF(AND(LEN(G11)<>8,LEN(G11)<>0), 0, 1) -> 1
D12: Exercice | G12: =YEAR(Sommaire!$M$35) -> 1900 | J12: =IF(Q12=0,"Veuillez renseigner un exercice valide.","") | Q12: =IF(OR(LEN(G12)=0,AND(ISNUMBER(G12),LEN(G12)=4)),1,0) -> 1
A14: Comment générer un fichier XML pour e-impots ? | G14: IMPORTANT
A15: #1 | B15: Renseignez votre NCC et l'exercice concerné ci-dessus. | G15: Les onglets grisés (GARDE, RECEVABILITE, FICHE R4, NOTES DGI - INS) et les champs grisés de l'onglet FICHE R1 peuvent être ignorés. Les informations qu'ils contiennent ne seront pas exportées dans le fichier XML.
A16: #2 | B16: Remplissez les onglets du fichier qui vous concernent.
A17: #3 | B17: Cliquez sur le bouton "Générer le fichier XML" ci-dessous.
A18: Comment utiliser le fichier XML géneré ? | G18: La structure de ce fichier ne peut pas être modifiée. Si vous avez besoin d'ajouter des informations supplémentaires, veuillez les ajouter dans l'onglet COMMENTAIRE ou en tant que pièce jointe dans e-impots.
A19: #4 | B19: Le fichier XML géneré est déposé dans le répertoire /Documents de votre poste de travail.
A20: #5 | B20: A l'étape 1 de la déclaration de vos états financiers, vous pouvez charger le fichier dans la section "Import des états financiers au format XML". | G20: Tous les champs déjà saisis dans e-impots seront écrasés lors de l'import.
G21: Tous les montants sont à exprimer en Francs CFA (sauf mention contraire)
D27: Note : La génération peut prendre plusieurs minutes.
E29: Version 1.1 - Juillet 2020

Sheet tableaux
A1: 1. MAPPING DES TABLEAUX
A4: Instructions
A5: Pour chaque tableau de la liste ci-dessous :
A6: Etape 1 Remplir la colonne Onglet avec le nom de l'onglet dans lequel se trouve le tableau dans le fichier Excel | C6: Etape 2 Remplir la colonne Première cellule avec le nom de la première cellule à remplir du tableau | G6: Etape 3 Si le tableau est de type variable, remplir la colonne Dernière cellule avec le nom de la dernière cellule à remplir du tableau
A7: Aide : Pour les tableaux qui se trouvent dans les mêmes onglets et/ou cellules que dans le modèle Excel de la DGI, vous pouvez directement copier les valeurs des colonnes Onglet DGI, Première cellule DGI et Dernière cellule DGI qui sont données à titre indicatif.
A9: Définitions
A11: Colonnes de la liste | F11: Types de tableaux
A12: Colonne | B12: Description | F12: Type de tableau | G12: Description
A13: Code tableau | B13: Le code DGI permettant d'identifier le tableau. | F13: Fixe | G13: Tableau ayant un nombre de lignes fixe (ex : tableau de résultat). | I13: 334
A14: Titre | B14: Le titre du tableau. | F14: Variable | G14: Tableau ayant un nombre de lignes variable (ex : liste des dirigeants).
A15: Type | B15: Le type du tableau (cf. liste ci-contre).
A16: Onglet | B16: Renseigner le nom de la feuille du fichier Excel qui contient le tableau.
A17: Première cellule | B17: Renseigner l'adresse de la première cellule à remplir du tableau (celle située en haut à gauche du tableau).
A18: Dernière cellule | B18: Renseigner l'adresse de la dernière cellule à remplir du tableau (celle située en bas à droite du tableau). Uniquement pour les tableaux variables.
A20: Onglet DGI | B20: Nom de la feuille qui contient le tableau dans le modèle Excel de la DGI.
A21: Première cellule DGI | B21: Adresse de la première cellule du tableau dans le modèle Excel de la DGI.
A22: Dernière cellule DGI | B22: Adresse de la dernière cellule du tableau dans le modèle Excel de la DGI.
A24: Liste des tableaux
A26: Informations d'identification des tableaux | D26: A remplir | G26: Valeurs du modèle Excel de la DGI (données à titre indicatif)
A27: Code tableau | B27: Titre | C27: Type | D27: Onglet | E27: Première cellule | F27: Dernière cellule | G27: Onglet DGI | H27: Première cellule DGI | I27: Dernière cellule DGI
A28: FR1 | B28: Fiche R1 | C28: Fixe | D28: FICHE R1 | E28: C8 | G28: FICHE R1 | H28: C8
A29: FR2A | B29: Fiche R2 - Divers | C29: Fixe | D29: FICHE R2 | E29: Q9 | G29: FICHE R2 | H29: Q9
A30: FR2B | B30: Fiche R2 - Détail de l'activité de l'entité | C30: Variable | D30: FICHE R2 | E30: A28 | F30: =ADDRESS(ROW('FICHE R2'!AH29),COLUMN('FICHE R2'!AH29),4) -> AH29 | G30: FICHE R2 | H30: A28 | I30: AH29
A31: FR2C | B31: Fiche R2 - Unité de mesure de l'activité | C31: Fixe | D31: FICHE R2 | E31: Y25 | G31: FICHE R2 | H31: Y25
A32: FR2D | B32: Fiche R2 - Total de l'activité de l'entité | C32: Fixe | D32: FICHE R2 | E32: =ADDRESS(ROW('FICHE R2'!Y30),COLUMN('FICHE R2'!Y30),4) -> Y30 | G32: FICHE R2 | H32: Y30
A33: FR3A | B33: Fiche R3 - Dirigeants | C33: Variable | D33: FICHE R3 | E33: A11 | F33: =ADDRESS(ROW('FICHE R3'!H11),COLUMN('FICHE R3'!H11),4) -> H11 | G33: FICHE R3 | H33: A11 | I33: H11
A34: FR3B | B34: Fiche R3 - Membres du conseil d'administration | C34: Variable | D34: FICHE R3 | E34: =ADDRESS(ROW('FICHE R3'!A17),COLUMN('FICHE R3'!A17),4) -> A17 | F34: =ADDRESS(ROW('FICHE R3'!G17),COLUMN('FICHE R3'!G17),4) -> G17 | G34: FICHE R3 | H34: A17 | I34: G17
A35: ACTIF | B35: Bilan - Actif | C35: Fixe | D35: ACTIF | E35: F11 | G35: ACTIF | H35: F11
A36: PASSIF | B36: Bilan - Passif | C36: Fixe | D36: PASSIF | E36: H11 | G36: PASSIF | H36: H11
A37: RESULTAT | B37: Résultat | C37: Fixe | D37: RESULTAT | E37: I11 | G37: RESULTAT | H37: I11
A38: TFT | B38: Tableau de flux de trésorerie | C38: Fixe | D38: TFT | E38: I10 | G38: TFT | H38: I10
A39: NOTE1A | B39: Dettes garanties par des sûretés réelles | C39: Fixe | D39: NOTE 1 | E39: F10 | G39: NOTE 1 | H39: F10
A40: NOTE1B | B40: Engagements financiers | C40: Fixe | D40: NOTE 1 | E40: G34 | G40: NOTE 1 | H40: G34
A41: NOTE2 | B41: Informations obligatoires | C41: Fixe | D41: NOTE 2 | E41: A9 | G41: NOTE 2 | H41: A9
A42: NOTE3A | B42: Immobilisations (brutes) | C42: Fixe | D42: NOTE 3A | E42: D11 | G42: NOTE 3A | H42: D11
A43: NOTE3B | B43: Biens pris en location acquisition | C43: Fixe | D43: NOTE 3B | E43: E11 | G43: NOTE 3B | H43: E11
A44: NOTE3C | B44: Immobilisations (amortissements) | C44: Fixe | D44: NOTE 3C | E44: D11 | G44: NOTE 3C | H44: D11
A45: NOTE3CBIS | B45: Immobilisations (dépréciations) | C45: Fixe | D45: NOTE 3C BIS | E45: D11 | G45: NOTE 3C BIS | H45: D11
A46: NOTE3D | B46: Immobilisations (plus-values et moins-values de cession) | C46: Fixe | D46: NOTE 3D | E46: D10 | G46: NOTE 3D | H46: D10
A47: NOTE3E1 | B47: Informations sur les réévaluations effectuées par l'entité | C47: Fixe | D47: NOTE 3E | E47: A9 | G47: NOTE 3E | H47: A9
A48: NOTE3E2 | B48: Montant de l'écart incorporé au capital | C48: Fixe | D48: NOTE 3E | E48: =ADDRESS(ROW('NOTE 3E'!H17),COLUMN('NOTE 3E'!H17),4) -> H17 | G48: NOTE 3E | H48: H17
A49: NOTE3E3 | B49: Détail des éléments réévalués par postes du bilan | C49: Variable | D49: NOTE 3E | E49: A11 | F49: =ADDRESS(ROW('NOTE 3E'!I11),COLUMN('NOTE 3E'!I11),4) -> I11 | G49: NOTE 3E | H49: A11 | I49: I11
A50: NOTE3E4 | B50: Total des éléments réévalués par postes du bilan | C50: Fixe | D50: NOTE 3E | E50: =ADDRESS(ROW('NOTE 3E'!F12),COLUMN('NOTE 3E'!F12),4) -> F12 | G50: NOTE 3E | H50: F12
A51: NOTE4A | B51: Immobilisations financières | C51: Fixe | D51: NOTE 4 | E51: F9 | G51: NOTE 4 | H51: F9
A52: NOTE4B | B52: Liste des filiales et participations | C52: Variable | D52: NOTE 4 | E52: A25 | F52: =ADDRESS(ROW('NOTE 4'!K25),COLUMN('NOTE 4'!K25),4) -> K25 | G52: NOTE 4 | H52: A25 | I52: K25
A53: NOTE5A | B53: Actif circulant HAO | C53: Fixe | D53: NOTE 5 | E53: E10 | G53: NOTE 5 | H53: E10
A54: NOTE5B | B54: Dettes circulantes HAO | C54: Fixe | D54: NOTE 5 | E54: E22 | G54: NOTE 5 | H54: E22
A55: NOTE6 | B55: Stocks et en cours | C55: Fixe | D55: NOTE 6 | E55: E9 | G55: NOTE 6 | H55: E9
A56: NOTE7 | B56: Clients | C56: Fixe | D56: NOTE 7 | E56: E9 | G56: NOTE 7 | H56: E9
A57: NOTE8 | B57: Autres créances | C57: Fixe | D57: NOTE 8 | E57: E9 | G57: NOTE 8 | H57: E9
A58: NOTE8A1 | B58: Tableau d'étalement des charges immobilisées | C58: Fixe | D58: NOTE 8A | E58: E10 | G58: NOTE 8A | H58: E10
A59: NOTE8A2 | B59: Détail des frais d'établissement pour l'exercice N | C59: Variable | D59: NOTE 8A | E59: E13 | F59: F42 | G59: NOTE 8A | H59: E13 | I59: F42
A60: NOTE8A3 | B60: Détail des charges à répartir sur plusieurs exercices pour l'exercice N | C60: Variable | D60: NOTE 8A | E60: G13 | F60: H42 | G60: NOTE 8A | H60: G13 | I60: H42
A61: NOTE8A4 | B61: Détail des primes de remboursement des obligations pour l'exercice N | C61: Fixe | D61: NOTE 8A | E61: J13 | G61: NOTE 8A | H61: J13
A62: NOTE8B | B62: Tableau d'étalement des provisions pour charges à répartir | C62: Fixe | D62: NOTE 8B | E62: E10 | G62: NOTE 8B | H62: E10
A63: NOTE8C | B63: Tableau d'étalement des provisions pour engagements de retraite | C63: Fixe | D63: NOTE 8C | E63: E10 | G63: NOTE 8C | H63: E10
A64: NOTE9 | B64: Titres de placement | C64: Fixe | D64: NOTE 9 | E64: E9 | G64: NOTE 9 | H64: E9
A65: NOTE10 | B65: Valeurs à encaisser | C65: Fixe | D65: NOTE 10 | E65: E9 | G65: NOTE 10 | H65: E9
A66: NOTE11 | B66: Disponibilités | C66: Fixe | D66: NOTE 11 | E66: E9 | G66: NOTE 11 | H66: E9
A67: NOTE12A1 | B67: Ecarts de conversion actif | C67: Variable | D67: NOTE 12 | E67: A11 | F67: =ADDRESS(ROW('NOTE 12'!I11),COLUMN('NOTE 12'!I11),4) -> I11 | G67: NOTE 12 | H67: A11 | I67: I11
A68: NOTE12A2 | B68: Ecarts de conversion passif | C68: Variable | D68: NOTE 12 | E68: =ADDRESS(ROW('NOTE 12'!A13),COLUMN('NOTE 12'!A13),4) -> A13 | F68: =ADDRESS(ROW('NOTE 12'!I13),COLUMN('NOTE 12'!I13),4) -> I13 | G68: NOTE 12 | H68: A13 | I68: I13
A69: NOTE12B1 | B69: Transferts de charges d'exploitation | C69: Variable | D69: NOTE 12 | E69: =ADDRESS(ROW('NOTE 12'!A18),COLUMN('NOTE 12'!A18),4) -> A18 | F69: =ADDRESS(ROW('NOTE 12'!I18),COLUMN('NOTE 12'!I18),4) -> I18 | G69: NOTE 12 | H69: A18 | I69: I18
A70: NOTE12B2 | B70: Transferts de charges financières | C70: Variable | D70: NOTE 12 | E70: =ADDRESS(ROW('NOTE 12'!A20),COLUMN('NOTE 12'!A20),4) -> A20 | F70: =ADDRESS(ROW('NOTE 12'!I20),COLUMN('NOTE 12'!I20),4) -> I20 | G70: NOTE 12 | H70: A20 | I70: I20
A71: NOTE13A | B71: Valeur nominale des actions ou parts | C71: Fixe | D71: NOTE 13 | E71: L8 | G71: NOTE 13 | H71: L8
A72: NOTE13B | B72: Détail du capital | C72: Variable | D72: NOTE 13 | E72: A10 | F72: =ADDRESS(ROW('NOTE 13'!L11),COLUMN('NOTE 13'!L11),4) -> L11 | G72: NOTE 13 | H72: A10 | I72: L11
A73: NOTE13C | B73: Total du capital | C73: Fixe | D73: NOTE 13 | E73: =ADDRESS(ROW('NOTE 13'!K12),COLUMN('NOTE 13'!K12),4) -> K12 | G73: NOTE 13 | H73: K12
A74: NOTE14 | B74: Primes et réserves | C74: Fixe | D74: NOTE 14 | E74: F9 | G74: NOTE 14 | H74: F9
A75: NOTE15A | B75: Subventions d'investissement et provisions réglementées | C75: Fixe | D75: NOTE 15A | E75: E9 | G75: NOTE 15A | H75: E9
A76: NOTE15B | B76: Autres fonds propres | C76: Fixe | D76: NOTE 15B | E76: G9 | G76: NOTE 15B | H76: G9
A77: NOTE16A | B77: Dettes financières et ressources assimilées | C77: Fixe | D77: NOTE 16A | E77: E9 | G77: NOTE 16A | H77: E9
A78: NOTE16B1 | B78: Hypothèses actuarielles | C78: Fixe | D78: NOTE 16B | E78: H10 | G78: NOTE 16B | H78: H10
A79: NOTE16B2 | B79: Variation de la valeur de l'engagement de retraite | C79: Fixe | D79: NOTE 16B | E79: H21 | G79: NOTE 16B | H79: H21
A80: NOTE16B3 | B80: Analyse de sensibilité des hypothèses actuarielles | C80: Fixe | D80: NOTE 16B | E80: F34 | G80: NOTE 16B | H80: F34
A81: NOTE16BBIS1 | B81: Actif/passif net comptabilisé au titre des régimes financés | C81: Fixe | D81: NOTE 16B BIS | E81: H10 | G81: NOTE 16B BIS | H81: H10
A82: NOTE16BBIS2 | B82: Valeur actuelle des actifs du régime | C82: Fixe | D82: NOTE 16B BIS | E82: F19 | G82: NOTE 16B BIS | H82: F19
A83: NOTE16C1 | B83: Actifs et passifs éventuels | C83: Fixe | D83: NOTE 16C | E83: G9 | G83: NOTE 16C | H83: G9
A84: NOTE16C2 | B84: Détail des actifs éventuels | C84: Variable | D84: NOTE 16C | E84: A11 | F84: =ADDRESS(ROW('NOTE 16C'!H11),COLUMN('NOTE 16C'!H11),4) -> H11 | G84: NOTE 16C | H84: A11 | I84: H11
A85: NOTE16C3 | B85: Détail des passifs éventuels | C85: Variable | D85: NOTE 16C | E85: =ADDRESS(ROW('NOTE 16C'!A14),COLUMN('NOTE 16C'!A14),4) -> A14 | F85: =ADDRESS(ROW('NOTE 16C'!H14),COLUMN('NOTE 16C'!H14),4) -> H14 | G85: NOTE 16C | H85: A14 | I85: H14
A86: NOTE17 | B86: Fournisseurs d'exploitation | C86: Fixe | D86: NOTE 17 | E86: F9 | G86: NOTE 17 | H86: F9
A87: NOTE18 | B87: Dettes fiscales et sociales | C87: Fixe | D87: NOTE 18 | E87: E9 | G87: NOTE 18 | H87: E9
A88: NOTE19 | B88: Autres dettes et provisions pour risques et charges à court terme | C88: Fixe | D88: NOTE 19 | E88: E9 | G88: NOTE 19 | H88: E9
A89: NOTE20 | B89: Banques, crédit d'escompte et de trésorerie | C89: Fixe | D89: NOTE 20 | E89: F9 | G89: NOTE 20 | H89: F9
A90: NOTE21A | B90: Chiffres d'affaires et autres produits | C90: Fixe | D90: NOTE 21 | E90: F9 | G90: NOTE 21 | H90: F9
A91: NOTE21B | B91: Détail des produits accessoires par nature d'activité économique | C91: Variable | D91: NOTE 21 | E91: A28 | F91: =ADDRESS(ROW('NOTE 21'!H28),COLUMN('NOTE 21'!H28),4) -> H28 | G91: NOTE 21 | H91: A28 | I91: H28
A92: NOTE22 | B92: Achats | C92: Fixe | D92: NOTE 22 | E92: F9 | G92: NOTE 22 | H92: F9
A93: NOTE23 | B93: Transports | C93: Fixe | D93: NOTE 23 | E93: F9 | G93: NOTE 23 | H93: F9
A94: NOTE24 | B94: Services extérieurs | C94: Fixe | D94: NOTE 24 | E94: F9 | G94: NOTE 24 | H94: F9
A95: NOTE25 | B95: Impôts et taxes | C95: Fixe | D95: NOTE 25 | E95: F9 | G95: NOTE 25 | H95: F9
A96: NOTE26 | B96: Autres charges | C96: Fixe | D96: NOTE 26 | E96: F9 | G96: NOTE 26 | H96: F9
A97: NOTE27A | B97: Charges de personnel | C97: Fixe | D97: NOTE 27A | E97: F9 | G97: NOTE 27A | H97: F9
A98: NOTE27B1 | B98: Effectifs | C98: Fixe | D98: NOTE 27B | E98: E12 | G98: NOTE 27B | H98: E12
A99: NOTE27B2 | B99: Masse salariale | C99: Fixe | D99: NOTE 27B | E99: L12 | G99: NOTE 27B | H99: L12
A100: NOTE27B3 | B100: Facturation à l'entité du personnel extérieur | C100: Fixe | D100: NOTE 27B | E100: L22 | G100: NOTE 27B | H100: L22
A101: NOTE27B4 | B101: Frais de personnel | C101: Fixe | D101: NOTE 27B | E101: R22 | G101: NOTE 27B | H101: R22
A102: NOTE28 | B102: Dotations et charges pour provisions et dépréciations | C102: Fixe | D102: NOTE 28 | E102: E11 | G102: NOTE 28 | H102: E11
A103: NOTE29 | B103: Charges et revenus financiers | C103: Fixe | D103: NOTE 29 | E103: F9 | G103: NOTE 29 | H103: F9
A104: NOTE30A | B104: Autres charges et produits HAO | C104: Fixe | D104: NOTE 30 | E104: F9 | G104: NOTE 30 | H104: F9
A105: NOTE30B | B105: Détail des charges HAO constatées | C105: Variable | D105: NOTE 30 | E105: A10 | F105: =ADDRESS(ROW('NOTE 30'!H10),COLUMN('NOTE 30'!H10),4) -> H10 | G105: NOTE 30 | H105: A10 | I105: H10
A106: NOTE30C | B106: Détail des produits HAO constatés | C106: Variable | D106: NOTE 30 | E106: =ADDRESS(ROW('NOTE 30'!A20),COLUMN('NOTE 30'!A20),4) -> A20 | F106: =ADDRESS(ROW('NOTE 30'!H20),COLUMN('NOTE 30'!H20),4) -> H20 | G106: NOTE 30 | H106: A20 | I106: H20
A107: NOTE31 | B107: Répartition du résultat des 5 derniers exercices | C107: Fixe | D107: NOTE 31 | E107: G10 | G107: NOTE 31 | H107: G10
...

Sheet champs fixes
A1: 2. MAPPING DES CHAMPS FIXES (champs des tableaux à nombre de lignes fixe)
A4: Instructions
A6: Etape 1 Cliquer sur le bouton Générer le mapping pour pré-remplir automatiquement la liste ci-dessous | D6: Etape 2 Pour les lignes de la liste qui le nécessitent, corriger manuellement le mapping du champ en modifiant Position ligne et Position colonne. Ces numéros doivent correspondre à la position de la cellule contenant la valeur du champ par rapport à la position de la première cellule du tableau. | G6: Etape 3 Cliquer sur le bouton Générer le mapping pour obtenir le mapping final
A8: Définitions
A10: Colonnes de la liste
A11: Colonne | B11: Description
A12: Code tableau | B12: Le code DGI permettant d'identifier le tableau auquel le champ appartient.
A13: Code ligne | B13: Le code permettant d'identifier la ligne du tableau où se trouve le champ dans le modèle Excel de la DGI (s'il y en a un).
A14: Libellé ligne | B14: Le libellé e-impots de la ligne du tableau où se trouve le champ.
A15: Libellé colonne | B15: Le libellé e-impots de la colonne du tableau où se trouve le champ.
A16: Code champ | B16: Le code DGI permettant d'identifier le champ.
A17: Position ligne | B17: Le numéro de position de la ligne du tableau où se trouve le champ par rapport à la première cellule du tableau. La valeur pré-remplie est celle correspondant au modèle Excel de la DGI.
A18: Position colonne | B18: Le numéro de position de la colonne du tableau où se trouve le champ par rapport à la première cellule du tableau. La valeur pré-remplie est celle correspondant au modèle Excel de la DGI.
A19: Cellule | B19: L'adresse de la cellule contenant la valeur du champ.
A20: Valeur | B20: La valeur du champ saisie dans le fichier (si le champ a été rempli).
A22: Liste des champs de tableaux fixes
A27: Informations d'identification des champs | F27: A modifier si nécessaire | H27: Mapping généré
A28: Code tableau | B28: Code ligne | C28: Libellé ligne | D28: Libellé colonne | E28: Code champ | F28: Position ligne | G28: Position colonne | H28: Cellule | I28: Valeur
A29: FR1 | B29: ZA | C29: DATE DE DEBUT DE L'EXERCICE COMPTABLE | D29: Valeurs | E29: NO_FR1_ZA1_1 | F29: 1 | G29: 12 | H29: N8
A30: FR1 | B30: ZA | C30: DATE DE FIN DE L'EXERCICE COMPTABLE | D30: Valeurs | E30: NO_FR1_ZA2_1 | F30: 1 | G30: 17 | H30: S8
A31: FR1 | B31: ZB | C31: DATE D'ARRETE EFFECTIF DES COMPTES | D31: Valeurs | E31: NO_FR1_ZB_1 | F31: 3 | G31: 6 | H31: H10
A32: FR1 | B32: ZC | C32: EXERCICE PRECEDENT CLOS LE | D32: Valeurs | E32: NO_FR1_ZC_1 | F32: 5 | G32: 6 | H32: H12
A33: FR1 | B33: ZD | C33: DUREE EXERCICE PRECEDENT EN MOIS | D33: Valeurs | E33: NO_FR1_ZD_1 | F33: 5 | G33: 19 | H33: U12
A34: FR1 | B34: ZE | C34: Greffe | D34: Valeurs | E34: NO_FR1_ZE1_1 | F34: 7 | G34: 1 | H34: C14
A35: FR1 | B35: ZE | C35: N°Registre du Commerce | D35: Valeurs | E35: NO_FR1_ZE2_1 | F35: 7 | G35: 2 | H35: D14
A36: FR1 | B36: ZF | C36: N° Répertoire des entités | D36: Valeurs | E36: NO_FR1_ZF_1 | F36: 7 | G36: 9 | H36: K14
A37: FR1 | B37: ZG | C37: N° de caisse sociale | D37: Valeurs | E37: NO_FR1_ZG_1 | F37: 10 | G37: 1 | H37: C17
A38: FR1 | B38: ZH | C38: N° Code Importateur | D38: Valeurs | E38: NO_FR1_ZH_1 | F38: 10 | G38: 4 | H38: F17
A39: FR1 | B39: ZI | C39: Code activité principale | D39: Valeurs | E39: NO_FR1_ZI_1 | F39: 10 | G39: 15 | H39: Q17
A40: FR1 | B40: ZK | C40: Adresse e-mail | D40: Valeurs | E40: NO_FR1_ZK1_1 | F40: 16 | G40: 3 | H40: E23
... A64: FR2A | B64: ZZ4 | C64: Première année d'exercice dans le pays : | D64: Valeurs | E64: NO_FR2A_ZZ4_1 | F64: 12 | G64: 1 | H64: Q20
A65: FR2A | C65: Contrôle de l'entité | D65: Valeurs | E65: NO_FR2A_1_1 | F65: 3 | G65: 7 | H65: W11
A66: FR2C | C66: Unité de mesure de l'activité | D66: Valeurs | E66: NO_FR2C_1_1 | F66: 1 | G66: 1 | H66: Y25
A67: FR2D | C67: Total de l'activité de l'entité | D67: Chiffre d'affaires HT ou Valeur ajoutée (VA) | E67: NO_FR2D_1_1 | F67: 1 | G67: 1 | H67: Y30 | I67: 0
A68: FR2D | C68: Total de l'activité de l'entité | D68: % activité dans le CA HT ou la VA | E68: NO_FR2D_1_2 | F68: 1 | G68: 10 | H68: AH30 | I68: 0,00%
A69: ACTIF | B69: AD | C69: IMMOBILISATIONS INCORPORELLES | D69: BRUT | E69: NO_ACTIF_AD_1 | F69: 1 | G69: 1 | H69: F11
A70: ACTIF | B70: AD | C70: IMMOBILISATIONS INCORPORELLES | D70: AMORT et DEPREC. | E70: NO_ACTIF_AD_2 | F70: 1 | G70: 2 | H70: G11
A71: ACTIF | B71: AD | C71: IMMOBILISATIONS INCORPORELLES | D71: NET | E71: NO_ACTIF_AD_3 | F71: 1 | G71: 3 | H71: H11
A72: ACTIF | B72: AD | C72: IMMOBILISATIONS INCORPORELLES | D72: NET (N-1) | E72: NO_ACTIF_AD_4 | F72: 1 | G72: 4 | H72: I11
A73: ACTIF | B73: AE | C73: Frais de développement et de prospection | D73: BRUT | E73: NO_ACTIF_AE_1 | F73: 2 | G73: 1 | H73: F12
A74: ACTIF | B74: AE | C74: Frais de développement et de prospection | D74: AMORT et DEPREC. | E74: NO_ACTIF_AE_2 | F74: 2 | G74: 2 | H74: G12
A75: ACTIF | B75: AE | C75: Frais de développement et de prospection | D75: NET | E75: NO_ACTIF_AE_3 | F75: 2 | G75: 3 | H75: H12
A76: ACTIF | B76: AE | C76: Frais de développement et de prospection | D76: NET (N-1) | E76: NO_ACTIF_AE_4 | F76: 2 | G76: 4 | H76: I12
A77: ACTIF | B77: AF | C77: Brevets, licences, logiciels, et droits similaires | D77: BRUT | E77: NO_ACTIF_AF_1 | F77: 3 | G77: 1 | H77: F13
A78: ACTIF | B78: AF | C78: Brevets, licences, logiciels, et droits similaires | D78: AMORT et DEPREC. | E78: NO_ACTIF_AF_2 | F78: 3 | G78: 2 | H78: G13
A79: ACTIF | B79: AF | C79: Brevets, licences, logiciels, et droits similaires | D79: NET | E79: NO_ACTIF_AF_3 | F79: 3 | G79: 3 | H79: H13
A80: ACTIF | B80: AF | C80: Brevets, licences, logiciels, et droits similaires | D80: NET (N-1) | E80: NO_ACTIF_AF_4 | F80: 3 | G80: 4 | H80: I13
... A96: ACTIF | B96: AJ | C96: Terrains | D96: NET (N-1) | E96: NO_ACTIF_AJ_4 | F96: 7 | G96: 4 | H96: I17
A97: ACTIF | C97: - dont Placement Net | D97: NET | E97: NO_ACTIF_1_3 | F97: 7 | G97: -2 | H97: C17
A98: ACTIF | C98: - dont Placement Net | D98: NET (N-1) | E98: NO_ACTIF_1_4 | F98: 7 | G98: -1 | H98: D17
A99: ACTIF | B99: AK | C99: Bâtiments | D99: BRUT | E99: NO_ACTIF_AK_1 | F99: 8 | G99: 1 | H99: F18
A100: ACTIF | B100: AK | C100: Bâtiments | D100: AMORT et DEPREC. | E100: NO_ACTIF_AK_2 | F100: 8 | G100: 2 | H100: G18
A101: ACTIF | B101: AK | C101: Bâtiments | D101: NET | E101: NO_ACTIF_AK_3 | F101: 8 | G101: 3 | H101: H18
A102: ACTIF | B102: AK | C102: Bâtiments | D102: NET (N-1) | E102: NO_ACTIF_AK_4 | F102: 8 | G102: 4 | H102: I18
A103: ACTIF | C103: - dont Placement Net | D103: NET | E103: NO_ACTIF_2_3 | F103: 8 | G103: -2 | H103: C18
A104: ACTIF | C104: - dont Placement Net | D104: NET (N-1) | E104: NO_ACTIF_2_4 | F104: 8 | G104: -1 | H104: D18
A105: ACTIF | B105: AL | C105: Aménagements, agencements et installations | D105: BRUT | E105: NO_ACTIF_AL_1 | F105: 9 | G105: 1 | H105: F19
A106: ACTIF | B106: AL | C106: Aménagements, agencements et installations | D106: AMORT et DEPREC. | E106: NO_ACTIF_AL_2 | F106: 9 | G106: 2 | H106: G19
A107: ACTIF | B107: AL | C107: Aménagements, agencements et installations | D107: NET | E107: NO_ACTIF_AL_3 | F107: 9 | G107: 3 | H107: H19
A108: ACTIF | B108: AL | C108: Aménagements, agencements et installations | D108: NET (N-1) | E108: NO_ACTIF_AL_4 | F108: 9 | G108: 4 | H108: I19
A109: ACTIF | B109: AM | C109: Matériel, mobilier et actifs biologiques | D109: BRUT | E109: NO_ACTIF_AM_1 | F109: 10 | G109: 1 | H109: F20
A110: ACTIF | B110: AM | C110: Matériel, mobilier et actifs biologiques | D110: AMORT et DEPREC. | E110: NO_ACTIF_AM_2 | F110: 10 | G110: 2 | H110: G20
A111: ACTIF | B111: AM | C111: Matériel, mobilier et actifs biologiques | D111: NET | E111: NO_ACTIF_AM_3 | F111: 10 | G111: 3 | H111: H20
A112: ACTIF | B112: AM | C112: Matériel, mobilier et actifs biologiques | D112: NET (N-1) | E112: NO_ACTIF_AM_4 | F112: 10 | G112: 4 | H112: I20
A113: ACTIF | B113: AN | C113: Matériel de transport | D113: BRUT | E113: NO_ACTIF_AN_1 | F113: 11 | G113: 1 | H113: F21
A114: ACTIF | B114: AN | C114: Matériel de transport | D114: AMORT et DEPREC. | E114: NO_ACTIF_AN_2 | F114: 11 | G114: 2 | H114: G21
A115: ACTIF | B115: AN | C115: Matériel de transport | D115: NET | E115: NO_ACTIF_AN_3 | F115: 11 | G115: 3 | H115: H21
A116: ACTIF | B116: AN | C116: Matériel de transport | D116: NET (N-1) | E116: NO_ACTIF_AN_4 | F116: 11 | G116: 4 | H116: I21
... A340: TFT | B340: FE | C340: + Variation du passif circulant (1) | D340: EXERCICE N-1 | E340: NO_TFT_FE_2 | F340: 7 | G340: 2 | H340: J16
A341: TFT | C341: Variation du BF lié aux activités opérationnelles FB+FC+FD+FE : | D341: EXERCICE N | E341: NO_TFT_2_1 | F341: 8 | G341: 1 | H341: I17
A342: TFT | C342: Variation du BF lié aux activités opérationnelles FB+FC+FD+FE : | D342: EXERCICE N-1 | E342: NO_TFT_2_2 | F342: 8 | G342: 2 | H342: J17
A343: TFT | B343: ZB | C343: Flux de trésorerie provenant des activités opérationnelles (Somme FA à FE) | D343: EXERCICE N | E343: NO_TFT_ZB_1 | F343: 10 | G343: 1 | H343: I19
A344: TFT | B344: ZB | C344: Flux de trésorerie provenant des activités opérationnelles (Somme FA à FE) | D344: EXERCICE N-1 | E344: NO_TFT_ZB_2 | F344: 10 | G344: 2 | H344: J19
A345: TFT | B345: FF | C345: - Décaissements liés aux acquisitions d'immobilisations incorporelles | D345: EXERCICE N | E345: NO_TFT_FF_1 | F345: 12 | G345: 1 | H345: I21
A346: TFT | B346: FF | C346: - Décaissements liés aux acquisitions d'immobilisations incorporelles | D346: EXERCICE N-1 | E346: NO_TFT_FF_2 | F346: 12 | G346: 2 | H346: J21
A347: TFT | B347: FG | C347: - Décaissements liés aux acquisitions d'immobilisations corporelles | D347: EXERCICE N | E347: NO_TFT_FG_1 | F347: 13 | G347: 1 | H347: I22
A348: TFT | B348: FG | C348: - Décaissements liés aux acquisitions d'immobilisations corporelles | D348: EXERCICE N-1 | E348: NO_TFT_FG_2 | F348: 13 | G348: 2 | H348: J22
A349: TFT | B349: FH | C349: - Décaissements liés aux acquisitions d'immobilisations financières | D349: EXERCICE N | E349: NO_TFT_FH_1 | F349: 14 | G349: 1 | H349: I23
A350: TFT | B350: FH | C350: - Décaissements liés aux acquisitions d'immobilisations financières | D350: EXERCICE N-1 | E350: NO_TFT_FH_2 | F350: 14 | G350: 2 | H350: J23
A351: TFT | B351: FI | C351: + Encaissements liés aux cessions d'immobilisations incorporelles et corporelles | D351: EXERCICE N | E351: NO_TFT_FI_1 | F351: 15 | G351: 1 | H351: I24
A352: TFT | B352: FI | C352: + Encaissements liés aux cessions d'immobilisations incorporelles et corporelles | D352: EXERCICE N-1 | E352: NO_TFT_FI_2 | F352: 15 | G352: 2 | H352: J24
A353: TFT | B353: FJ | C353: + Encaissements liés aux cessions d'immobilisations financières | D353: EXERCICE N | E353: NO_TFT_FJ_1 | F353: 16 | G353: 1 | H353: I25
A354: TFT | B354: FJ | C354: + Encaissements liés aux cessions d'immobilisations financières | D354: EXERCICE N-1 | E354: NO_TFT_FJ_2 | F354: 16 | G354: 2 | H354: J25
... A380: TFT | B380: ZH | C380: Trésorerie nette au 31 Décembre (ZG + ZA) Contrôle : Trésorerie actif N - Trésorerie passif N | D380: EXERCICE N-1 | E380: NO_TFT_ZH_2 | F380: 31 | G380: 2 | H380: J40
A381: NOTE1A | C381: Emprunts obligataires convertibles | D381: Montant brut (1) | E381: NO_NOTE1A_2_1 | F381: 2 | G381: 1 | H381: F11
A382: NOTE1A | C382: Emprunts obligataires convertibles | D382: Hypothèques (2) | E382: NO_NOTE1A_2_2 | F382: 2 | G382: 2 | H382: G11
A383: NOTE1A | C383: Emprunts obligataires convertibles | D383: Nantissements (2) | E383: NO_NOTE1A_2_3 | F383: 2 | G383: 3 | H383: H11
A384: NOTE1A | C384: Emprunts obligataires convertibles | D384: Gages/autres (2) | E384: NO_NOTE1A_2_4 | F384: 2 | G384: 4 | H384: I11
A385: NOTE1A | C385: Autres emprunts obligataires | D385: Montant brut (1) | E385: NO_NOTE1A_3_1 | F385: 3 | G385: 1 | H385: F12
A386: NOTE1A | C386: Autres emprunts obligataires | D386: Hypothèques (2) | E386: NO_NOTE1A_3_2 | F386: 3 | G386: 2 | H386: G12
A387: NOTE1A | C387: Autres emprunts obligataires | D387: Nantissements (2) | E387: NO_NOTE1A_3_3 | F387: 3 | G387: 3 | H387: H12
A388: NOTE1A | C388: Autres emprunts obligataires | D388: Gages/autres (2) | E388: NO_NOTE1A_3_4 | F388: 3 | G388: 4 | H388: I12
A389: NOTE1A | C389: Emprunts et dettes des établissements de crédit | D389: Montant brut (1) | E389: NO_NOTE1A_4_1 | F389: 4 | G389: 1 | H389: F13
A390: NOTE1A | C390: Emprunts et dettes des établissements de crédit | D390: Hypothèques (2) | E390: NO_NOTE1A_4_2 | F390: 4 | G390: 2 | H390: G13
A391: NOTE1A | C391: Emprunts et dettes des établissements de crédit | D391: Nantissements (2) | E391: NO_NOTE1A_4_3 | F391: 4 | G391: 3 | H391: H13
A392: NOTE1A | C392: Emprunts et dettes des établissements de crédit | D392: Gages/autres (2) | E392: NO_NOTE1A_4_4 | F392: 4 | G392: 4 | H392: I13
... A396: NOTE1A | C396: Autres dettes financières | D396: Gages/autres (2) | E396: NO_NOTE1A_5_4 | F396: 5 | G396: 4 | H396: I14
A397: NOTE1A | C397: SOUS TOTAL (1) | D397: Montant brut (1) | E397: NO_NOTE1A_6_1 | F397: 6 | G397: 1 | H397: F15 | I397: 0
A398: NOTE1A | C398: Dettes de crédit-bail immobilier | D398: Montant brut (1) | E398: NO_NOTE1A_8_1 | F398: 8 | G398: 1 | H398: F17
A399: NOTE1A | C399: Dettes de crédit-bail immobilier | D399: Hypothèques (2) | E399: NO_NOTE1A_8_2 | F399: 8 | G399: 2 | H399: G17
...

Sheet champs variables
A1: 3. MAPPING DES CHAMPS VARIABLES (champs des tableaux à nombre de lignes variable)
A4: Instructions
A6: Etape 1 Cliquer sur le bouton Générer le mapping pour pré-remplir automatiquement la liste ci-dessous | B6: Etape 2 Pour les lignes de la liste qui le nécessitent, corriger manuellement le mapping en modifiant Position colonne. Ce numéro doit correspondre à la position de la colonne par rapport à la position de la première cellule du tableau. | D6: Etape 3 Cliquer sur le bouton Générer le mapping pour obtenir le mapping final
A8: Définitions
A10: Colonnes de la liste
A11: Colonne | B11: Description
A12: Code tableau | B12: Le code DGI permettant d'identifier le tableau auquel la colonne appartient.
A13: Libellé colonne | B13: Le libellé e-impots de la colonne.
A14: Code colonne | B14: Le code DGI permettant d'identifier la colonne.
A15: Position colonne | B15: Le numéro de position de la colonne dans le fichier par rapport à la première cellule du tableau. La valeur pré-remplie est celle correspondant au modèle Excel de la DGI.
A16: Cellule | B16: L'adresse de la cellule contenant la valeur du premier champ de la colonne.
A18: Liste des colonnes de tableaux variables
A23: Informations d'identification des colonnes | D23: A modifier si nécessaire | E23: Mapping généré
A24: Code tableau | B24: Libellé colonne | C24: Code colonne | D24: Position colonne | E24: Cellule
A25: FR2B | B25: Désignation de l'activité | C25: NO_FR2B_1 | D25: 1 | E25: A28
A26: FR2B | B26: Code nomenclature d'activité | C26: NO_FR2B_2 | D26: 16 | E26: P28
A27: FR2B | B27: Chiffre d'affaires HT (CA HT) ou Valeur ajoutée (VA) | C27: NO_FR2B_3 | D27: 25 | E27: Y28
A28: FR2B | B28: % activité dans le CA HT ou la VA | C28: NO_FR2B_4 | D28: 34 | E28: AH28
A29: FR3A | B29: Nom et Prénoms | C29: NO_FR3A_1 | D29: 1 | E29: A11
A30: FR3A | B30: Nationalité | C30: NO_FR3A_2 | D30: 3 | E30: C11
A31: FR3A | B31: Autres nationalités (2) | C31: NO_FR3A_3 | D31: 4 | E31: D11
A32: FR3A | B32: Qualité (1) | C32: NO_FR3A_4 | D32: 5 | E32: E11
A33: FR3A | B33: N° d'identification fiscale | C33: NO_FR3A_5 | D33: 6 | E33: F11
A34: FR3A | B34: Adresse (BP, ville, pays, adresse géographique et adresse email) | C34: NO_FR3A_6 | D34: 8 | E34: H11
A35: FR3B | B35: Nom et Prénoms | C35: NO_FR3B_1 | D35: 1 | E35: A17
A36: FR3B | B36: Structure représentée | C36: NO_FR3B_2 | D36: 3 | E36: C17
... A159: SUPPL7B | B159: INTERETS | C159: NO_SUPPL7B_3 | D159: 9 | E159: I11

Sheet export
A1: 4. VERIFICATION DU MAPPING
A4: Instructions
A6: Etape 1 Remplir les champs de la liasse avec des valeurs | C6: Etape 2 Cliquer sur le bouton Récupérer les champs remplis pour obtenir les valeurs récupérées grâce au mapping | E6: Etape 3 Vérifier que les valeurs des champs de la liasse qui ont été remplis ont bien été récupérées. Corriger le mapping si ce n'est pas le cas.
A8: Contenu de la liasse récupéré grâce au mapping
A10: Type de liasse | B10: NCC | C10: Exercice
A11: ='Export XML'!G10 -> NO | B11: ='Export XML'!G11 | C11: ='Export XML'!G12 -> 1900
A13: Valeurs remplies dans les champs variables | E13: Valeurs remplies dans les champs fixes
A14: Code colonne | B14: Ligne | C14: Valeur | E14: Code champ | F14: Valeur
A15: NO_FR2B_1 | B15: 2 | C15: Divers | E15: NO_FR1_ZA1_1 | F15: 01/01/2019
A16: NO_NOTE13B_1 | B16: 2 | C16: Apporteurs, capital non appelé | E16: NO_FR1_ZA2_1 | F16: 31/12/2019
A17: NO_NOTE32_1 | B17: 2 | C17: NON VENTILE | E17: NO_FR1_ZB_1 | F17: 25/03/2020
A18: NO_NOTE33_1 | B18: 2 | C18: NON VENTILE | E18: NO_FR1_ZC_1 | F18: 31/12/2019
A19: NO_SUPPL1B_1 | B19: 52 | C19: NON VENTILE | E19: NO_FR1_ZD_1 | F19: 12
E20: NO_FR1_ZE1_1 | F20: ABJ
E21: NO_FR1_ZE2_1 | F21: CI-ABJ-2020-B-04044
E22: NO_FR1_ZG_1 | F22: 362401
E23: NO_FR1_ZI_1 | F23: J620002
E24: NO_FR1_ZK1_1 | F24: info@befils.com
E25: NO_FR1_ZK2_1 | F25: 08
E26: NO_FR1_ZK3_1 | F26: 3181
E27: NO_FR1_ZK4_1 | F27: ABIDJAN
E28: NO_FR1_ZL_1 | F28: YOPOUGON BATIM
E29: NO_FR2A_ZX_1 | F29: 03
E30: NO_FR2A_ZY_1 | F30: 2
E31: NO_FR2A_ZZ1_1 | F31: 03
E32: NO_FR2A_ZZ4_1 | F32: 2018
E33: NO_NOTE34_31_3 | F33: 0 points
E34: NO_NOTE34_32_3 | F34: 0 points
E35: NO_NOTE37_28_1 | F35: 0.25

Sheet Sommaire
B2: SOMMAIRE | O2: ETATS COMPLEMENTAIRES
B4: TABLE DE CONVERSION | F4: NOTE 3E - INFORMATIONS SUR LES REEVALUATIONS EFFEC | I4: FALSE | J4: =IF(I4=TRUE,1,0) -> 0 | K4: NOTE 18 - DETTES FISCALES ET SOCIALES | M4: TRUE | N4: =IF(M4=TRUE,1,0) -> 1 | O4: NOTES DGI - INS - FICHE RECAPITULATIVE DES ETATS S | R4: TRUE
B5: COUVERTURE | D5: TRUE | E5: =IF(D5=TRUE,1,0) -> 1 | F5: NOTE 4 - IMMOBILISATIONS FINANCIERES | I5: FALSE | J5: =IF(I5=TRUE,1,0) -> 0 | K5: NOTE 19 - AUTRES DETTES ET PROVISIONS POUR RISQUES | M5: FALSE | N5: =IF(M5=TRUE,1,0) -> 0 | O5: COMP-CHARGES - DETAIL DES CHARGES | R5: TRUE
B6: GARDE | D6: TRUE | E6: =IF(D6=TRUE,1,0) -> 1 | F6: NOTE 5 - ACTIF CIRCULANT ET DETTES CIRCULANTES HA | I6: FALSE | J6: =IF(I6=TRUE,1,0) -> 0 | K6: NOTE 20 - BANQUES, CREDIT D'ESCOMPTE ET DE TRESORE | M6: TRUE | N6: =IF(M6=TRUE,1,0) -> 1 | O6: COMP-TVA - ETAT TVA | R6: TRUE
B7: RECEVABILITE | D7: TRUE | E7: =IF(D7=TRUE,1,0) -> 1 | F7: NOTE 6 - STOCKS ET ENCOURS | I7: FALSE | J7: =IF(I7=TRUE,1,0) -> 0 | K7: NOTE 21 - CHIFFRE D'AFFAIRES ET AUTRES PRODUITS | M7: TRUE | N7: =IF(M7=TRUE,1,0) -> 1 | O7: COMP-TVA (2) - ETAT TVA SUPPORTE NON DEDUCTIBLE | R7: TRUE
B8: NOTE36 - TABLE DES CODES | D8: TRUE | E8: =IF(D8=TRUE,1,0) -> 1 | F8: NOTE 7 - CLIENTS | I8: FALSE | J8: =IF(I8=TRUE,1,0) -> 0 | K8: NOTE 22 - ACHATS | M8: TRUE | N8: =IF(M8=TRUE,1,0) -> 1 | O8: SUPPL1 - ELEMENTS STATISTIQUES UEMOA | R8: FALSE
B9: NOTE36 Suite - Nomenclature | D9: TRUE | E9: =IF(D9=TRUE,1,0) -> 1 | F9: NOTE 8 - AUTRES CREANCES | I9: FALSE | J9: =IF(I9=TRUE,1,0) -> 0 | K9: NOTE 23 - TRANSPORTS | M9: TRUE | N9: =IF(M9=TRUE,1,0) -> 1 | O9: SUPPL2 - REPARTITION DU RESULTAT FISCAL DES SOCIET | R9: FALSE | U9: Contacts
B10: FICHE R1 - FICHE IDENTIFICATION ET RENS. DIVERS 1 | D10: TRUE | E10: =IF(D10=TRUE,1,0) -> 1 | F10: NOTE 8A - TAB D’ETALEMENT DES CHARGES IMMOBILISEES | I10: FALSE | J10: =IF(I10=TRUE,1,0) -> 0 | K10: NOTE 24 - SERVICES EXTERIEURS | M10: TRUE | N10: =IF(M10=TRUE,1,0) -> 1 | O10: SUPPL3 - COMPLEMENT INFORMATIONS ENTITES INDIVIDUE | R10: FALSE
B11: FICHE R2 - FICHE IDENTIFICATION ET RENS. DIVERS 2 | D11: TRUE | E11: =IF(D11=TRUE,1,0) -> 1 | F11: NOTE 8B - TAB D’ETALEMENT DES PROVISIONS POUR CHAR | I11: FALSE | J11: =IF(I11=TRUE,1,0) -> 0 | K11: NOTE 25 - IMPOTS ET TAXES | M11: TRUE | N11: =IF(M11=TRUE,1,0) -> 1 | O11: SUPPL4 - TABLEAU DES AMORTISSEMENTS ET INVENTAIRE | R11: TRUE | U11: +225 77 23 23 25
B12: FICHE R3 - FICHE IDENTIFICATION ET RENS. DIVERS 3 | D12: TRUE | E12: =IF(D12=TRUE,1,0) -> 1 | F12: NOTE 8C - TAB D'ETALEMENT DES PROVISIONS POUR ENGA | I12: FALSE | J12: =IF(I12=TRUE,1,0) -> 0 | K12: NOTE 26 - AUTRES CHARGES | M12: FALSE | N12: =IF(M12=TRUE,1,0) -> 0 | O12: SUPPL5 - DETAIL DES FRAIS ACCESSOIRES SUR ACHATS | R12: FALSE | U12: +225 74 64 44 91
B13: BILAN | D13: TRUE | E13: =IF(D13=TRUE,1,0) -> 1 | F13: NOTE 9 - TITRES DE PLACEMENT | I13: FALSE | J13: =IF(I13=TRUE,1,0) -> 0 | K13: NOTE 27A - CHARGES DE PERSONNEL | M13: TRUE | N13: =IF(M13=TRUE,1,0) -> 1 | O13: SUPPL6 - DETAIL DES AVANTAGES EN NATURE ET EN ESPE | R13: FALSE | U13: +225 20 35 31 73
B14: BILAN - ACTIF | D14: TRUE | E14: =IF(D14=TRUE,1,0) -> 1 | F14: NOTE 10 - VALEURS A ENCAISSER | I14: FALSE | J14: =IF(I14=TRUE,1,0) -> 0 | K14: NOTE 27B - EFFECTIFS, MASSE SALARIALE ET PERSONNEL | M14: TRUE | N14: =IF(M14=TRUE,1,0) -> 1 | O14: SUPPL7 - CREANCES & DETTES ECHUES DE L'EXERCICE | R14: TRUE | U14: info@befils.com
B15: BILAN - PASSIF | D15: TRUE | E15: =IF(D15=TRUE,1,0) -> 1 | F15: NOTE 11 - DISPONIBILITES | I15: TRUE | J15: =IF(I15=TRUE,1,0) -> 1 | K15: NOTE 28 - DOTATIONS ET CHARGES POUR PROVISIONS ET | M15: TRUE | N15: =IF(M15=TRUE,1,0) -> 1 | O15: COMMENTAIRE | R15: TRUE
B16: COMPTE DE RESULTAT | D16: TRUE | E16: =IF(D16=TRUE,1,0) -> 1 | F16: NOTE 12 - ECARTS DE CONVERSION ET TRANSFERT DE CHA | I16: FALSE | J16: =IF(I16=TRUE,1,0) -> 0 | K16: NOTE 29 - CHARGES ET REVENUS FINANCIERS | M16: FALSE | N16: =IF(M16=TRUE,1,0) -> 0
B17: TABLEAU DES FLUX DE TRESORERIE | D17: TRUE | E17: =IF(D17=TRUE,1,0) -> 1 | F17: NOTE 13 - CAPITAL : VALEUR NOMINALE DES ACTIONS OU | I17: TRUE | J17: =IF(I17=TRUE,1,0) -> 1 | K17: NOTE 30 - AUTRES CHARGES ET PRODUITS HAO | M17: FALSE | N17: =IF(M17=TRUE,1,0) -> 0 | O17: IMPORTANT !!! -------------------------------------------- Merci cocher les feuilles à imprimer. Seules les feuilles cochées ici seront imprimées
B18: FICHE R4 - FICHE RECAPITULATIVE DES NOTES ANNEXES | D18: TRUE | E18: =IF(D18=TRUE,1,0) -> 1 | F18: NOTE 14 - PRIMES ET RESERVES | I18: TRUE | J18: =IF(I18=TRUE,1,0) -> 1 | K18: NOTE 31 - REPARTITION DU RESULTAT ET AUTRES ELEMEN | M18: TRUE | N18: =IF(M18=TRUE,1,0) -> 1
B19: NOTE 1 - DETTES GARANTIES PAR DES SURETES REELLES | D19: FALSE | E19: =IF(D19=TRUE,1,0) -> 0 | F19: NOTE 15A - SUBVENTIONS ET PROVISIONS REGLEMENTEES | I19: FALSE | J19: =IF(I19=TRUE,1,0) -> 0 | K19: NOTE 32 - PRODUCTION DE L'EXERCICE | M19: FALSE | N19: =IF(M19=TRUE,1,0) -> 0
B20: NOTE 2 - INFORMATIONS OBLIGATOIRES | D20: FALSE | E20: =IF(D20=TRUE,1,0) -> 0 | F20: NOTE 15B - AUTRES FONDS PROPRES | I20: FALSE | J20: =IF(I20=TRUE,1,0) -> 0 | K20: NOTE 33 - ACHATS DESTINES A LA PRODUCTION | M20: FALSE | N20: =IF(M20=TRUE,1,0) -> 0
B21: NOTE 3A - IMMOBILISATIONS BRUTES | D21: TRUE | E21: =IF(D21=TRUE,1,0) -> 1 | F21: NOTE 16A - DETTES FINANCIERES ET RESSOURCES ASSIMI | I21: TRUE | J21: =IF(I21=TRUE,1,0) -> 1 | K21: NOTE 34 - FICHE DE SYNTHESE DES PRINCIPAUX INDICAT | M21: TRUE | N21: =IF(M21=TRUE,1,0) -> 1
B22: NOTE 3B - BIENS PRIS EN LOCATION-ACQUISITION | D22: FALSE | E22: =IF(D22=TRUE,1,0) -> 0 | F22: NOTE 16B - ENGAGEMENTS DE RETRAITE ET AVANTAGES AS | I22: FALSE | J22: =IF(I22=TRUE,1,0) -> 0 | K22: NOTE 35 - LISTE DES INFORMATIONS SOCIALES, ENVIRON | M22: FALSE | N22: =IF(M22=TRUE,1,0) -> 0 | T22: =IF(OR(Code!$R$6=Code!$S$6,Code!$U$6="vert"),"","Veuillez saisir la clé d'activation Pour activer les calculs automatiques")
B23: NOTE 3C - IMMOBILISATIONS : AMORTISSEMENTS | D23: TRUE | E23: =IF(D23=TRUE,1,0) -> 1 | F23: NOTE 16B BIS - ENGAGEMENTS DE RETRAITE ET AVANTAGE | I23: FALSE | J23: =IF(I23=TRUE,1,0) -> 0 | K23: NOTE 37 - DETERMINATION IMPOT SUR RESULTAT | M23: TRUE | N23: =IF(M23=TRUE,1,0) -> 1
B24: NOTE 3C BIS - IMMOBILISATIONS : DEPRECIATIONS | D24: FALSE | E24: =IF(D24=TRUE,1,0) -> 0 | F24: NOTE 16C - ACTIFS ET PASSIFS EVENTUELS | I24: FALSE | J24: =IF(I24=TRUE,1,0) -> 0 | K24: NOTE 38 - EVENEMENTS POSTERIEURS A LA CLOTURE DE L | M24: FALSE
B25: NOTE 3D - IMMOBILISATIONS : PLUS-VALUES ET MOINS V | D25: FALSE | E25: =IF(D25=TRUE,1,0) -> 0 | F25: NOTE 17 - FOURNISSEURS D'EXPLOITATION | I25: TRUE | J25: =IF(I25=TRUE,1,0) -> 1 | K25: NOTE 39 - CHANGEMENTS DE METHODES COMPTABLES, D’ES | M25: FALSE | N25: =IF(M25=TRUE,1,0) -> 0
B27: Dénomination sociale de l'entreprise : | D27: OHADA | K27: N° de caisse sociale :
B29: Sigle usuel : | K29: N° répertoire des entreprises
B31: Agrément prioritaire : | K31: N° Code Importateur :
B33: Forme juridique : | K33: N° de téléphone / Email
B35: Si autre forme juridique préciser | K35: Exercice du :
B37: Désignation de l'activité | K37: Exercice précédent du :
B39: Boîte Postale de l'entreprise : | K39: Date d'arrêt des comptes :
B41: Commune / Quartier : | K41: Année du premier exercice :
B43: Greffe / N° Registre du Commerce | K43: Taux d'imposition BIC / BNC | M43: 0.25
B45: N° Identification fiscale / Télédéclarant: | K45: Taux IMF | M45: 0.005
B47: Regime Fiscal / Centre des Impôts :
B49: Pays Siège social / Code activité principale

Sheet TABLE DE CONVERSION
A1: ="BALANCE A 6 COLONNES DE L'EXERCICE "&TEXT(Sommaire!Q35,"yyyy") -> BALANCE A 6 COLONNES DE L'EXERCICE 1900 | M1: =IF(AND(A3="",A4="",N3="",N4=""),0,1) -> 0 | N1: ="BALANCE A 6 COLONNES DE L'EXERCICE "&TEXT(Sommaire!Q37,"yyyy") -> BALANCE A 6 COLONNES DE L'EXERCICE 1900
A2: ="Veuillez copier et coller en valeur votre balance à 6 colonnes de l'exercice "&TEXT(Sommaire!Q35,"yyyy") -> Veuillez copier et coller en valeur votre balance à 6 colonnes de l'exercice 1900 | N2: ="Veuillez copier et coller en valeur votre balance à 6 colonnes de l'exercice "&TEXT(Sommaire!Q37,"yyyy") -> Veuillez copier et coller en valeur votre balance à 6 colonnes de l'exercice 1900
A3: =IF(COUNTIF(BalanceN[Vérif],"A")=0,"","Veuillez vérifier le numéro de comptes des Lignes surlignés en rouges en tenant compte du plan comptable OHADA Révisé") | N3: =IF(COUNTIF(BalanceN1[Vérif],"A")=0,"","Veuillez vérifier le numéro de comptes des Lignes surlignés en rouges en tenant compte du plan comptable OHADA Révisé")
A4: =IF(AND(COUNTIF(BalanceN[SF],"A")=0,COUNTIF(BalanceN[SI],"A")=0),"","Veuillez corriger l'imputation des comptes des Lignes surlignés en orange (Voir Balance d'entrée et/ou balance sortie)") | N4: =IF(AND(COUNTIF(BalanceN1[SF],"A")=0,COUNTIF(BalanceN1[SI],"A")=0),"","Veuillez corriger l'imputation des comptes des Lignes surlignés en orange (Voir Balance d'entrée et/ou balance sortie)")
A5: =IF(AND(M5=M6,Z5=Z6),"","Balance d'entrée "&TEXT(Sommaire!Q35,"yyyy")&" différent de Balance de sortie "&TEXT(Sommaire!Q37,"yyyy")) | M5: =SUMIFS(BalanceN[BE_Debit],BalanceN[Table],">=10000",BalanceN[Table],"<60000") -> 825656309 | Z5: =SUMIFS(BalanceN[BE_Credit],BalanceN[Table],">=10000",BalanceN[Table],"<60000") -> 825656309
A6: =IF(OR('Table TFT'!B36<>"",'Table TFT'!B37<>"",'Table TFT'!B38<>"",'Table TFT'!B39<>"",'Table TFT'!B40<>"",'Table TFT'!B41<>"",'Table TFT'!B42<>"",'Table TFT'!B43<>""),"Attention, veuillez remplir la Table TFT de l'exercice "&TEXT(Sommaire!Q35,"yyyy"),"") | M6: =IF( SUMIFS(BalanceN1[BS_Credit],BalanceN1[Table],">=60000",BalanceN1[Table],"<90000") >= SUMIFS(BalanceN1[BS_Debit],BalanceN1[Table],">=60000",BalanceN1[Table],"<90000"), SUMIFS(BalanceN1[BS_Debit],BalanceN1[Table],">=10000",BalanceN1[Table],"<60000"), SUMIFS(BalanceN1[BS_Debit],BalanceN1[Table],">=10000",BalanceN1[Table],"<60000") + SUMIFS(BalanceN1[BS_Debit],BalanceN1[Table],">=60000",BalanceN1[Table],"<90000") - SUMIFS(BalanceN1[BS_Credit],BalanceN1[Table],">=60000",BalanceN1[Table],"<90000") ) -> 825656309 | N6: =IF(OR('Table TFT'!K36<>"",'Table TFT'!K37<>"",'Table TFT'!K38<>"",'Table TFT'!K39<>"",'Table TFT'!K40<>"",'Table TFT'!K41<>"",'Table TFT'!K42<>"",'Table TFT'!K43<>""),"Attention, veuillez remplir Attention, veuillez remplir la Table TFT de l'exercice "&TEXT(Sommaire!AD35,"yyyy"),"") | Z6: =IF( SUMIFS(BalanceN1[BS_Credit],BalanceN1[Table],">=60000",BalanceN1[Table],"<90000") >= SUMIFS(BalanceN1[BS_Debit],BalanceN1[Table],">=60000",BalanceN1[Table],"<90000"), SUMIFS(BalanceN1[BS_Credit],BalanceN1[Table],">=10000",BalanceN1[Table],"<60000") + SUMIFS(BalanceN1[BS_Credit],BalanceN1[Table],">=60000",BalanceN1[Table],"<90000") - SUMIFS(BalanceN1[BS_Debit],BalanceN1[Table],">=60000",BalanceN1[Table],"<90000"), SUMIFS(BalanceN1[BS_Credit],BalanceN1[Table],">=10000",BalanceN1[Table],"<60000")) -> 825656309
B7: =IF(AND(C7=D7,E7=F7,G7=H7),"","Attention la balance n'est pas équilibré") | C7: =SUM(BalanceN[BE_Debit]) -> 825656309 | D7: =SUM(BalanceN[BE_Credit]) -> 825656309 | E7: =SUM(BalanceN[Mvt_Debit]) -> 9736437162 | F7: =SUM(BalanceN[Mvt_Credit]) -> 9736437162 | G7: =SUM(BalanceN[BS_Debit]) -> 3382628833 | H7: =SUM(BalanceN[BS_Credit]) -> 3382628833 | O7: =IF(AND(P7=Q7,R7=S7,T7=U7),"","Attention la balance n'est pas équilibré") | P7: =SUM(BalanceN1[BE_Debit]) -> 743900145 | Q7: =SUM(BalanceN1[BE_Credit]) -> 743900145 | R7: =SUM(BalanceN1[Mvt_Debit]) -> 7011264571 | S7: =SUM(BalanceN1[Mvt_Credit]) -> 7011264571 | T7: =SUM(BalanceN1[BS_Debit]) -> 2613872627 | U7: =SUM(BalanceN1[BS_Credit]) -> 2613872627
A8: Compte | B8: Désignation | C8: BE_Debit | D8: BE_Credit | E8: Mvt_Debit | F8: Mvt_Credit | G8: BS_Debit | H8: BS_Credit | I8: Table | J8: Vérif | K8: SI | L8: SF | N8: Compte | O8: Désignation | P8: BE_Debit | Q8: BE_Credit | R8: Mvt_Debit | S8: Mvt_Credit | T8: BS_Debit | U8: BS_Credit | V8: Table | W8: Vérif | X8: SI | Y8: SF
A9: 101100 | B9: Capital souscrit, non appelé | E9: 200000000 | F9: 300000000 | H9: 100000000 | I9: =VALUE(LEFT(BalanceN[[#This Row],[Compte]]&"00000000",5)) -> 10110 | J9: {=IF(BalanceN[[#This Row],[Compte]]="",0,_xlfn.IFNA(INDEX(Plan_Comptable[[Table de Compte]:[Sens]],MATCH(VALUE(LEFT(BalanceN[[#This Row],[Table]],4)),VALUE(Plan_Comptable[Table de Compte]),0),2),"A"))} -> 0 | K9: =IF(AND(BalanceN[[#This Row],[Vérif]]="D",BalanceN[[#This Row],[BS_Credit]]>0),"A",IF(AND(BalanceN[[#This Row],[Vérif]]="C",BalanceN[[#This Row],[BS_Debit]]>0),"A","")) | L9: =IF(AND(BalanceN[[#This Row],[Vérif]]="D",BalanceN[[#This Row],[BE_Credit]]>0),"A",IF(AND(BalanceN[[#This Row],[Vérif]]="C",BalanceN[[#This Row],[BE_Debit]]>0),"A","")) | N9: 101300 | O9: Capital souscrit, appelé, versé, oon amorti | Q9: 100000000 | U9: 100000000 | V9: =VALUE(LEFT(BalanceN1[[#This Row],[Compte]]&"00000000",5)) -> 10130 | W9: {=IF(BalanceN1[[#This Row],[Compte]]="",0,_xlfn.IFNA(INDEX(Plan_Comptable[[Table de Compte]:[Sens]],MATCH(VALUE(LEFT(BalanceN1[[#This Row],[Table]],4)),VALUE(Plan_Comptable[Table de Compte]),0),2),"A"))} -> 0 | X9: =IF(AND(BalanceN1[[#This Row],[Vérif]]="D",BalanceN1[[#This Row],[BS_Credit]]>0),"A",IF(AND(BalanceN1[[#This Row],[Vérif]]="C",BalanceN1[[#This Row],[BS_Debit]]>0),"A","")) | Y9: =IF(AND(BalanceN1[[#This Row],[Vérif]]="D",BalanceN1[[#This Row],[BE_Credit]]>0),"A",IF(AND(BalanceN1[[#This Row],[Vérif]]="C",BalanceN1[[#This Row],[BE_Debit]]>0),"A",""))
A10: 101200 | B10: Capital souscrit, appelé, non versé | E10: 200000000 | F10: 200000000 | I10: =VALUE(LEFT(BalanceN[[#This Row],[Compte]]&"00000000",5)) -> 10120 | J10: {=IF(BalanceN[[#This Row],[Compte]]="",0,_xlfn.IFNA(INDEX(Plan_Comptable[[Table de Compte]:[Sens]],MATCH(VALUE(LEFT(BalanceN[[#This Row],[Table]],4)),VALUE(Plan_Comptable[Table de Compte]),0),2),"A"))} -> 0 | K10: =IF(AND(BalanceN[[#This Row],[Vérif]]="D",BalanceN[[#This Row],[BS_Credit]]>0),"A",IF(AND(BalanceN[[#This Row],[Vérif]]="C",BalanceN[[#This Row],[BS_Debit]]>0),"A","")) | L10: =IF(AND(BalanceN[[#This Row],[Vérif]]="D",BalanceN[[#This Row],[BE_Credit]]>0),"A",IF(AND(BalanceN[[#This Row],[Vérif]]="C",BalanceN[[#This Row],[BE_Debit]]>0),"A","")) | N10: 111000 | O10: Réserve légale | Q10: 20000000 | U10: 20000000 | V10: =VALUE(LEFT(BalanceN1[[#This Row],[Compte]]&"00000000",5)) -> 11100 | W10: {=IF(BalanceN1[[#This Row],[Compte]]="",0,_xlfn.IFNA(INDEX(Plan_Comptable[[Table de Compte]:[Sens]],MATCH(VALUE(LEFT(BalanceN1[[#This Row],[Table]],4)),VALUE(Plan_Comptable[Table de Compte]),0),2),"A"))} -> 0 | X10: =IF(AND(BalanceN1[[#This Row],[Vérif]]="D",BalanceN1[[#This Row],[BS_Credit]]>0),"A",IF(AND(BalanceN1[[#This Row],[Vérif]]="C",BalanceN1[[#This Row],[BS_Debit]]>0),"A","")) | Y10: =IF(AND(BalanceN1[[#This Row],[Vérif]]="D",BalanceN1[[#This Row],[BE_Credit]]>0),"A",IF(AND(BalanceN1[[#This Row],[Vérif]]="C",BalanceN1[[#This Row],[BE_Debit]]>0),"A",""))
A11: 101300 | B11: Capital souscrit, appelé, versé non amorti | D11: 100000000 | F11: 200000000 | H11: 300000000 | I11: =VALUE(LEFT(BalanceN[[#This Row],[Compte]]&"00000000",5)) -> 10130 | J11: {=IF(BalanceN[[#This Row],[Compte]]="",0,_xlfn.IFNA(INDEX(Plan_Comptable[[Table de Compte]:[Sens]],MATCH(VALUE(LEFT(BalanceN[[#This Row],[Table]],4)),VALUE(Plan_Comptable[Table de Compte]),0),2),"A"))} -> 0 | K11: =IF(AND(BalanceN[[#This Row],[Vérif]]="D",BalanceN[[#This Row],[BS_Credit]]>0),"A",IF(AND(BalanceN[[#This Row],[Vérif]]="C",BalanceN[[#This Row],[BS_Debit]]>0),"A","")) | L11: =IF(AND(BalanceN[[#This Row],[Vérif]]="D",BalanceN[[#This Row],[BE_Credit]]>0),"A",IF(AND(BalanceN[[#This Row],[Vérif]]="C",BalanceN[[#This Row],[BE_Debit]]>0),"A","")) | N11: 121 | O11: Report à nouveau | Q11: 20818799 | S11: 26631518 | U11: 47450317 | V11: =VALUE(LEFT(BalanceN1[[#This Row],[Compte]]&"00000000",5)) -> 12100 | W11: {=IF(BalanceN1[[#This Row],[Compte]]="",0,_xlfn.IFNA(INDEX(Plan_Comptable[[Table de Compte]:[Sens]],MATCH(VALUE(LEFT(BalanceN1[[#This Row],[Table]],4)),VALUE(Plan_Comptable[Table de Compte]),0),2),"A"))} -> 0 | X11: =IF(AND(BalanceN1[[#This Row],[Vérif]]="D",BalanceN1[[#This Row],[BS_Credit]]>0),"A",IF(AND(BalanceN1[[#This Row],[Vérif]]="C",BalanceN1[[#This Row],[BS_Debit]]>0),"A","")) | Y11: =IF(AND(BalanceN1[[#This Row],[Vérif]]="D",BalanceN1[[#This Row],[BE_Credit]]>0),"A",IF(AND(BalanceN1[[#This Row],[Vérif]]="C",BalanceN1[[#This Row],[BE_Debit]]>0),"A",""))
A12: 106200 | B12: Ecarts de réévaluation | F12: 3500000 | H12: 3500000 | I12: =VALUE(LEFT(BalanceN[[#This Row],[Compte]]&"00000000",5)) -> 10620 | J12: {=IF(BalanceN[[#This Row],[Compte]]="",0,_xlfn.IFNA(INDEX(Plan_Comptable[[Table de Compte]:[Sens]],MATCH(VALUE(LEFT(BalanceN[[#This Row],[Table]],4)),VALUE(Plan_Comptable[Table de Compte]),0),2),"A"))} -> 0 | K12: =IF(AND(BalanceN[[#This Row],[Vérif]]="D",BalanceN[[#This Row],[BS_Credit]]>0),"A",IF(AND(BalanceN[[#This Row],[Vérif]]="C",BalanceN[[#This Row],[BS_Debit]]>0),"A","")) | L12: =IF(AND(BalanceN[[#This Row],[Vérif]]="D",BalanceN[[#This Row],[BE_Credit]]>0),"A",IF(AND(BalanceN[[#This Row],[Vérif]]="C",BalanceN[[#This Row],[BE_Debit]]>0),"A","")) | N12: 131000 | O12: Résultat net | Q12: 66631518 | R12: 66631518 | V12: =VALUE(LEFT(BalanceN1[[#This Row],[Compte]]&"00000000",5)) -> 13100 | W12: {=IF(BalanceN1[[#This Row],[Compte]]="",0,_xlfn.IFNA(INDEX(Plan_Comptable[[Table de Compte]:[Sens]],MATCH(VALUE(LEFT(BalanceN1[[#This Row],[Table]],4)),VALUE(Plan_Comptable[Table de Compte]),0),2),"A"))} -> 0 | X12: =IF(AND(BalanceN1[[#This Row],[Vérif]]="D",BalanceN1[[#This Row],[BS_Credit]]>0),"A",IF(AND(BalanceN1[[#This Row],[Vérif]]="C",BalanceN1[[#This Row],[BS_Debit]]>0),"A","")) | Y12: =IF(AND(BalanceN1[[#This Row],[Vérif]]="D",BalanceN1[[#This Row],[BE_Credit]]>0),"A",IF(AND(BalanceN1[[#This Row],[Vérif]]="C",BalanceN1[[#This Row],[BE_Debit]]>0),"A",""))
A13: 109000 | B13: Apporteurs, capital souscrit, non appelé | E13: 300000000 | F13: 200000000 | G13: 100000000 | I13: =VALUE(LEFT(BalanceN[[#This Row],[Compte]]&"00000000",5)) -> 10900 | J13: {=IF(BalanceN[[#This Row],[Compte]]="",0,_xlfn.IFNA(INDEX(Plan_Comptable[[Table de Compte]:[Sens]],MATCH(VALUE(LEFT(BalanceN[[#This Row],[Table]],4)),VALUE(Plan_Comptable[Table de Compte]),0),2),"A"))} -> 0 | K13: =IF(AND(BalanceN[[#This Row],[Vérif]]="D",BalanceN[[#This Row],[BS_Credit]]>0),"A",IF(AND(BalanceN[[#This Row],[Vérif]]="C",BalanceN[[#This Row],[BS_Debit]]>0),"A","")) | L13: =IF(AND(BalanceN[[#This Row],[Vérif]]="D",BalanceN[[#This Row],[BE_Credit]]>0),"A",IF(AND(BalanceN[[#This Row],[Vérif]]="C",BalanceN[[#This Row],[BE_Debit]]>0),"A","")) | N13: 165200 | O13: Cau.tionoemeots reçus | Q13: 2200000 | U13: 2200000 | V13: =VALUE(LEFT(BalanceN1[[#This Row],[Compte]]&"00000000",5)) -> 16520 | W13: {=IF(BalanceN1[[#This Row],[Compte]]="",0,_xlfn.IFNA(INDEX(Plan_Comptable[[Table de Compte]:[Sens]],MATCH(VALUE(LEFT(BalanceN1[[#This Row],[Table]],4)),VALUE(Plan_Comptable[Table de Compte]),0),2),"A"))} -> 0 | X13: =IF(AND(BalanceN1[[#This Row],[Vérif]]="D",BalanceN1[[#This Row],[BS_Credit]]>0),"A",IF(AND(BalanceN1[[#This Row],[Vérif]]="C",BalanceN1[[#This Row],[BS_Debit]]>0),"A","")) | Y13: =IF(AND(BalanceN1[[#This Row],[Vérif]]="D",BalanceN1[[#This Row],[BE_Credit]]>0),"A",IF(AND(BalanceN1[[#This Row],[Vérif]]="C",BalanceN1[[#This Row],[BE_Debit]]>0),"A",""))
A14: 111000 | B14: Réserve légale | D14: 20000000 | H14: 20000000 | I14: =VALUE(LEFT(BalanceN[[#This Row],[Compte]]&"00000000",5)) -> 11100 | J14: {=IF(BalanceN[[#This Row],[Compte]]="",0,_xlfn.IFNA(INDEX(Plan_Comptable[[Table de Compte]:[Sens]],MATCH(VALUE(LEFT(BalanceN[[#This Row],[Table]],4)),VALUE(Plan_Comptable[Table de Compte]),0),2),"A"))} -> 0 | K14: =IF(AND(BalanceN[[#This Row],[Vérif]]="D",BalanceN[[#This Row],[BS_Credit]]>0),"A",IF(AND(BalanceN[[#This Row],[Vérif]]="C",BalanceN[[#This Row],[BS_Debit]]>0),"A","")) | L14: =IF(AND(BalanceN[[#This Row],[Vérif]]="D",BalanceN[[#This Row],[BE_Credit]]>0),"A",IF(AND(BalanceN[[#This Row],[Vérif]]="C",BalanceN[[#This Row],[BE_Debit]]>0),"A","")) | N14: 196100 | O14: Provision pour pensions et obligations assimilées | Q14: 47553935 | R14: 3771900 | S14: 11082662 | U14: 54864697 | V14: =VALUE(LEFT(BalanceN1[[#This Row],[Compte]]&"00000000",5)) -> 19610 | W14: {=IF(BalanceN1[[#This Row],[Compte]]="",0,_xlfn.IFNA(INDEX(Plan_Comptable[[Table de Compte]:[Sens]],MATCH(VALUE(LEFT(BalanceN1[[#This Row],[Table]],4)),VALUE(Plan_Comptable[Table de Compte]),0),2),"A"))} -> 0 | X14: =IF(AND(BalanceN1[[#This Row],[Vérif]]="D",BalanceN1[[#This Row],[BS_Credit]]>0),"A",IF(AND(BalanceN1[[#This Row],[Vérif]]="C",BalanceN1[[#This Row],[BS_Debit]]>0),"A","")) | Y14: =IF(AND(BalanceN1[[#This Row],[Vérif]]="D",BalanceN1[[#This Row],[BE_Credit]]>0),"A",IF(AND(BalanceN1[[#This Row],[Vérif]]="C",BalanceN1[[#This Row],[BE_Debit]]>0),"A",""))
A15: 121 | B15: Report à nouveau | D15: 47450317 | E15: 90000000 | F15: 118619674 | H15: 76069991 | I15: =VALUE(LEFT(BalanceN[[#This Row],[Compte]]&"00000000",5)) -> 12100 | J15: {=IF(BalanceN[[#This Row],[Compte]]="",0,_xlfn.IFNA(INDEX(Plan_Comptable[[Table de Compte]:[Sens]],MATCH(VALUE(LEFT(BalanceN[[#This Row],[Table]],4)),VALUE(Plan_Comptable[Table de Compte]),0),2),"A"))} -> 0 | K15: =IF(AND(BalanceN[[#This Row],[Vérif]]="D",BalanceN[[#This Row],[BS_Credit]]>0),"A",IF(AND(BalanceN[[#This Row],[Vérif]]="C",BalanceN[[#This Row],[BS_Debit]]>0),"A","")) | L15: =IF(AND(BalanceN[[#This Row],[Vérif]]="D",BalanceN[[#This Row],[BE_Credit]]>0),"A",IF(AND(BalanceN[[#This Row],[Vérif]]="C",BalanceN[[#This Row],[BE_Debit]]>0),"A","")) | N15: 2131 | O15: Logiciels | P15: 1050000 | T15: 1050000 | V15: =VALUE(LEFT(BalanceN1[[#This Row],[Compte]]&"00000000",5)) -> 21310 | W15: {=IF(BalanceN1[[#This Row],[Compte]]="",0,_xlfn.IFNA(INDEX(Plan_Comptable[[Table de Compte]:[Sens]],MATCH(VALUE(LEFT(BalanceN1[[#This Row],[Table]],4)),VALUE(Plan_Comptable[Table de Compte]),0),2),"A"))} -> D | X15: =IF(AND(BalanceN1[[#This Row],[Vérif]]="D",BalanceN1[[#This Row],[BS_Credit]]>0),"A",IF(AND(BalanceN1[[#This Row],[Vérif]]="C",BalanceN1[[#This Row],[BS_Debit]]>0),"A","")) | Y15: =IF(AND(BalanceN1[[#This Row],[Vérif]]="D",BalanceN1[[#This Row],[BE_Credit]]>0),"A",IF(AND(BalanceN1[[#This Row],[Vérif]]="C",BalanceN1[[#This Row],[BE_Debit]]>0),"A",""))
A16: 131000 | B16: Résultat net | D16: 118619674 | E16: 118619674 | I16: =VALUE(LEFT(BalanceN[[#This Row],[Compte]]&"00000000",5)) -> 13100 | J16: {=IF(BalanceN[[#This Row],[Compte]]="",0,_xlfn.IFNA(INDEX(Plan_Comptable[[Table de Compte]:[Sens]],MATCH(VALUE(LEFT(BalanceN[[#This Row],[Table]],4)),VALUE(Plan_Comptable[Table de Compte]),0),2),"A"))} -> 0 | K16: =IF(AND(BalanceN[[#This Row],[Vérif]]="D",BalanceN[[#This Row],[BS_Credit]]>0),"A",IF(AND(BalanceN[[#This Row],[Vérif]]="C",BalanceN[[#This Row],[BS_Debit]]>0),"A","")) | L16: =IF(AND(BalanceN[[#This Row],[Vérif]]="D",BalanceN[[#This Row],[BE_Credit]]>0),"A",IF(AND(BalanceN[[#This Row],[Vérif]]="C",BalanceN[[#This Row],[BE_Debit]]>0),"A","")) | N16: 215000 | O16: Fonds commercial | P16: 1600000 | T16: 1600000 | V16: =VALUE(LEFT(BalanceN1[[#This Row],[Compte]]&"00000000",5)) -> 21500 | W16: {=IF(BalanceN1[[#This Row],[Compte]]="",0,_xlfn.IFNA(INDEX(Plan_Comptable[[Table de Compte]:[Sens]],MATCH(VALUE(LEFT(BalanceN1[[#This Row],[Table]],4)),VALUE(Plan_Comptable[Table de Compte]),0),2),"A"))} -> D | X16: =IF(AND(BalanceN1[[#This Row],[Vérif]]="D",BalanceN1[[#This Row],[BS_Credit]]>0),"A",IF(AND(BalanceN1[[#This Row],[Vérif]]="C",BalanceN1[[#This Row],[BS_Debit]]>0),"A","")) | Y16: =IF(AND(BalanceN1[[#This Row],[Vérif]]="D",BalanceN1[[#This Row],[BE_Credit]]>0),"A",IF(AND(BalanceN1[[#This Row],[Vérif]]="C",BalanceN1[[#This Row],[BE_Debit]]>0),"A",""))
A17: 141600 | B17: Subvention d'investissement | F17: 2000000 | H17: 2000000 | I17: =VALUE(LEFT(BalanceN[[#This Row],[Compte]]&"00000000",5)) -> 14160 | J17: {=IF(BalanceN[[#This Row],[Compte]]="",0,_xlfn.IFNA(INDEX(Plan_Comptable[[Table de Compte]:[Sens]],MATCH(VALUE(LEFT(BalanceN[[#This Row],[Table]],4)),VALUE(Plan_Comptable[Table de Compte]),0),2),"A"))} -> 0 | K17: =IF(AND(BalanceN[[#This Row],[Vérif]]="D",BalanceN[[#This Row],[BS_Credit]]>0),"A",IF(AND(BalanceN[[#This Row],[Vérif]]="C",BalanceN[[#This Row],[BS_Debit]]>0),"A","")) | L17: =IF(AND(BalanceN[[#This Row],[Vérif]]="D",BalanceN[[#This Row],[BE_Credit]]>0),"A",IF(AND(BalanceN[[#This Row],[Vérif]]="C",BalanceN[[#This Row],[BE_Debit]]>0),"A","")) | N17: 2231 | O17: Terrains bâtis | P17: 12500000 | T17: 12500000 | V17: =VALUE(LEFT(BalanceN1[[#This Row],[Compte]]&"00000000",5)) -> 22310 | W17: {=IF(BalanceN1[[#This Row],[Compte]]="",0,_xlfn.IFNA(INDEX(Plan_Comptable[[Table de Compte]:[Sens]],MATCH(VALUE(LEFT(BalanceN1[[#This Row],[Table]],4)),VALUE(Plan_Comptable[Table de Compte]),0),2),"A"))} -> D | X17: =IF(AND(BalanceN1[[#This Row],[Vérif]]="D",BalanceN1[[#This Row],[BS_Credit]]>0),"A",IF(AND(BalanceN1[[#This Row],[Vérif]]="C",BalanceN1[[#This Row],[BS_Debit]]>0),"A","")) | Y17: =IF(AND(BalanceN1[[#This Row],[Vérif]]="D",BalanceN1[[#This Row],[BE_Credit]]>0),"A",IF(AND(BalanceN1[[#This Row],[Vérif]]="C",BalanceN1[[#This Row],[BE_Debit]]>0),"A",""))
A18: 154000 | B18: Provisions spéciales de réévaluation | F18: 40000000 | H18: 40000000 | I18: =VALUE(LEFT(BalanceN[[#This Row],[Compte]]&"00000000",5)) -> 15400 | J18: {=IF(BalanceN[[#This Row],[Compte]]="",0,_xlfn.IFNA(INDEX(Plan_Comptable[[Table de Compte]:[Sens]],MATCH(VALUE(LEFT(BalanceN[[#This Row],[Table]],4)),VALUE(Plan_Comptable[Table de Compte]),0),2),"A"))} -> 0 | K18: =IF(AND(BalanceN[[#This Row],[Vérif]]="D",BalanceN[[#This Row],[BS_Credit]]>0),"A",IF(AND(BalanceN[[#This Row],[Vérif]]="C",BalanceN[[#This Row],[BS_Debit]]>0),"A","")) | L18: =IF(AND(BalanceN[[#This Row],[Vérif]]="D",BalanceN[[#This Row],[BE_Credit]]>0),"A",IF(AND(BalanceN[[#This Row],[Vérif]]="C",BalanceN[[#This Row],[BE_Debit]]>0),"A","")) | N18: 2298 | O18: Aménagement de terraio en cours | P18: 22673950 | T18: 22673950 | V18: =VALUE(LEFT(BalanceN1[[#This Row],[Compte]]&"00000000",5)) -> 22980 | W18: {=IF(BalanceN1[[#This Row],[Compte]]="",0,_xlfn.IFNA(INDEX(Plan_Comptable[[Table de Compte]:[Sens]],MATCH(VALUE(LEFT(BalanceN1[[#This Row],[Table]],4)),VALUE(Plan_Comptable[Table de Compte]),0),2),"A"))} -> D | X18: =IF(AND(BalanceN1[[#This Row],[Vérif]]="D",BalanceN1[[#This Row],[BS_Credit]]>0),"A",IF(AND(BalanceN1[[#This Row],[Vérif]]="C",BalanceN1[[#This Row],[BS_Debit]]>0),"A","")) | Y18: =IF(AND(BalanceN1[[#This Row],[Vérif]]="D",BalanceN1[[#This Row],[BE_Credit]]>0),"A",IF(AND(BalanceN1[[#This Row],[Vérif]]="C",BalanceN1[[#This Row],[BE_Debit]]>0),"A",""))
A19: 162000 | B19: Emprunt bancaire | E19: 7500925 | F19: 100000000 | H19: 92499075 | I19: =VALUE(LEFT(BalanceN[[#This Row],[Compte]]&"00000000",5)) -> 16200 | J19: {=IF(BalanceN[[#This Row],[Compte]]="",0,_xlfn.IFNA(INDEX(Plan_Comptable[[Table de Compte]:[Sens]],MATCH(VALUE(LEFT(BalanceN[[#This Row],[Table]],4)),VALUE(Plan_Comptable[Table de Compte]),0),2),"A"))} -> 0 | K19: =IF(AND(BalanceN[[#This Row],[Vérif]]="D",BalanceN[[#This Row],[BS_Credit]]>0),"A",IF(AND(BalanceN[[#This Row],[Vérif]]="C",BalanceN[[#This Row],[BS_Debit]]>0),"A","")) | L19: =IF(AND(BalanceN[[#This Row],[Vérif]]="D",BalanceN[[#This Row],[BE_Credit]]>0),"A",IF(AND(BalanceN[[#This Row],[Vérif]]="C",BalanceN[[#This Row],[BE_Debit]]>0),"A","")) | N19: 231100 | O19: Bâtiments industriels sur sol propre | P19: 55000000 | T19: 55000000 | V19: =VALUE(LEFT(BalanceN1[[#This Row],[Compte]]&"00000000",5)) -> 23110 | W19: {=IF(BalanceN1[[#This Row],[Compte]]="",0,_xlfn.IFNA(INDEX(Plan_Comptable[[Table de Compte]:[Sens]],MATCH(VALUE(LEFT(BalanceN1[[#This Row],[Table]],4)),VALUE(Plan_Comptable[Table de Compte]),0),2),"A"))} -> D | X19: =IF(AND(BalanceN1[[#This Row],[Vérif]]="D",BalanceN1[[#This Row],[BS_Credit]]>0),"A",IF(AND(BalanceN1[[#This Row],[Vérif]]="C",BalanceN1[[#This Row],[BS_Debit]]>0),"A","")) | Y19: =IF(AND(BalanceN1[[#This Row],[Vérif]]="D",BalanceN1[[#This Row],[BE_Credit]]>0),"A",IF(AND(BalanceN1[[#This Row],[Vérif]]="C",BalanceN1[[#This Row],[BE_Debit]]>0),"A",""))
A20: 165200 | B20: Cautionnements reçus | D20: 2200000 | H20: 2200000 | I20: =VALUE(LEFT(BalanceN[[#This Row],[Compte]]&"00000000",5)) -> 16520 | J20: {=IF(BalanceN[[#This Row],[Compte]]="",0,_xlfn.IFNA(INDEX(Plan_Comptable[[Table de Compte]:[Sens]],MATCH(VALUE(LEFT(BalanceN[[#This Row],[Table]],4)),VALUE(Plan_Comptable[Table de Compte]),0),2),"A"))} -> 0 | K20: =IF(AND(BalanceN[[#This Row],[Vérif]]="D",BalanceN[[#This Row],[BS_Credit]]>0),"A",IF(AND(BalanceN[[#This Row],[Vérif]]="C",BalanceN[[#This Row],[BS_Debit]]>0),"A","")) | L20: =IF(AND(BalanceN[[#This Row],[Vérif]]="D",BalanceN[[#This Row],[BE_Credit]]>0),"A",IF(AND(BalanceN[[#This Row],[Vérif]]="C",BalanceN[[#This Row],[BE_Debit]]>0),"A","")) | N20: 232100 | O20: Bâtiments industriels sur sol d'autrui | P20: 231411100 | T20: 231411100 | V20: =VALUE(LEFT(BalanceN1[[#This Row],[Compte]]&"00000000",5)) -> 23210 | W20: {=IF(BalanceN1[[#This Row],[Compte]]="",0,_xlfn.IFNA(INDEX(Plan_Comptable[[Table de Compte]:[Sens]],MATCH(VALUE(LEFT(BalanceN1[[#This Row],[Table]],4)),VALUE(Plan_Comptable[Table de Compte]),0),2),"A"))} -> D | X20: =IF(AND(BalanceN1[[#This Row],[Vérif]]="D",BalanceN1[[#This Row],[BS_Credit]]>0),"A",IF(AND(BalanceN1[[#This Row],[Vérif]]="C",BalanceN1[[#This Row],[BS_Debit]]>0),"A","")) | Y20: =IF(AND(BalanceN1[[#This Row],[Vérif]]="D",BalanceN1[[#This Row],[BE_Credit]]>0),"A",IF(AND(BalanceN1[[#This Row],[Vérif]]="C",BalanceN1[[#This Row],[BE_Debit]]>0),"A",""))
A21: 196100 | B21: Provisions pour pensions et obligations similaires | D21: 54864697 | E21: 6701530 | F21: 13953199 | H21: 62116366 | I21: =VALUE(LEFT(BalanceN[[#This Row],[Compte]]&"00000000",5)) -> 19610 | J21: {=IF(BalanceN[[#This Row],[Compte]]="",0,_xlfn.IFNA(INDEX(Plan_Comptable[[Table de Compte]:[Sens]],MATCH(VALUE(LEFT(BalanceN[[#This Row],[Table]],4)),VALUE(Plan_Comptable[Table de Compte]),0),2),"A"))} -> 0 | K21: =IF(AND(BalanceN[[#This Row],[Vérif]]="D",BalanceN[[#This Row],[BS_Credit]]>0),"A",IF(AND(BalanceN[[#This Row],[Vérif]]="C",BalanceN[[#This Row],[BS_Debit]]>0),"A","")) | L21: =IF(AND(BalanceN[[#This Row],[Vérif]]="D",BalanceN[[#This Row],[BE_Credit]]>0),"A",IF(AND(BalanceN[[#This Row],[Vérif]]="C",BalanceN[[#This Row],[BE_Debit]]>0),"A","")) | N21: 235100 | O21: Installatioos générales | P21: 60263648 | T21: 60263648 | V21: =VALUE(LEFT(BalanceN1[[#This Row],[Compte]]&"00000000",5)) -> 23510 | W21: {=IF(BalanceN1[[#This Row],[Compte]]="",0,_xlfn.IFNA(INDEX(Plan_Comptable[[Table de Compte]:[Sens]],MATCH(VALUE(LEFT(BalanceN1[[#This Row],[Table]],4)),VALUE(Plan_Comptable[Table de Compte]),0),2),"A"))} -> D | X21: =IF(AND(BalanceN1[[#This Row],[Vérif]]="D",BalanceN1[[#This Row],[BS_Credit]]>0),"A",IF(AND(BalanceN1[[#This Row],[Vérif]]="C",BalanceN1[[#This Row],[BS_Debit]]>0),"A","")) | Y21: =IF(AND(BalanceN1[[#This Row],[Vérif]]="D",BalanceN1[[#This Row],[BE_Credit]]>0),"A",IF(AND(BalanceN1[[#This Row],[Vérif]]="C",BalanceN1[[#This Row],[BE_Debit]]>0),"A",""))
A22: 2131 | B22: Logiciels | C22: 1050000 | E22: 2000000 | G22: 3050000 | I22: =VALUE(LEFT(BalanceN[[#This Row],[Compte]]&"00000000",5)) -> 21310 | J22: {=IF(BalanceN[[#This Row],[Compte]]="",0,_xlfn.IFNA(INDEX(Plan_Comptable[[Table de Compte]:[Sens]],MATCH(VALUE(LEFT(BalanceN[[#This Row],[Table]],4)),VALUE(Plan_Comptable[Table de Compte]),0),2),"A"))} -> D | K22: =IF(AND(BalanceN[[#This Row],[Vérif]]="D",BalanceN[[#This Row],[BS_Credit]]>0),"A",IF(AND(BalanceN[[#This Row],[Vérif]]="C",BalanceN[[#This Row],[BS_Debit]]>0),"A","")) | L22: =IF(AND(BalanceN[[#This Row],[Vérif]]="D",BalanceN[[#This Row],[BE_Credit]]>0),"A",IF(AND(BalanceN[[#This Row],[Vérif]]="C",BalanceN[[#This Row],[BE_Debit]]>0),"A","")) | N22: 238000 | O22: Autres installations et agencements | P22: 11064619 | T22: 11064619 | V22: =VALUE(LEFT(BalanceN1[[#This Row],[Compte]]&"00000000",5)) -> 23800 | W22: {=IF(BalanceN1[[#This Row],[Compte]]="",0,_xlfn.IFNA(INDEX(Plan_Comptable[[Table de Compte]:[Sens]],MATCH(VALUE(LEFT(BalanceN1[[#This Row],[Table]],4)),VALUE(Plan_Comptable[Table de Compte]),0),2),"A"))} -> D | X22: =IF(AND(BalanceN1[[#This Row],[Vérif]]="D",BalanceN1[[#This Row],[BS_Credit]]>0),"A",IF(AND(BalanceN1[[#This Row],[Vérif]]="C",BalanceN1[[#This Row],[BS_Debit]]>0),"A","")) | Y22: =IF(AND(BalanceN1[[#This Row],[Vérif]]="D",BalanceN1[[#This Row],[BE_Credit]]>0),"A",IF(AND(BalanceN1[[#This Row],[Vérif]]="C",BalanceN1[[#This Row],[BE_Debit]]>0),"A",""))
A23: 215000 | B23: Fonds commercial | C23: 1600000 | G23: 1600000 | I23: =VALUE(LEFT(BalanceN[[#This Row],[Compte]]&"00000000",5)) -> 21500 | J23: {=IF(BalanceN[[#This Row],[Compte]]="",0,_xlfn.IFNA(INDEX(Plan_Comptable[[Table de Compte]:[Sens]],MATCH(VALUE(LEFT(BalanceN[[#This Row],[Table]],4)),VALUE(Plan_Comptable[Table de Compte]),0),2),"A"))} -> D | K23: =IF(AND(BalanceN[[#This Row],[Vérif]]="D",BalanceN[[#This Row],[BS_Credit]]>0),"A",IF(AND(BalanceN[[#This Row],[Vérif]]="C",BalanceN[[#This Row],[BS_Debit]]>0),"A","")) | L23: =IF(AND(BalanceN[[#This Row],[Vérif]]="D",BalanceN[[#This Row],[BE_Credit]]>0),"A",IF(AND(BalanceN[[#This Row],[Vérif]]="C",BalanceN[[#This Row],[BE_Debit]]>0),"A","")) | N23: 241100 | O23: Matériel industriel | P23: 74507291 | R23: 17153112 | S23: 350000 | T23: 91310403 | V23: =VALUE(LEFT(BalanceN1[[#This Row],[Compte]]&"00000000",5)) -> 24110 | W23: {=IF(BalanceN1[[#This Row],[Compte]]="",0,_xlfn.IFNA(INDEX(Plan_Comptable[[Table de Compte]:[Sens]],MATCH(VALUE(LEFT(BalanceN1[[#This Row],[Table]],4)),VALUE(Plan_Comptable[Table de Compte]),0),2),"A"))} -> D | X23: =IF(AND(BalanceN1[[#This Row],[Vérif]]="D",BalanceN1[[#This Row],[BS_Credit]]>0),"A",IF(AND(BalanceN1[[#This Row],[Vérif]]="C",BalanceN1[[#This Row],[BS_Debit]]>0),"A","")) | Y23: =IF(AND(BalanceN1[[#This Row],[Vérif]]="D",BalanceN1[[#This Row],[BE_Credit]]>0),"A",IF(AND(BalanceN1[[#This Row],[Vérif]]="C",BalanceN1[[#This Row],[BE_Debit]]>0),"A",""))
A24: 2231 | B24: Terrains bâtis | C24: 12500000 | E24: 3500000 | G24: 16000000 | I24: =VALUE(LEFT(BalanceN[[#This Row],[Compte]]&"00000000",5)) -> 22310 | J24: {=IF(BalanceN[[#This Row],[Compte]]="",0,_xlfn.IFNA(INDEX(Plan_Comptable[[Table de Compte]:[Sens]],MATCH(VALUE(LEFT(BalanceN[[#This Row],[Table]],4)),VALUE(Plan_Comptable[Table de Compte]),0),2),"A"))} -> D | K24: =IF(AND(BalanceN[[#This Row],[Vérif]]="D",BalanceN[[#This Row],[BS_Credit]]>0),"A",IF(AND(BalanceN[[#This Row],[Vérif]]="C",BalanceN[[#This Row],[BS_Debit]]>0),"A","")) | L24: =IF(AND(BalanceN[[#This Row],[Vérif]]="D",BalanceN[[#This Row],[BE_Credit]]>0),"A",IF(AND(BalanceN[[#This Row],[Vérif]]="C",BalanceN[[#This Row],[BE_Debit]]>0),"A","")) | N24: 244100 | O24: Matériel de bureau | P24: 1325000 | T24: 1325000 | V24: =VALUE(LEFT(BalanceN1[[#This Row],[Compte]]&"00000000",5)) -> 24410 | W24: {=IF(BalanceN1[[#This Row],[Compte]]="",0,_xlfn.IFNA(INDEX(Plan_Comptable[[Table de Compte]:[Sens]],MATCH(VALUE(LEFT(BalanceN1[[#This Row],[Table]],4)),VALUE(Plan_Comptable[Table de Compte]),0),2),"A"))} -> D | X24: =IF(AND(BalanceN1[[#This Row],[Vérif]]="D",BalanceN1[[#This Row],[BS_Credit]]>0),"A",IF(AND(BalanceN1[[#This Row],[Vérif]]="C",BalanceN1[[#This Row],[BS_Debit]]>0),"A","")) | Y24: =IF(AND(BalanceN1[[#This Row],[Vérif]]="D",BalanceN1[[#This Row],[BE_Credit]]>0),"A",IF(AND(BalanceN1[[#This Row],[Vérif]]="C",BalanceN1[[#This Row],[BE_Debit]]>0),"A",""))
A25: 2298 | B25: Aménagement de terrain en cours | C25: 22673950 | G25: 22673950 | I25: =VALUE(LEFT(BalanceN[[#This Row],[Compte]]&"00000000",5)) -> 22980 | J25: {=IF(BalanceN[[#This Row],[Compte]]="",0,_xlfn.IFNA(INDEX(Plan_Comptable[[Table de Compte]:[Sens]],MATCH(VALUE(LEFT(BalanceN[[#This Row],[Table]],4)),VALUE(Plan_Comptable[Table de Compte]),0),2),"A"))} -> D | K25: =IF(AND(BalanceN[[#This Row],[Vérif]]="D",BalanceN[[#This Row],[BS_Credit]]>0),"A",IF(AND(BalanceN[[#This Row],[Vérif]]="C",BalanceN[[#This Row],[BS_Debit]]>0),"A","")) | L25: =IF(AND(BalanceN[[#This Row],[Vérif]]="D",BalanceN[[#This Row],[BE_Credit]]>0),"A",IF(AND(BalanceN[[#This Row],[Vérif]]="C",BalanceN[[#This Row],[BE_Debit]]>0),"A","")) | N25: 244200 | O25: Matériel infonnatique | P25: 6867703 | T25: 6867703 | V25: =VALUE(LEFT(BalanceN1[[#This Row],[Compte]]&"00000000",5)) -> 24420 | W25: {=IF(BalanceN1[[#This Row],[Compte]]="",0,_xlfn.IFNA(INDEX(Plan_Comptable[[Table de Compte]:[Sens]],MATCH(VALUE(LEFT(BalanceN1[[#This Row],[Table]],4)),VALUE(Plan_Comptable[Table de Compte]),0),2),"A"))} -> D | X25: =IF(AND(BalanceN1[[#This Row],[Vérif]]="D",BalanceN1[[#This Row],[BS_Credit]]>0),"A",IF(AND(BalanceN1[[#This Row],[Vérif]]="C",BalanceN1[[#This Row],[BS_Debit]]>0),"A","")) | Y25: =IF(AND(BalanceN1[[#This Row],[Vérif]]="D",BalanceN1[[#This Row],[BE_Credit]]>0),"A",IF(AND(BalanceN1[[#This Row],[Vérif]]="C",BalanceN1[[#This Row],[BE_Debit]]>0),"A",""))
A26: 231100 | B26: Bâtiments industriels sur sol propre | C26: 55000000 | E26: 23000000 | G26: 78000000 | I26: =VALUE(LEFT(BalanceN[[#This Row],[Compte]]&"00000000",5)) -> 23110 | J26: {=IF(BalanceN[[#This Row],[Compte]]="",0,_xlfn.IFNA(INDEX(Plan_Comptable[[Table de Compte]:[Sens]],MATCH(VALUE(LEFT(BalanceN[[#This Row],[Table]],4)),VALUE(Plan_Comptable[Table de Compte]),0),2),"A"))} -> D | K26: =IF(AND(BalanceN[[#This Row],[Vérif]]="D",BalanceN[[#This Row],[BS_Credit]]>0),"A",IF(AND(BalanceN[[#This Row],[Vérif]]="C",BalanceN[[#This Row],[BS_Debit]]>0),"A","")) | L26: =IF(AND(BalanceN[[#This Row],[Vérif]]="D",BalanceN[[#This Row],[BE_Credit]]>0),"A",IF(AND(BalanceN[[#This Row],[Vérif]]="C",BalanceN[[#This Row],[BE_Debit]]>0),"A","")) | N26: 244400 | O26: Mobilier de bureau | P26: 4968900 | T26: 4968900 | V26: =VALUE(LEFT(BalanceN1[[#This Row],[Compte]]&"00000000",5)) -> 24440 | W26: {=IF(BalanceN1[[#This Row],[Compte]]="",0,_xlfn.IFNA(INDEX(Plan_Comptable[[Table de Compte]:[Sens]],MATCH(VALUE(LEFT(BalanceN1[[#This Row],[Table]],4)),VALUE(Plan_Comptable[Table de Compte]),0),2),"A"))} -> D | X26: =IF(AND(BalanceN1[[#This Row],[Vérif]]="D",BalanceN1[[#This Row],[BS_Credit]]>0),"A",IF(AND(BalanceN1[[#This Row],[Vérif]]="C",BalanceN1[[#This Row],[BS_Debit]]>0),"A","")) | Y26: =IF(AND(BalanceN1[[#This Row],[Vérif]]="D",BalanceN1[[#This Row],[BE_Credit]]>0),"A",IF(AND(BalanceN1[[#This Row],[Vérif]]="C",BalanceN1[[#This Row],[BE_Debit]]>0),"A",""))
A27: 232100 | B27: Bâtiments industriels sur sol d'autrui | C27: 231411100 | E27: 432000000 | G27: 663411100 | I27: =VALUE(LEFT(BalanceN[[#This Row],[Compte]]&"00000000",5)) -> 23210 | J27: {=IF(BalanceN[[#This Row],[Compte]]="",0,_xlfn.IFNA(INDEX(Plan_Comptable[[Table de Compte]:[Sens]],MATCH(VALUE(LEFT(BalanceN[[#This Row],[Table]],4)),VALUE(Plan_Comptable[Table de Compte]),0),2),"A"))} -> D | K27: =IF(AND(BalanceN[[#This Row],[Vérif]]="D",BalanceN[[#This Row],[BS_Credit]]>0),"A",IF(AND(BalanceN[[#This Row],[Vérif]]="C",BalanceN[[#This Row],[BS_Debit]]>0),"A","")) | L27: =IF(AND(BalanceN[[#This Row],[Vérif]]="D",BalanceN[[#This Row],[BE_Credit]]>0),"A",IF(AND(BalanceN[[#This Row],[Vérif]]="C",BalanceN[[#This Row],[BE_Debit]]>0),"A","")) | N27: 245100 | O27: Matériel automobile | P27: 54050000 | T27: 54050000 | V27: =VALUE(LEFT(BalanceN1[[#This Row],[Compte]]&"00000000",5)) -> 24510 | W27: {=IF(BalanceN1[[#This Row],[Compte]]="",0,_xlfn.IFNA(INDEX(Plan_Comptable[[Table de Compte]:[Sens]],MATCH(VALUE(LEFT(BalanceN1[[#This Row],[Table]],4)),VALUE(Plan_Comptable[Table de Compte]),0),2),"A"))} -> D | X27: =IF(AND(BalanceN1[[#This Row],[Vérif]]="D",BalanceN1[[#This Row],[BS_Credit]]>0),"A",IF(AND(BalanceN1[[#This Row],[Vérif]]="C",BalanceN1[[#This Row],[BS_Debit]]>0),"A","")) | Y27: =IF(AND(BalanceN1[[#This Row],[Vérif]]="D",BalanceN1[[#This Row],[BE_Credit]]>0),"A",IF(AND(BalanceN1[[#This Row],[Vérif]]="C",BalanceN1[[#This Row],[BE_Debit]]>0),"A",""))
A28: 235100 | B28: Installations générales | C28: 60263648 | E28: 1000000 | G28: 61263648 | I28: =VALUE(LEFT(BalanceN[[#This Row],[Compte]]&"00000000",5)) -> 23510 | J28: {=IF(BalanceN[[#This Row],[Compte]]="",0,_xlfn.IFNA(INDEX(Plan_Comptable[[Table de Compte]:[Sens]],MATCH(VALUE(LEFT(BalanceN[[#This Row],[Table]],4)),VALUE(Plan_Comptable[Table de Compte]),0),2),"A"))} -> D | K28: =IF(AND(BalanceN[[#This Row],[Vérif]]="D",BalanceN[[#This Row],[BS_Credit]]>0),"A",IF(AND(BalanceN[[#This Row],[Vérif]]="C",BalanceN[[#This Row],[BS_Debit]]>0),"A","")) | L28: =IF(AND(BalanceN[[#This Row],[Vérif]]="D",BalanceN[[#This Row],[BE_Credit]]>0),"A",IF(AND(BalanceN[[#This Row],[Vérif]]="C",BalanceN[[#This Row],[BE_Debit]]>0),"A","")) | N28: 272800 | O28: Autres prêts au personnel | P28: 1245000 | R28: 682000 | T28: 1927000 | V28: =VALUE(LEFT(BalanceN1[[#This Row],[Compte]]&"00000000",5)) -> 27280 | W28: {=IF(BalanceN1[[#This Row],[Compte]]="",0,_xlfn.IFNA(INDEX(Plan_Comptable[[Table de Compte]:[Sens]],MATCH(VALUE(LEFT(BalanceN1[[#This Row],[Table]],4)),VALUE(Plan_Comptable[Table de Compte]),0),2),"A"))} -> D | X28: =IF(AND(BalanceN1[[#This Row],[Vérif]]="D",BalanceN1[[#This Row],[BS_Credit]]>0),"A",IF(AND(BalanceN1[[#This Row],[Vérif]]="C",BalanceN1[[#This Row],[BS_Debit]]>0),"A","")) | Y28: =IF(AND(BalanceN1[[#This Row],[Vérif]]="D",BalanceN1[[#This Row],[BE_Credit]]>0),"A",IF(AND(BalanceN1[[#This Row],[Vérif]]="C",BalanceN1[[#This Row],[BE_Debit]]>0),"A",""))
A29: 238000 | B29: Autres installations et agencements | C29: 11064619 | E29: 1000000 | G29: 12064619 | I29: =VALUE(LEFT(BalanceN[[#This Row],[Compte]]&"00000000",5)) -> 23800 | J29: {=IF(BalanceN[[#This Row],[Compte]]="",0,_xlfn.IFNA(INDEX(Plan_Comptable[[Table de Compte]:[Sens]],MATCH(VALUE(LEFT(BalanceN[[#This Row],[Table]],4)),VALUE(Plan_Comptable[Table de Compte]),0),2),"A"))} -> D | K29: =IF(AND(BalanceN[[#This Row],[Vérif]]="D",BalanceN[[#This Row],[BS_Credit]]>0),"A",IF(AND(BalanceN[[#This Row],[Vérif]]="C",BalanceN[[#This Row],[BS_Debit]]>0),"A","")) | L29: =IF(AND(BalanceN[[#This Row],[Vérif]]="D",BalanceN[[#This Row],[BE_Credit]]>0),"A",IF(AND(BalanceN[[#This Row],[Vérif]]="C",BalanceN[[#This Row],[BE_Debit]]>0),"A","")) | N29: 2752 | O29: Dépôts et cautiono. | P29: 1238776 | R29: 276379 | S29: 179865 | T29: 1335290 | V29: =VALUE(LEFT(BalanceN1[[#This Row],[Compte]]&"00000000",5)) -> 27520 | W29: {=IF(BalanceN1[[#This Row],[Compte]]="",0,_xlfn.IFNA(INDEX(Plan_Comptable[[Table de Compte]:[Sens]],MATCH(VALUE(LEFT(BalanceN1[[#This Row],[Table]],4)),VALUE(Plan_Comptable[Table de Compte]),0),2),"A"))} -> D | X29: =IF(AND(BalanceN1[[#This Row],[Vérif]]="D",BalanceN1[[#This Row],[BS_Credit]]>0),"A",IF(AND(BalanceN1[[#This Row],[Vérif]]="C",BalanceN1[[#This Row],[BS_Debit]]>0),"A","")) | Y29: =IF(AND(BalanceN1[[#This Row],[Vérif]]="D",BalanceN1[[#This Row],[BE_Credit]]>0),"A",IF(AND(BalanceN1[[#This Row],[Vérif]]="C",BalanceN1[[#This Row],[BE_Debit]]>0),"A",""))
A30: 241100 | B30: Matériel industriel | C30: 91310403 | E30: 17694000 | F30: 40023276 | G30: 68981127 | I30: =VALUE(LEFT(BalanceN[[#This Row],[Compte]]&"00000000",5)) -> 24110 | J30: {=IF(BalanceN[[#This Row],[Compte]]="",0,_xlfn.IFNA(INDEX(Plan_Comptable[[Table de Compte]:[Sens]],MATCH(VALUE(LEFT(BalanceN[[#This Row],[Table]],4)),VALUE(Plan_Comptable[Table de Compte]),0),2),"A"))} -> D | K30: =IF(AND(BalanceN[[#This Row],[Vérif]]="D",BalanceN[[#This Row],[BS_Credit]]>0),"A",IF(AND(BalanceN[[#This Row],[Vérif]]="C",BalanceN[[#This Row],[BS_Debit]]>0),"A","")) | L30: =IF(AND(BalanceN[[#This Row],[Vérif]]="D",BalanceN[[#This Row],[BE_Credit]]>0),"A",IF(AND(BalanceN[[#This Row],[Vérif]]="C",BalanceN[[#This Row],[BE_Debit]]>0),"A","")) | N30: 275300 | O30: Dépôts et caution. Eau | P30: 87068 | T30: 87068 | V30: =VALUE(LEFT(BalanceN1[[#This Row],[Compte]]&"00000000",5)) -> 27530 | W30: {=IF(BalanceN1[[#This Row],[Compte]]="",0,_xlfn.IFNA(INDEX(Plan_Comptable[[Table de Compte]:[Sens]],MATCH(VALUE(LEFT(BalanceN1[[#This Row],[Table]],4)),VALUE(Plan_Comptable[Table de Compte]),0),2),"A"))} -> D | X30: =IF(AND(BalanceN1[[#This Row],[Vérif]]="D",BalanceN1[[#This Row],[BS_Credit]]>0),"A",IF(AND(BalanceN1[[#This Row],[Vérif]]="C",BalanceN1[[#This Row],[BS_Debit]]>0),"A","")) | Y30: =IF(AND(BalanceN1[[#This Row],[Vérif]]="D",BalanceN1[[#This Row],[BE_Credit]]>0),"A",IF(AND(BalanceN1[[#This Row],[Vérif]]="C",BalanceN1[[#This Row],[BE_Debit]]>0),"A",""))
A31: 244100 | B31: Matériel de bureau | C31: 1325000 | E31: 5075000 | F31: 140000 | G31: 6260000 | I31: =VALUE(LEFT(BalanceN[[#This Row],[Compte]]&"00000000",5)) -> 24410 | J31: {=IF(BalanceN[[#This Row],[Compte]]="",0,_xlfn.IFNA(INDEX(Plan_Comptable[[Table de Compte]:[Sens]],MATCH(VALUE(LEFT(BalanceN[[#This Row],[Table]],4)),VALUE(Plan_Comptable[Table de Compte]),0),2),"A"))} -> D | K31: =IF(AND(BalanceN[[#This Row],[Vérif]]="D",BalanceN[[#This Row],[BS_Credit]]>0),"A",IF(AND(BalanceN[[#This Row],[Vérif]]="C",BalanceN[[#This Row],[BS_Debit]]>0),"A","")) | L31: =IF(AND(BalanceN[[#This Row],[Vérif]]="D",BalanceN[[#This Row],[BE_Credit]]>0),"A",IF(AND(BalanceN[[#This Row],[Vérif]]="C",BalanceN[[#This Row],[BE_Debit]]>0),"A","")) | N31: 275500 | O31: Dépôt/téléphooe télex télécopie | P31: 449300 | T31: 449300 | V31: =VALUE(LEFT(BalanceN1[[#This Row],[Compte]]&"00000000",5)) -> 27550 | W31: {=IF(BalanceN1[[#This Row],[Compte]]="",0,_xlfn.IFNA(INDEX(Plan_Comptable[[Table de Compte]:[Sens]],MATCH(VALUE(LEFT(BalanceN1[[#This Row],[Table]],4)),VALUE(Plan_Comptable[Table de Compte]),0),2),"A"))} -> D | X31: =IF(AND(BalanceN1[[#This Row],[Vérif]]="D",BalanceN1[[#This Row],[BS_Credit]]>0),"A",IF(AND(BalanceN1[[#This Row],[Vérif]]="C",BalanceN1[[#This Row],[BS_Debit]]>0),"A","")) | Y31: =IF(AND(BalanceN1[[#This Row],[Vérif]]="D",BalanceN1[[#This Row],[BE_Credit]]>0),"A",IF(AND(BalanceN1[[#This Row],[Vérif]]="C",BalanceN1[[#This Row],[BE_Debit]]>0),"A",""))
A32: 244200 | B32: Matériel informatique | C32: 6867703 | E32: 1199000 | F32: 5829703 | G32: 2237000 | I32: =VALUE(LEFT(BalanceN[[#This Row],[Compte]]&"00000000",5)) -> 24420 | J32: {=IF(BalanceN[[#This Row],[Compte]]="",0,_xlfn.IFNA(INDEX(Plan_Comptable[[Table de Compte]:[Sens]],MATCH(VALUE(LEFT(BalanceN[[#This Row],[Table]],4)),VALUE(Plan_Comptable[Table de Compte]),0),2),"A"))} -> D | K32: =IF(AND(BalanceN[[#This Row],[Vérif]]="D",BalanceN[[#This Row],[BS_Credit]]>0),"A",IF(AND(BalanceN[[#This Row],[Vérif]]="C",BalanceN[[#This Row],[BS_Debit]]>0),"A","")) | L32: =IF(AND(BalanceN[[#This Row],[Vérif]]="D",BalanceN[[#This Row],[BE_Credit]]>0),"A",IF(AND(BalanceN[[#This Row],[Vérif]]="C",BalanceN[[#This Row],[BE_Debit]]>0),"A","")) | N32: 275800 | O32: Autres dépôts et cautiono. | P32: 750000 | T32: 750000 | V32: =VALUE(LEFT(BalanceN1[[#This Row],[Compte]]&"00000000",5)) -> 27580 | W32: {=IF(BalanceN1[[#This Row],[Compte]]="",0,_xlfn.IFNA(INDEX(Plan_Comptable[[Table de Compte]:[Sens]],MATCH(VALUE(LEFT(BalanceN1[[#This Row],[Table]],4)),VALUE(Plan_Comptable[Table de Compte]),0),2),"A"))} -> D | X32: =IF(AND(BalanceN1[[#This Row],[Vérif]]="D",BalanceN1[[#This Row],[BS_Credit]]>0),"A",IF(AND(BalanceN1[[#This Row],[Vérif]]="C",BalanceN1[[#This Row],[BS_Debit]]>0),"A","")) | Y32: =IF(AND(BalanceN1[[#This Row],[Vérif]]="D",BalanceN1[[#This Row],[BE_Credit]]>0),"A",IF(AND(BalanceN1[[#This Row],[Vérif]]="C",BalanceN1[[#This Row],[BE_Debit]]>0),"A",""))
A33: 244400 | B33: Mobilier de bureau | C33: 4968900 | E33: 500000 | G33: 5468900 | I33: =VALUE(LEFT(BalanceN[[#This Row],[Compte]]&"00000000",5)) -> 24440 | J33: {=IF(BalanceN[[#This Row],[Compte]]="",0,_xlfn.IFNA(INDEX(Plan_Comptable[[Table de Compte]:[Sens]],MATCH(VALUE(LEFT(BalanceN[[#This Row],[Table]],4)),VALUE(Plan_Comptable[Table de Compte]),0),2),"A"))} -> D | K33: =IF(AND(BalanceN[[#This Row],[Vérif]]="D",BalanceN[[#This Row],[BS_Credit]]>0),"A",IF(AND(BalanceN[[#This Row],[Vérif]]="C",BalanceN[[#This Row],[BS_Debit]]>0),"A","")) | L33: =IF(AND(BalanceN[[#This Row],[Vérif]]="D",BalanceN[[#This Row],[BE_Credit]]>0),"A",IF(AND(BalanceN[[#This Row],[Vérif]]="C",BalanceN[[#This Row],[BE_Debit]]>0),"A","")) | N33: 276200 | O33: Prêt amicale personnel | P33: 1000000 | S33: 1000000 | V33: =VALUE(LEFT(BalanceN1[[#This Row],[Compte]]&"00000000",5)) -> 27620 | W33: {=IF(BalanceN1[[#This Row],[Compte]]="",0,_xlfn.IFNA(INDEX(Plan_Comptable[[Table de Compte]:[Sens]],MATCH(VALUE(LEFT(BalanceN1[[#This Row],[Table]],4)),VALUE(Plan_Comptable[Table de Compte]),0),2),"A"))} -> D | X33: =IF(AND(BalanceN1[[#This Row],[Vérif]]="D",BalanceN1[[#This Row],[BS_Credit]]>0),"A",IF(AND(BalanceN1[[#This Row],[Vérif]]="C",BalanceN1[[#This Row],[BS_Debit]]>0),"A","")) | Y33: =IF(AND(BalanceN1[[#This Row],[Vérif]]="D",BalanceN1[[#This Row],[BE_Credit]]>0),"A",IF(AND(BalanceN1[[#This Row],[Vérif]]="C",BalanceN1[[#This Row],[BE_Debit]]>0),"A",""))
A34: 245100 | B34: Matériel automobile | C34: 54050000 | E34: 22000000 | G34: 76050000 | I34: =VALUE(LEFT(BalanceN[[#This Row],[Compte]]&"00000000",5)) -> 24510 | J34: {=IF(BalanceN[[#This Row],[Compte]]="",0,_xlfn.IFNA(INDEX(Plan_Comptable[[Table de Compte]:[Sens]],MATCH(VALUE(LEFT(BalanceN[[#This Row],[Table]],4)),VALUE(Plan_Comptable[Table de Compte]),0),2),"A"))} -> D | K34: =IF(AND(BalanceN[[#This Row],[Vérif]]="D",BalanceN[[#This Row],[BS_Credit]]>0),"A",IF(AND(BalanceN[[#This Row],[Vérif]]="C",BalanceN[[#This Row],[BS_Debit]]>0),"A","")) | L34: =IF(AND(BalanceN[[#This Row],[Vérif]]="D",BalanceN[[#This Row],[BE_Credit]]>0),"A",IF(AND(BalanceN[[#This Row],[Vérif]]="C",BalanceN[[#This Row],[BE_Debit]]>0),"A","")) | N34: 283210 | O34: Amortissement des bâtiments indust. | Q34: 140579277 | S34: 9734682 | U34: 150313959 | V34: =VALUE(LEFT(BalanceN1[[#This Row],[Compte]]&"00000000",5)) -> 28321 | W34: {=IF(BalanceN1[[#This Row],[Compte]]="",0,_xlfn.IFNA(INDEX(Plan_Comptable[[Table de Compte]:[Sens]],MATCH(VALUE(LEFT(BalanceN1[[#This Row],[Table]],4)),VALUE(Plan_Comptable[Table de Compte]),0),2),"A"))} -> C | X34: =IF(AND(BalanceN1[[#This Row],[Vérif]]="D",BalanceN1[[#This Row],[BS_Credit]]>0),"A",IF(AND(BalanceN1[[#This Row],[Vérif]]="C",BalanceN1[[#This Row],[BS_Debit]]>0),"A","")) | Y34: =IF(AND(BalanceN1[[#This Row],[Vérif]]="D",BalanceN1[[#This Row],[BE_Credit]]>0),"A",IF(AND(BalanceN1[[#This Row],[Vérif]]="C",BalanceN1[[#This Row],[BE_Debit]]>0),"A",""))
A35: 252000 | B35: Avance acompt.e sur immobilisation | E35: 25000000 | F35: 5000000 | G35: 20000000 | I35: =VALUE(LEFT(BalanceN[[#This Row],[Compte]]&"00000000",5)) -> 25200 | J35: {=IF(BalanceN[[#This Row],[Compte]]="",0,_xlfn.IFNA(INDEX(Plan_Comptable[[Table de Compte]:[Sens]],MATCH(VALUE(LEFT(BalanceN[[#This Row],[Table]],4)),VALUE(Plan_Comptable[Table de Compte]),0),2),"A"))} -> D | K35: =IF(AND(BalanceN[[#This Row],[Vérif]]="D",BalanceN[[#This Row],[BS_Credit]]>0),"A",IF(AND(BalanceN[[#This Row],[Vérif]]="C",BalanceN[[#This Row],[BS_Debit]]>0),"A","")) | L35: =IF(AND(BalanceN[[#This Row],[Vérif]]="D",BalanceN[[#This Row],[BE_Credit]]>0),"A",IF(AND(BalanceN[[#This Row],[Vérif]]="C",BalanceN[[#This Row],[BE_Debit]]>0),"A","")) | N35: 283510 | O35: Amortissement des instal. Générales | Q35: 71310267 | S35: 18000 | U35: 71328267 | V35: =VALUE(LEFT(BalanceN1[[#This Row],[Compte]]&"00000000",5)) -> 28351 | W35: {=IF(BalanceN1[[#This Row],[Compte]]="",0,_xlfn.IFNA(INDEX(Plan_Comptable[[Table de Compte]:[Sens]],MATCH(VALUE(LEFT(BalanceN1[[#This Row],[Table]],4)),VALUE(Plan_Comptable[Table de Compte]),0),2),"A"))} -> C | X35: =IF(AND(BalanceN1[[#This Row],[Vérif]]="D",BalanceN1[[#This Row],[BS_Credit]]>0),"A",IF(AND(BalanceN1[[#This Row],[Vérif]]="C",BalanceN1[[#This Row],[BS_Debit]]>0),"A","")) | Y35: =IF(AND(BalanceN1[[#This Row],[Vérif]]="D",BalanceN1[[#This Row],[BE_Credit]]>0),"A",IF(AND(BalanceN1[[#This Row],[Vérif]]="C",BalanceN1[[#This Row],[BE_Debit]]>0),"A",""))
A36: 272800 | B36: Autres prêts au personnel | C36: 1927000 | G36: 1927000 | I36: =VALUE(LEFT(BalanceN[[#This Row],[Compte]]&"00000000",5)) -> 27280 | J36: {=IF(BalanceN[[#This Row],[Compte]]="",0,_xlfn.IFNA(INDEX(Plan_Comptable[[Table de Compte]:[Sens]],MATCH(VALUE(LEFT(BalanceN[[#This Row],[Table]],4)),VALUE(Plan_Comptable[Table de Compte]),0),2),"A"))} -> D | K36: =IF(AND(BalanceN[[#This Row],[Vérif]]="D",BalanceN[[#This Row],[BS_Credit]]>0),"A",IF(AND(BalanceN[[#This Row],[Vérif]]="C",BalanceN[[#This Row],[BS_Debit]]>0),"A","")) | L36: =IF(AND(BalanceN[[#This Row],[Vérif]]="D",BalanceN[[#This Row],[BE_Credit]]>0),"A",IF(AND(BalanceN[[#This Row],[Vérif]]="C",BalanceN[[#This Row],[BE_Debit]]>0),"A","")) | N36: 284110 | O36: Amortissement du matériel indust. | Q36: 53005415 | R36: 58333 | S36: 7356831 | U36: 60303913 | V36: =VALUE(LEFT(BalanceN1[[#This Row],[Compte]]&"00000000",5)) -> 28411 | W36: {=IF(BalanceN1[[#This Row],[Compte]]="",0,_xlfn.IFNA(INDEX(Plan_Comptable[[Table de Compte]:[Sens]],MATCH(VALUE(LEFT(BalanceN1[[#This Row],[Table]],4)),VALUE(Plan_Comptable[Table de Compte]),0),2),"A"))} -> C | X36: =IF(AND(BalanceN1[[#This Row],[Vérif]]="D",BalanceN1[[#This Row],[BS_Credit]]>0),"A",IF(AND(BalanceN1[[#This Row],[Vérif]]="C",BalanceN1[[#This Row],[BS_Debit]]>0),"A","")) | Y36: =IF(AND(BalanceN1[[#This Row],[Vérif]]="D",BalanceN1[[#This Row],[BE_Credit]]>0),"A",IF(AND(BalanceN1[[#This Row],[Vérif]]="C",BalanceN1[[#This Row],[BE_Debit]]>0),"A",""))
A37: 2752 | B37: Dépôts et cautionnement électricité | C37: 1335290 | E37: 401175 | F37: 730043 | G37: 1006422 | I37: =VALUE(LEFT(BalanceN[[#This Row],[Compte]]&"00000000",5)) -> 27520 | J37: {=IF(BalanceN[[#This Row],[Compte]]="",0,_xlfn.IFNA(INDEX(Plan_Comptable[[Table de Compte]:[Sens]],MATCH(VALUE(LEFT(BalanceN[[#This Row],[Table]],4)),VALUE(Plan_Comptable[Table de Compte]),0),2),"A"))} -> D | K37: =IF(AND(BalanceN[[#This Row],[Vérif]]="D",BalanceN[[#This Row],[BS_Credit]]>0),"A",IF(AND(BalanceN[[#This Row],[Vérif]]="C",BalanceN[[#This Row],[BS_Debit]]>0),"A","")) | L37: =IF(AND(BalanceN[[#This Row],[Vérif]]="D",BalanceN[[#This Row],[BE_Credit]]>0),"A",IF(AND(BalanceN[[#This Row],[Vérif]]="C",BalanceN[[#This Row],[BE_Debit]]>0),"A","")) | N37: 284410 | O37: Amortissement du matériel de bureau | Q37: 1325000 | U37: 1325000 | V37: =VALUE(LEFT(BalanceN1[[#This Row],[Compte]]&"00000000",5)) -> 28441 | W37: {=IF(BalanceN1[[#This Row],[Compte]]="",0,_xlfn.IFNA(INDEX(Plan_Comptable[[Table de Compte]:[Sens]],MATCH(VALUE(LEFT(BalanceN1[[#This Row],[Table]],4)),VALUE(Plan_Comptable[Table de Compte]),0),2),"A"))} -> C | X37: =IF(AND(BalanceN1[[#This Row],[Vérif]]="D",BalanceN1[[#This Row],[BS_Credit]]>0),"A",IF(AND(BalanceN1[[#This Row],[Vérif]]="C",BalanceN1[[#This Row],[BS_Debit]]>0),"A","")) | Y37: =IF(AND(BalanceN1[[#This Row],[Vérif]]="D",BalanceN1[[#This Row],[BE_Credit]]>0),"A",IF(AND(BalanceN1[[#This Row],[Vérif]]="C",BalanceN1[[#This Row],[BE_Debit]]>0),"A",""))
A38: 275300 | B38: Dépôts et caution. Eau | C38: 87068 | G38: 87068 | I38: =VALUE(LEFT(BalanceN[[#This Row],[Compte]]&"00000000",5)) -> 27530 | J38: {=IF(BalanceN[[#This Row],[Compte]]="",0,_xlfn.IFNA(INDEX(Plan_Comptable[[Table de Compte]:[Sens]],MATCH(VALUE(LEFT(BalanceN[[#This Row],[Table]],4)),VALUE(Plan_Comptable[Table de Compte]),0),2),"A"))} -> D | K38: =IF(AND(BalanceN[[#This Row],[Vérif]]="D",BalanceN[[#This Row],[BS_Credit]]>0),"A",IF(AND(BalanceN[[#This Row],[Vérif]]="C",BalanceN[[#This Row],[BS_Debit]]>0),"A","")) | L38: =IF(AND(BalanceN[[#This Row],[Vérif]]="D",BalanceN[[#This Row],[BE_Credit]]>0),"A",IF(AND(BalanceN[[#This Row],[Vérif]]="C",BalanceN[[#This Row],[BE_Debit]]>0),"A","")) | N38: 284420 | O38: Amortissement du matériel infonnatique | Q38: 5733437 | S38: 441600 | U38: 6175037 | V38: =VALUE(LEFT(BalanceN1[[#This Row],[Compte]]&"00000000",5)) -> 28442 | W38: {=IF(BalanceN1[[#This Row],[Compte]]="",0,_xlfn.IFNA(INDEX(Plan_Comptable[[Table de Compte]:[Sens]],MATCH(VALUE(LEFT(BalanceN1[[#This Row],[Table]],4)),VALUE(Plan_Comptable[Table de Compte]),0),2),"A"))} -> C | X38: =IF(AND(BalanceN1[[#This Row],[Vérif]]="D",BalanceN1[[#This Row],[BS_Credit]]>0),"A",IF(AND(BalanceN1[[#This Row],[Vérif]]="C",BalanceN1[[#This Row],[BS_Debit]]>0),"A","")) | Y38: =IF(AND(BalanceN1[[#This Row],[Vérif]]="D",BalanceN1[[#This Row],[BE_Credit]]>0),"A",IF(AND(BalanceN1[[#This Row],[Vérif]]="C",BalanceN1[[#This Row],[BE_Debit]]>0),"A",""))
A39: 275500 | B39: Dépôt/téléphone télex télécopie | C39: 449300 | E39: 200000 | G39: 649300 | I39: =VALUE(LEFT(BalanceN[[#This Row],[Compte]]&"00000000",5)) -> 27550 | J39: {=IF(BalanceN[[#This Row],[Compte]]="",0,_xlfn.IFNA(INDEX(Plan_Comptable[[Table de Compte]:[Sens]],MATCH(VALUE(LEFT(BalanceN[[#This Row],[Table]],4)),VALUE(Plan_Comptable[Table de Compte]),0),2),"A"))} -> D | K39: =IF(AND(BalanceN[[#This Row],[Vérif]]="D",BalanceN[[#This Row],[BS_Credit]]>0),"A",IF(AND(BalanceN[[#This Row],[Vérif]]="C",BalanceN[[#This Row],[BS_Debit]]>0),"A","")) | L39: =IF(AND(BalanceN[[#This Row],[Vérif]]="D",BalanceN[[#This Row],[BE_Credit]]>0),"A",IF(AND(BalanceN[[#This Row],[Vérif]]="C",BalanceN[[#This Row],[BE_Debit]]>0),"A","")) | N39: 284440 | O39: Amortissement du mobilier de bureau | Q39: 4283140 | S39: 298880 | U39: 4582020 | V39: =VALUE(LEFT(BalanceN1[[#This Row],[Compte]]&"00000000",5)) -> 28444 | W39: {=IF(BalanceN1[[#This Row],[Compte]]="",0,_xlfn.IFNA(INDEX(Plan_Comptable[[Table de Compte]:[Sens]],MATCH(VALUE(LEFT(BalanceN1[[#This Row],[Table]],4)),VALUE(Plan_Comptable[Table de Compte]),0),2),"A"))} -> C | X39: =IF(AND(BalanceN1[[#This Row],[Vérif]]="D",BalanceN1[[#This Row],[BS_Credit]]>0),"A",IF(AND(BalanceN1[[#This Row],[Vérif]]="C",BalanceN1[[#This Row],[BS_Debit]]>0),"A","")) | Y39: =IF(AND(BalanceN1[[#This Row],[Vérif]]="D",BalanceN1[[#This Row],[BE_Credit]]>0),"A",IF(AND(BalanceN1[[#This Row],[Vérif]]="C",BalanceN1[[#This Row],[BE_Debit]]>0),"A",""))
A40: 275800 | B40: Autres dépôts et cautionn. | C40: 750000 | G40: 750000 | I40: =VALUE(LEFT(BalanceN[[#This Row],[Compte]]&"00000000",5)) -> 27580 | J40: {=IF(BalanceN[[#This Row],[Compte]]="",0,_xlfn.IFNA(INDEX(Plan_Comptable[[Table de Compte]:[Sens]],MATCH(VALUE(LEFT(BalanceN[[#This Row],[Table]],4)),VALUE(Plan_Comptable[Table de Compte]),0),2),"A"))} -> D | K40: =IF(AND(BalanceN[[#This Row],[Vérif]]="D",BalanceN[[#This Row],[BS_Credit]]>0),"A",IF(AND(BalanceN[[#This Row],[Vérif]]="C",BalanceN[[#This Row],[BS_Debit]]>0),"A","")) | L40: =IF(AND(BalanceN[[#This Row],[Vérif]]="D",BalanceN[[#This Row],[BE_Credit]]>0),"A",IF(AND(BalanceN[[#This Row],[Vérif]]="C",BalanceN[[#This Row],[BE_Debit]]>0),"A","")) | N40: 284510 | O40: Amortissement du matériel automobile | Q40: 47407500 | S40: 6455000 | U40: 53862500 | V40: =VALUE(LEFT(BalanceN1[[#This Row],[Compte]]&"00000000",5)) -> 28451 | W40: {=IF(BalanceN1[[#This Row],[Compte]]="",0,_xlfn.IFNA(INDEX(Plan_Comptable[[Table de Compte]:[Sens]],MATCH(VALUE(LEFT(BalanceN1[[#This Row],[Table]],4)),VALUE(Plan_Comptable[Table de Compte]),0),2),"A"))} -> C | X40: =IF(AND(BalanceN1[[#This Row],[Vérif]]="D",BalanceN1[[#This Row],[BS_Credit]]>0),"A",IF(AND(BalanceN1[[#This Row],[Vérif]]="C",BalanceN1[[#This Row],[BS_Debit]]>0),"A","")) | Y40: =IF(AND(BalanceN1[[#This Row],[Vérif]]="D",BalanceN1[[#This Row],[BE_Credit]]>0),"A",IF(AND(BalanceN1[[#This Row],[Vérif]]="C",BalanceN1[[#This Row],[BE_Debit]]>0),"A",""))
A41: 283210 | B41: Amortissement des bâtiments industriels | D41: 150313959 | F41: 9734682 | H41: 160048641 | I41: =VALUE(LEFT(BalanceN[[#This Row],[Compte]]&"00000000",5)) -> 28321 | J41: {=IF(BalanceN[[#This Row],[Compte]]="",0,_xlfn.IFNA(INDEX(Plan_Comptable[[Table de Compte]:[Sens]],MATCH(VALUE(LEFT(BalanceN[[#This Row],[Table]],4)),VALUE(Plan_Comptable[Table de Compte]),0),2),"A"))} -> C | K41: =IF(AND(BalanceN[[#This Row],[Vérif]]="D",BalanceN[[#This Row],[BS_Credit]]>0),"A",IF(AND(BalanceN[[#This Row],[Vérif]]="C",BalanceN[[#This Row],[BS_Debit]]>0),"A","")) | L41: =IF(AND(BalanceN[[#This Row],[Vérif]]="D",BalanceN[[#This Row],[BE_Credit]]>0),"A",IF(AND(BalanceN[[#This Row],[Vérif]]="C",BalanceN[[#This Row],[BE_Debit]]>0),"A","")) | N41: 321 | O41: Stock de matières premières | P41: 10552040 | R41: 7721440 | S41: 10552040 | T41: 7721440 | V41: =VALUE(LEFT(BalanceN1[[#This Row],[Compte]]&"00000000",5)) -> 32100 | W41: {=IF(BalanceN1[[#This Row],[Compte]]="",0,_xlfn.IFNA(INDEX(Plan_Comptable[[Table de Compte]:[Sens]],MATCH(VALUE(LEFT(BalanceN1[[#This Row],[Table]],4)),VALUE(Plan_Comptable[Table de Compte]),0),2),"A"))} -> D | X41: =IF(AND(BalanceN1[[#This Row],[Vérif]]="D",BalanceN1[[#This Row],[BS_Credit]]>0),"A",IF(AND(BalanceN1[[#This Row],[Vérif]]="C",BalanceN1[[#This Row],[BS_Debit]]>0),"A","")) | Y41: =IF(AND(BalanceN1[[#This Row],[Vérif]]="D",BalanceN1[[#This Row],[BE_Credit]]>0),"A",IF(AND(BalanceN1[[#This Row],[Vérif]]="C",BalanceN1[[#This Row],[BE_Debit]]>0),"A",""))
A42: 283510 | B42: Amortissement des instal. Générales | D42: 71328267 | H42: 71328267 | I42: =VALUE(LEFT(BalanceN[[#This Row],[Compte]]&"00000000",5)) -> 28351 | J42: {=IF(BalanceN[[#This Row],[Compte]]="",0,_xlfn.IFNA(INDEX(Plan_Comptable[[Table de Compte]:[Sens]],MATCH(VALUE(LEFT(BalanceN[[#This Row],[Table]],4)),VALUE(Plan_Comptable[Table de Compte]),0),2),"A"))} -> C | K42: =IF(AND(BalanceN[[#This Row],[Vérif]]="D",BalanceN[[#This Row],[BS_Credit]]>0),"A",IF(AND(BalanceN[[#This Row],[Vérif]]="C",BalanceN[[#This Row],[BS_Debit]]>0),"A","")) | L42: =IF(AND(BalanceN[[#This Row],[Vérif]]="D",BalanceN[[#This Row],[BE_Credit]]>0),"A",IF(AND(BalanceN[[#This Row],[Vérif]]="C",BalanceN[[#This Row],[BE_Debit]]>0),"A","")) | N42: 335100 | O42: Stocks emballages | P42: 6262346 | R42: 8146993 | S42: 6262346 | T42: 8146993 | V42: =VALUE(LEFT(BalanceN1[[#This Row],[Compte]]&"00000000",5)) -> 33510 | W42: {=IF(BalanceN1[[#This Row],[Compte]]="",0,_xlfn.IFNA(INDEX(Plan_Comptable[[Table de Compte]:[Sens]],MATCH(VALUE(LEFT(BalanceN1[[#This Row],[Table]],4)),VALUE(Plan_Comptable[Table de Compte]),0),2),"A"))} -> D | X42: =IF(AND(BalanceN1[[#This Row],[Vérif]]="D",BalanceN1[[#This Row],[BS_Credit]]>0),"A",IF(AND(BalanceN1[[#This Row],[Vérif]]="C",BalanceN1[[#This Row],[BS_Debit]]>0),"A","")) | Y42: =IF(AND(BalanceN1[[#This Row],[Vérif]]="D",BalanceN1[[#This Row],[BE_Credit]]>0),"A",IF(AND(BalanceN1[[#This Row],[Vérif]]="C",BalanceN1[[#This Row],[BE_Debit]]>0),"A",""))
A43: 284110 | B43: Amortissement du matériel industriel | D43: 60303913 | E43: 40023276 | F43: 8385232 | H43: 28665869 | I43: =VALUE(LEFT(BalanceN[[#This Row],[Compte]]&"00000000",5)) -> 28411 | J43: {=IF(BalanceN[[#This Row],[Compte]]="",0,_xlfn.IFNA(INDEX(Plan_Comptable[[Table de Compte]:[Sens]],MATCH(VALUE(LEFT(BalanceN[[#This Row],[Table]],4)),VALUE(Plan_Comptable[Table de Compte]),0),2),"A"))} -> C | K43: =IF(AND(BalanceN[[#This Row],[Vérif]]="D",BalanceN[[#This Row],[BS_Credit]]>0),"A",IF(AND(BalanceN[[#This Row],[Vérif]]="C",BalanceN[[#This Row],[BS_Debit]]>0),"A","")) | L43: =IF(AND(BalanceN[[#This Row],[Vérif]]="D",BalanceN[[#This Row],[BE_Credit]]>0),"A",IF(AND(BalanceN[[#This Row],[Vérif]]="C",BalanceN[[#This Row],[BE_Debit]]>0),"A","")) | N43: 401100 | O43: Fournisseurs | Q43: 76549980 | R43: 562421027 | S43: 526454947 | U43: 40583900 | V43: =VALUE(LEFT(BalanceN1[[#This Row],[Compte]]&"00000000",5)) -> 40110 | W43: {=IF(BalanceN1[[#This Row],[Compte]]="",0,_xlfn.IFNA(INDEX(Plan_Comptable[[Table de Compte]:[Sens]],MATCH(VALUE(LEFT(BalanceN1[[#This Row],[Table]],4)),VALUE(Plan_Comptable[Table de Compte]),0),2),"A"))} -> C | X43: =IF(AND(BalanceN1[[#This Row],[Vérif]]="D",BalanceN1[[#This Row],[BS_Credit]]>0),"A",IF(AND(BalanceN1[[#This Row],[Vérif]]="C",BalanceN1[[#This Row],[BS_Debit]]>0),"A","")) | Y43: =IF(AND(BalanceN1[[#This Row],[Vérif]]="D",BalanceN1[[#This Row],[BE_Credit]]>0),"A",IF(AND(BalanceN1[[#This Row],[Vérif]]="C",BalanceN1[[#This Row],[BE_Debit]]>0),"A",""))
A44: 284410 | B44: Amortissement du matériel de bureau | D44: 1325000 | E44: 140000 | F44: 4833 | H44: 1189833 | I44: =VALUE(LEFT(BalanceN[[#This Row],[Compte]]&"00000000",5)) -> 28441 | J44: {=IF(BalanceN[[#This Row],[Compte]]="",0,_xlfn.IFNA(INDEX(Plan_Comptable[[Table de Compte]:[Sens]],MATCH(VALUE(LEFT(BalanceN[[#This Row],[Table]],4)),VALUE(Plan_Comptable[Table de Compte]),0),2),"A"))} -> C | K44: =IF(AND(BalanceN[[#This Row],[Vérif]]="D",BalanceN[[#This Row],[BS_Credit]]>0),"A",IF(AND(BalanceN[[#This Row],[Vérif]]="C",BalanceN[[#This Row],[BS_Debit]]>0),"A","")) | L44: =IF(AND(BalanceN[[#This Row],[Vérif]]="D",BalanceN[[#This Row],[BE_Credit]]>0),"A",IF(AND(BalanceN[[#This Row],[Vérif]]="C",BalanceN[[#This Row],[BE_Debit]]>0),"A","")) | N44: 408100 | O44: Fournisseurs fac non parvenues | Q44: 8071358 | R44: 54500645 | S44: 60428763 | U44: 13999476 | V44: =VALUE(LEFT(BalanceN1[[#This Row],[Compte]]&"00000000",5)) -> 40810 | W44: {=IF(BalanceN1[[#This Row],[Compte]]="",0,_xlfn.IFNA(INDEX(Plan_Comptable[[Table de Compte]:[Sens]],MATCH(VALUE(LEFT(BalanceN1[[#This Row],[Table]],4)),VALUE(Plan_Comptable[Table de Compte]),0),2),"A"))} -> C | X44: =IF(AND(BalanceN1[[#This Row],[Vérif]]="D",BalanceN1[[#This Row],[BS_Credit]]>0),"A",IF(AND(BalanceN1[[#This Row],[Vérif]]="C",BalanceN1[[#This Row],[BS_Debit]]>0),"A","")) | Y44: =IF(AND(BalanceN1[[#This Row],[Vérif]]="D",BalanceN1[[#This Row],[BE_Credit]]>0),"A",IF(AND(BalanceN1[[#This Row],[Vérif]]="C",BalanceN1[[#This Row],[BE_Debit]]>0),"A",""))
A45: 284420 | B45: Amortissement du matériel informatique | D45: 6175037 | E45: 5829703 | F45: 496917 | H45: 842251 | I45: =VALUE(LEFT(BalanceN[[#This Row],[Compte]]&"00000000",5)) -> 28442 | J45: {=IF(BalanceN[[#This Row],[Compte]]="",0,_xlfn.IFNA(INDEX(Plan_Comptable[[Table de Compte]:[Sens]],MATCH(VALUE(LEFT(BalanceN[[#This Row],[Table]],4)),VALUE(Plan_Comptable[Table de Compte]),0),2),"A"))} -> C | K45: =IF(AND(BalanceN[[#This Row],[Vérif]]="D",BalanceN[[#This Row],[BS_Credit]]>0),"A",IF(AND(BalanceN[[#This Row],[Vérif]]="C",BalanceN[[#This Row],[BS_Debit]]>0),"A","")) | L45: =IF(AND(BalanceN[[#This Row],[Vérif]]="D",BalanceN[[#This Row],[BE_Credit]]>0),"A",IF(AND(BalanceN[[#This Row],[Vérif]]="C",BalanceN[[#This Row],[BE_Debit]]>0),"A","")) | N45: 408110 | O45: Fac. Non parvenues eau | Q45: 782702 | R45: 782702 | V45: =VALUE(LEFT(BalanceN1[[#This Row],[Compte]]&"00000000",5)) -> 40811 | W45: {=IF(BalanceN1[[#This Row],[Compte]]="",0,_xlfn.IFNA(INDEX(Plan_Comptable[[Table de Compte]:[Sens]],MATCH(VALUE(LEFT(BalanceN1[[#This Row],[Table]],4)),VALUE(Plan_Comptable[Table de Compte]),0),2),"A"))} -> C | X45: =IF(AND(BalanceN1[[#This Row],[Vérif]]="D",BalanceN1[[#This Row],[BS_Credit]]>0),"A",IF(AND(BalanceN1[[#This Row],[Vérif]]="C",BalanceN1[[#This Row],[BS_Debit]]>0),"A","")) | Y45: =IF(AND(BalanceN1[[#This Row],[Vérif]]="D",BalanceN1[[#This Row],[BE_Credit]]>0),"A",IF(AND(BalanceN1[[#This Row],[Vérif]]="C",BalanceN1[[#This Row],[BE_Debit]]>0),"A",""))
A46: 284440 | B46: Amortissement du mobilier de bureau | D46: 4582020 | F46: 260480 | H46: 4842500 | I46: =VALUE(LEFT(BalanceN[[#This Row],[Compte]]&"00000000",5)) -> 28444 | J46: {=IF(BalanceN[[#This Row],[Compte]]="",0,_xlfn.IFNA(INDEX(Plan_Comptable[[Table de Compte]:[Sens]],MATCH(VALUE(LEFT(BalanceN[[#This Row],[Table]],4)),VALUE(Plan_Comptable[Table de Compte]),0),2),"A"))} -> C | K46: =IF(AND(BalanceN[[#This Row],[Vérif]]="D",BalanceN[[#This Row],[BS_Credit]]>0),"A",IF(AND(BalanceN[[#This Row],[Vérif]]="C",BalanceN[[#This Row],[BS_Debit]]>0),"A","")) | L46: =IF(AND(BalanceN[[#This Row],[Vérif]]="D",BalanceN[[#This Row],[BE_Credit]]>0),"A",IF(AND(BalanceN[[#This Row],[Vérif]]="C",BalanceN[[#This Row],[BE_Debit]]>0),"A","")) | N46: 408120 | O46: Fac. Non parvenues téléphone | Q46: 415200 | R46: 415200 | V46: =VALUE(LEFT(BalanceN1[[#This Row],[Compte]]&"00000000",5)) -> 40812 | W46: {=IF(BalanceN1[[#This Row],[Compte]]="",0,_xlfn.IFNA(INDEX(Plan_Comptable[[Table de Compte]:[Sens]],MATCH(VALUE(LEFT(BalanceN1[[#This Row],[Table]],4)),VALUE(Plan_Comptable[Table de Compte]),0),2),"A"))} -> C | X46: =IF(AND(BalanceN1[[#This Row],[Vérif]]="D",BalanceN1[[#This Row],[BS_Credit]]>0),"A",IF(AND(BalanceN1[[#This Row],[Vérif]]="C",BalanceN1[[#This Row],[BS_Debit]]>0),"A","")) | Y46: =IF(AND(BalanceN1[[#This Row],[Vérif]]="D",BalanceN1[[#This Row],[BE_Credit]]>0),"A",IF(AND(BalanceN1[[#This Row],[Vérif]]="C",BalanceN1[[#This Row],[BE_Debit]]>0),"A",""))
A47: 284510 | B47: Amortissement du matériel automobile | D47: 53862500 | F47: 377500 | H47: 54240000 | I47: =VALUE(LEFT(BalanceN[[#This Row],[Compte]]&"00000000",5)) -> 28451 | J47: {=IF(BalanceN[[#This Row],[Compte]]="",0,_xlfn.IFNA(INDEX(Plan_Comptable[[Table de Compte]:[Sens]],MATCH(VALUE(LEFT(BalanceN[[#This Row],[Table]],4)),VALUE(Plan_Comptable[Table de Compte]),0),2),"A"))} -> C | K47: =IF(AND(BalanceN[[#This Row],[Vérif]]="D",BalanceN[[#This Row],[BS_Credit]]>0),"A",IF(AND(BalanceN[[#This Row],[Vérif]]="C",BalanceN[[#This Row],[BS_Debit]]>0),"A","")) | L47: =IF(AND(BalanceN[[#This Row],[Vérif]]="D",BalanceN[[#This Row],[BE_Credit]]>0),"A",IF(AND(BalanceN[[#This Row],[Vérif]]="C",BalanceN[[#This Row],[BE_Debit]]>0),"A","")) | N47: 408130 | O47: Fac. Non parvenues électricité | Q47: 3257358 | R47: 3257358 | V47: =VALUE(LEFT(BalanceN1[[#This Row],[Compte]]&"00000000",5)) -> 40813 | W47: {=IF(BalanceN1[[#This Row],[Compte]]="",0,_xlfn.IFNA(INDEX(Plan_Comptable[[Table de Compte]:[Sens]],MATCH(VALUE(LEFT(BalanceN1[[#This Row],[Table]],4)),VALUE(Plan_Comptable[Table de Compte]),0),2),"A"))} -> C | X47: =IF(AND(BalanceN1[[#This Row],[Vérif]]="D",BalanceN1[[#This Row],[BS_Credit]]>0),"A",IF(AND(BalanceN1[[#This Row],[Vérif]]="C",BalanceN1[[#This Row],[BS_Debit]]>0),"A","")) | Y47: =IF(AND(BalanceN1[[#This Row],[Vérif]]="D",BalanceN1[[#This Row],[BE_Credit]]>0),"A",IF(AND(BalanceN1[[#This Row],[Vérif]]="C",BalanceN1[[#This Row],[BE_Debit]]>0),"A",""))
A48: 3111 | B48: Stock marchandises | E48: 5000000 | G48: 5000000 | I48: =VALUE(LEFT(BalanceN[[#This Row],[Compte]]&"00000000",5)) -> 31110 | J48: {=IF(BalanceN[[#This Row],[Compte]]="",0,_xlfn.IFNA(INDEX(Plan_Comptable[[Table de Compte]:[Sens]],MATCH(VALUE(LEFT(BalanceN[[#This Row],[Table]],4)),VALUE(Plan_Comptable[Table de Compte]),0),2),"A"))} -> D | K48: =IF(AND(BalanceN[[#This Row],[Vérif]]="D",BalanceN[[#This Row],[BS_Credit]]>0),"A",IF(AND(BalanceN[[#This Row],[Vérif]]="C",BalanceN[[#This Row],[BS_Debit]]>0),"A","")) | L48: =IF(AND(BalanceN[[#This Row],[Vérif]]="D",BalanceN[[#This Row],[BE_Credit]]>0),"A",IF(AND(BalanceN[[#This Row],[Vérif]]="C",BalanceN[[#This Row],[BE_Debit]]>0),"A","")) | N48: 408140 | O48: Fac. Noo parvenues transporteur | Q48: 637437 | R48: 14451330 | S48: 13813893 | V48: =VALUE(LEFT(BalanceN1[[#This Row],[Compte]]&"00000000",5)) -> 40814 | W48: {=IF(BalanceN1[[#This Row],[Compte]]="",0,_xlfn.IFNA(INDEX(Plan_Comptable[[Table de Compte]:[Sens]],MATCH(VALUE(LEFT(BalanceN1[[#This Row],[Table]],4)),VALUE(Plan_Comptable[Table de Compte]),0),2),"A"))} -> C | X48: =IF(AND(BalanceN1[[#This Row],[Vérif]]="D",BalanceN1[[#This Row],[BS_Credit]]>0),"A",IF(AND(BalanceN1[[#This Row],[Vérif]]="C",BalanceN1[[#This Row],[BS_Debit]]>0),"A","")) | Y48: =IF(AND(BalanceN1[[#This Row],[Vérif]]="D",BalanceN1[[#This Row],[BE_Credit]]>0),"A",IF(AND(BalanceN1[[#This Row],[Vérif]]="C",BalanceN1[[#This Row],[BE_Debit]]>0),"A",""))
A49: 321 | B49: Stock de matières premières | C49: 7721440 | E49: 57881451 | F49: 57775035 | G49: 7827856 | I49: =VALUE(LEFT(BalanceN[[#This Row],[Compte]]&"00000000",5)) -> 32100 | J49: {=IF(BalanceN[[#This Row],[Compte]]="",0,_xlfn.IFNA(INDEX(Plan_Comptable[[Table de Compte]:[Sens]],MATCH(VALUE(LEFT(BalanceN[[#This Row],[Table]],4)),VALUE(Plan_Comptable[Table de Compte]),0),2),"A"))} -> D | K49: =IF(AND(BalanceN[[#This Row],[Vérif]]="D",BalanceN[[#This Row],[BS_Credit]]>0),"A",IF(AND(BalanceN[[#This Row],[Vérif]]="C",BalanceN[[#This Row],[BS_Debit]]>0),"A","")) | L49: =IF(AND(BalanceN[[#This Row],[Vérif]]="D",BalanceN[[#This Row],[BE_Credit]]>0),"A",IF(AND(BalanceN[[#This Row],[Vérif]]="C",BalanceN[[#This Row],[BE_Debit]]>0),"A","")) | N49: 408150 | O49: Fac. Non parvenues avocats | S49: 1310830 | U49: 1310830 | V49: =VALUE(LEFT(BalanceN1[[#This Row],[Compte]]&"00000000",5)) -> 40815 | W49: {=IF(BalanceN1[[#This Row],[Compte]]="",0,_xlfn.IFNA(INDEX(Plan_Comptable[[Table de Compte]:[Sens]],MATCH(VALUE(LEFT(BalanceN1[[#This Row],[Table]],4)),VALUE(Plan_Comptable[Table de Compte]),0),2),"A"))} -> C | X49: =IF(AND(BalanceN1[[#This Row],[Vérif]]="D",BalanceN1[[#This Row],[BS_Credit]]>0),"A",IF(AND(BalanceN1[[#This Row],[Vérif]]="C",BalanceN1[[#This Row],[BS_Debit]]>0),"A","")) | Y49: =IF(AND(BalanceN1[[#This Row],[Vérif]]="D",BalanceN1[[#This Row],[BE_Credit]]>0),"A",IF(AND(BalanceN1[[#This Row],[Vérif]]="C",BalanceN1[[#This Row],[BE_Debit]]>0),"A",""))
A50: 335100 | B50: Stocks emballages | C50: 8146993 | E50: 76874255 | F50: 79288966 | G50: 5732282 | I50: =VALUE(LEFT(BalanceN[[#This Row],[Compte]]&"00000000",5)) -> 33510 | J50: {=IF(BalanceN[[#This Row],[Compte]]="",0,_xlfn.IFNA(INDEX(Plan_Comptable[[Table de Compte]:[Sens]],MATCH(VALUE(LEFT(BalanceN[[#This Row],[Table]],4)),VALUE(Plan_Comptable[Table de Compte]),0),2),"A"))} -> D | K50: =IF(AND(BalanceN[[#This Row],[Vérif]]="D",BalanceN[[#This Row],[BS_Credit]]>0),"A",IF(AND(BalanceN[[#This Row],[Vérif]]="C",BalanceN[[#This Row],[BS_Debit]]>0),"A","")) | L50: =IF(AND(BalanceN[[#This Row],[Vérif]]="D",BalanceN[[#This Row],[BE_Credit]]>0),"A",IF(AND(BalanceN[[#This Row],[Vérif]]="C",BalanceN[[#This Row],[BE_Debit]]>0),"A","")) | N50: 409100 | O50: Fournisse urs, avances et acomptes | R50: 1433750 | S50: 733750 | T50: 700000 | V50: =VALUE(LEFT(BalanceN1[[#This Row],[Compte]]&"00000000",5)) -> 40910 | W50: {=IF(BalanceN1[[#This Row],[Compte]]="",0,_xlfn.IFNA(INDEX(Plan_Comptable[[Table de Compte]:[Sens]],MATCH(VALUE(LEFT(BalanceN1[[#This Row],[Table]],4)),VALUE(Plan_Comptable[Table de Compte]),0),2),"A"))} -> D | X50: =IF(AND(BalanceN1[[#This Row],[Vérif]]="D",BalanceN1[[#This Row],[BS_Credit]]>0),"A",IF(AND(BalanceN1[[#This Row],[Vérif]]="C",BalanceN1[[#This Row],[BS_Debit]]>0),"A","")) | Y50: =IF(AND(BalanceN1[[#This Row],[Vérif]]="D",BalanceN1[[#This Row],[BE_Credit]]>0),"A",IF(AND(BalanceN1[[#This Row],[Vérif]]="C",BalanceN1[[#This Row],[BE_Debit]]>0),"A",""))
A51: 401100 | B51: Fournisseurs | D51: 40583900 | E51: 579308293 | F51: 565419408 | H51: 26695015 | I51: =VALUE(LEFT(BalanceN[[#This Row],[Compte]]&"00000000",5)) -> 40110 | J51: {=IF(BalanceN[[#This Row],[Compte]]="",0,_xlfn.IFNA(INDEX(Plan_Comptable[[Table de Compte]:[Sens]],MATCH(VALUE(LEFT(BalanceN[[#This Row],[Table]],4)),VALUE(Plan_Comptable[Table de Compte]),0),2),"A"))} -> C | K51: =IF(AND(BalanceN[[#This Row],[Vérif]]="D",BalanceN[[#This Row],[BS_Credit]]>0),"A",IF(AND(BalanceN[[#This Row],[Vérif]]="C",BalanceN[[#This Row],[BS_Debit]]>0),"A","")) | L51: =IF(AND(BalanceN[[#This Row],[Vérif]]="D",BalanceN[[#This Row],[BE_Credit]]>0),"A",IF(AND(BalanceN[[#This Row],[Vérif]]="C",BalanceN[[#This Row],[BE_Debit]]>0),"A","")) | N51: 411100 | O51: Clients | P51: 114098863 | R51: 1906855340 | S51: 1880270370 | T51: 140683833 | V51: =VALUE(LEFT(BalanceN1[[#This Row],[Compte]]&"00000000",5)) -> 41110 | W51: {=IF(BalanceN1[[#This Row],[Compte]]="",0,_xlfn.IFNA(INDEX(Plan_Comptable[[Table de Compte]:[Sens]],MATCH(VALUE(LEFT(BalanceN1[[#This Row],[Table]],4)),VALUE(Plan_Comptable[Table de Compte]),0),2),"A"))} -> D | X51: =IF(AND(BalanceN1[[#This Row],[Vérif]]="D",BalanceN1[[#This Row],[BS_Credit]]>0),"A",IF(AND(BalanceN1[[#This Row],[Vérif]]="C",BalanceN1[[#This Row],[BS_Debit]]>0),"A","")) | Y51: =IF(AND(BalanceN1[[#This Row],[Vérif]]="D",BalanceN1[[#This Row],[BE_Credit]]>0),"A",IF(AND(BalanceN1[[#This Row],[Vérif]]="C",BalanceN1[[#This Row],[BE_Debit]]>0),"A",""))
A52: 408100 | B52: Fournisseurs fac. Noo parvenues | D52: 15310306 | E52: 117810569 | F52: 114015470 | H52: 11515207 | I52: =VALUE(LEFT(BalanceN[[#This Row],[Compte]]&"00000000",5)) -> 40810 | J52: {=IF(BalanceN[[#This Row],[Compte]]="",0,_xlfn.IFNA(INDEX(Plan_Comptable[[Table de Compte]:[Sens]],MATCH(VALUE(LEFT(BalanceN[[#This Row],[Table]],4)),VALUE(Plan_Comptable[Table de Compte]),0),2),"A"))} -> C | K52: =IF(AND(BalanceN[[#This Row],[Vérif]]="D",BalanceN[[#This Row],[BS_Credit]]>0),"A",IF(AND(BalanceN[[#This Row],[Vérif]]="C",BalanceN[[#This Row],[BS_Debit]]>0),"A","")) | L52: =IF(AND(BalanceN[[#This Row],[Vérif]]="D",BalanceN[[#This Row],[BE_Credit]]>0),"A",IF(AND(BalanceN[[#This Row],[Vérif]]="C",BalanceN[[#This Row],[BE_Debit]]>0),"A","")) | N52: 416200 | O52: Créances douteuses | P52: 31677520 | T52: 31677520 | V52: =VALUE(LEFT(BalanceN1[[#This Row],[Compte]]&"00000000",5)) -> 41620 | W52: {=IF(BalanceN1[[#This Row],[Compte]]="",0,_xlfn.IFNA(INDEX(Plan_Comptable[[Table de Compte]:[Sens]],MATCH(VALUE(LEFT(BalanceN1[[#This Row],[Table]],4)),VALUE(Plan_Comptable[Table de Compte]),0),2),"A"))} -> D | X52: =IF(AND(BalanceN1[[#This Row],[Vérif]]="D",BalanceN1[[#This Row],[BS_Credit]]>0),"A",IF(AND(BalanceN1[[#This Row],[Vérif]]="C",BalanceN1[[#This Row],[BS_Debit]]>0),"A","")) | Y52: =IF(AND(BalanceN1[[#This Row],[Vérif]]="D",BalanceN1[[#This Row],[BE_Credit]]>0),"A",IF(AND(BalanceN1[[#This Row],[Vérif]]="C",BalanceN1[[#This Row],[BE_Debit]]>0),"A",""))
A53: 409100 | B53: Fournisse urs, avances et acomptes | C53: 700000 | E53: 4007612 | F53: 3850000 | G53: 857612 | I53: =VALUE(LEFT(BalanceN[[#This Row],[Compte]]&"00000000",5)) -> 40910 | J53: {=IF(BalanceN[[#This Row],[Compte]]="",0,_xlfn.IFNA(INDEX(Plan_Comptable[[Table de Compte]:[Sens]],MATCH(VALUE(LEFT(BalanceN[[#This Row],[Table]],4)),VALUE(Plan_Comptable[Table de Compte]),0),2),"A"))} -> D | K53: =IF(AND(BalanceN[[#This Row],[Vérif]]="D",BalanceN[[#This Row],[BS_Credit]]>0),"A",IF(AND(BalanceN[[#This Row],[Vérif]]="C",BalanceN[[#This Row],[BS_Debit]]>0),"A","")) | L53: =IF(AND(BalanceN[[#This Row],[Vérif]]="D",BalanceN[[#This Row],[BE_Credit]]>0),"A",IF(AND(BalanceN[[#This Row],[Vérif]]="C",BalanceN[[#This Row],[BE_Debit]]>0),"A","")) | N53: 4181 | O53: R. R.. Ristournes &avoirs à accorder | P53: 948441 | S53: 948441 | V53: =VALUE(LEFT(BalanceN1[[#This Row],[Compte]]&"00000000",5)) -> 41810 | W53: {=IF(BalanceN1[[#This Row],[Compte]]="",0,_xlfn.IFNA(INDEX(Plan_Comptable[[Table de Compte]:[Sens]],MATCH(VALUE(LEFT(BalanceN1[[#This Row],[Table]],4)),VALUE(Plan_Comptable[Table de Compte]),0),2),"A"))} -> D | X53: =IF(AND(BalanceN1[[#This Row],[Vérif]]="D",BalanceN1[[#This Row],[BS_Credit]]>0),"A",IF(AND(BalanceN1[[#This Row],[Vérif]]="C",BalanceN1[[#This Row],[BS_Debit]]>0),"A","")) | Y53: =IF(AND(BalanceN1[[#This Row],[Vérif]]="D",BalanceN1[[#This Row],[BE_Credit]]>0),"A",IF(AND(BalanceN1[[#This Row],[Vérif]]="C",BalanceN1[[#This Row],[BE_Debit]]>0),"A",""))
A54: 411100 | B54: Clients | C54: 140683833 | E54: 2068782537 | F54: 2073205069 | G54: 136261301 | I54: =VALUE(LEFT(BalanceN[[#This Row],[Compte]]&"00000000",5)) -> 41110 | J54: {=IF(BalanceN[[#This Row],[Compte]]="",0,_xlfn.IFNA(INDEX(Plan_Comptable[[Table de Compte]:[Sens]],MATCH(VALUE(LEFT(BalanceN[[#This Row],[Table]],4)),VALUE(Plan_Comptable[Table de Compte]),0),2),"A"))} -> D | K54: =IF(AND(BalanceN[[#This Row],[Vérif]]="D",BalanceN[[#This Row],[BS_Credit]]>0),"A",IF(AND(BalanceN[[#This Row],[Vérif]]="C",BalanceN[[#This Row],[BS_Debit]]>0),"A","")) | L54: =IF(AND(BalanceN[[#This Row],[Vérif]]="D",BalanceN[[#This Row],[BE_Credit]]>0),"A",IF(AND(BalanceN[[#This Row],[Vérif]]="C",BalanceN[[#This Row],[BE_Debit]]>0),"A","")) | N54: 4212 | O54: Personnel avances &acomptes | P54: 675000 | R54: 5362000 | S54: 5344500 | T54: 692500 | V54: =VALUE(LEFT(BalanceN1[[#This Row],[Compte]]&"00000000",5)) -> 42120 | W54: {=IF(BalanceN1[[#This Row],[Compte]]="",0,_xlfn.IFNA(INDEX(Plan_Comptable[[Table de Compte]:[Sens]],MATCH(VALUE(LEFT(BalanceN1[[#This Row],[Table]],4)),VALUE(Plan_Comptable[Table de Compte]),0),2),"A"))} -> D | X54: =IF(AND(BalanceN1[[#This Row],[Vérif]]="D",BalanceN1[[#This Row],[BS_Credit]]>0),"A",IF(AND(BalanceN1[[#This Row],[Vérif]]="C",BalanceN1[[#This Row],[BS_Debit]]>0),"A","")) | Y54: =IF(AND(BalanceN1[[#This Row],[Vérif]]="D",BalanceN1[[#This Row],[BE_Credit]]>0),"A",IF(AND(BalanceN1[[#This Row],[Vérif]]="C",BalanceN1[[#This Row],[BE_Debit]]>0),"A",""))
A55: 416200 | B55: Créances douteuses | C55: 31677520 | G55: 31677520 | I55: =VALUE(LEFT(BalanceN[[#This Row],[Compte]]&"00000000",5)) -> 41620 | J55: {=IF(BalanceN[[#This Row],[Compte]]="",0,_xlfn.IFNA(INDEX(Plan_Comptable[[Table de Compte]:[Sens]],MATCH(VALUE(LEFT(BalanceN[[#This Row],[Table]],4)),VALUE(Plan_Comptable[Table de Compte]),0),2),"A"))} -> D | K55: =IF(AND(BalanceN[[#This Row],[Vérif]]="D",BalanceN[[#This Row],[BS_Credit]]>0),"A",IF(AND(BalanceN[[#This Row],[Vérif]]="C",BalanceN[[#This Row],[BS_Debit]]>0),"A","")) | L55: =IF(AND(BalanceN[[#This Row],[Vérif]]="D",BalanceN[[#This Row],[BE_Credit]]>0),"A",IF(AND(BalanceN[[#This Row],[Vérif]]="C",BalanceN[[#This Row],[BE_Debit]]>0),"A","")) | N55: 4213 | O55: Frais médicaux | P55: 1162554 | R55: 1935977 | S55: 2510745 | T55: 587786 | V55: =VALUE(LEFT(BalanceN1[[#This Row],[Compte]]&"00000000",5)) -> 42130 | W55: {=IF(BalanceN1[[#This Row],[Compte]]="",0,_xlfn.IFNA(INDEX(Plan_Comptable[[Table de Compte]:[Sens]],MATCH(VALUE(LEFT(BalanceN1[[#This Row],[Table]],4)),VALUE(Plan_Comptable[Table de Compte]),0),2),"A"))} -> D | X55: =IF(AND(BalanceN1[[#This Row],[Vérif]]="D",BalanceN1[[#This Row],[BS_Credit]]>0),"A",IF(AND(BalanceN1[[#This Row],[Vérif]]="C",BalanceN1[[#This Row],[BS_Debit]]>0),"A","")) | Y55: =IF(AND(BalanceN1[[#This Row],[Vérif]]="D",BalanceN1[[#This Row],[BE_Credit]]>0),"A",IF(AND(BalanceN1[[#This Row],[Vérif]]="C",BalanceN1[[#This Row],[BE_Debit]]>0),"A",""))
A56: 4212 | B56: Personnel avances & acomptes | C56: 692500 | E56: 20740622 | F56: 6330272 | G56: 15102850 | I56: =VALUE(LEFT(BalanceN[[#This Row],[Compte]]&"00000000",5)) -> 42120 | J56: {=IF(BalanceN[[#This Row],[Compte]]="",0,_xlfn.IFNA(INDEX(Plan_Comptable[[Table de Compte]:[Sens]],MATCH(VALUE(LEFT(BalanceN[[#This Row],[Table]],4)),VALUE(Plan_Comptable[Table de Compte]),0),2),"A"))} -> D | K56: =IF(AND(BalanceN[[#This Row],[Vérif]]="D",BalanceN[[#This Row],[BS_Credit]]>0),"A",IF(AND(BalanceN[[#This Row],[Vérif]]="C",BalanceN[[#This Row],[BS_Debit]]>0),"A","")) | L56: =IF(AND(BalanceN[[#This Row],[Vérif]]="D",BalanceN[[#This Row],[BE_Credit]]>0),"A",IF(AND(BalanceN[[#This Row],[Vérif]]="C",BalanceN[[#This Row],[BE_Debit]]>0),"A","")) | N56: 422000 | O56: Personnel rémunérations dues | R56: 130502753 | S56: 131486004 | U56: 983251 | V56: =VALUE(LEFT(BalanceN1[[#This Row],[Compte]]&"00000000",5)) -> 42200 | W56: {=IF(BalanceN1[[#This Row],[Compte]]="",0,_xlfn.IFNA(INDEX(Plan_Comptable[[Table de Compte]:[Sens]],MATCH(VALUE(LEFT(BalanceN1[[#This Row],[Table]],4)),VALUE(Plan_Comptable[Table de Compte]),0),2),"A"))} -> C | X56: =IF(AND(BalanceN1[[#This Row],[Vérif]]="D",BalanceN1[[#This Row],[BS_Credit]]>0),"A",IF(AND(BalanceN1[[#This Row],[Vérif]]="C",BalanceN1[[#This Row],[BS_Debit]]>0),"A","")) | Y56: =IF(AND(BalanceN1[[#This Row],[Vérif]]="D",BalanceN1[[#This Row],[BE_Credit]]>0),"A",IF(AND(BalanceN1[[#This Row],[Vérif]]="C",BalanceN1[[#This Row],[BE_Debit]]>0),"A",""))
A57: 421300 | B57: Personnel frais avances | C57: 587786 | E57: 2856452 | F57: 1625425 | G57: 1818813 | I57: =VALUE(LEFT(BalanceN[[#This Row],[Compte]]&"00000000",5)) -> 42130 | J57: {=IF(BalanceN[[#This Row],[Compte]]="",0,_xlfn.IFNA(INDEX(Plan_Comptable[[Table de Compte]:[Sens]],MATCH(VALUE(LEFT(BalanceN[[#This Row],[Table]],4)),VALUE(Plan_Comptable[Table de Compte]),0),2),"A"))} -> D | K57: =IF(AND(BalanceN[[#This Row],[Vérif]]="D",BalanceN[[#This Row],[BS_Credit]]>0),"A",IF(AND(BalanceN[[#This Row],[Vérif]]="C",BalanceN[[#This Row],[BS_Debit]]>0),"A","")) | L57: =IF(AND(BalanceN[[#This Row],[Vérif]]="D",BalanceN[[#This Row],[BE_Credit]]>0),"A",IF(AND(BalanceN[[#This Row],[Vérif]]="C",BalanceN[[#This Row],[BE_Debit]]>0),"A","")) | N57: 423200 | O57: Personnel saisies- arrêts | Q57: 40000 | R57: 480000 | S57: 480000 | U57: 40000 | V57: =VALUE(LEFT(BalanceN1[[#This Row],[Compte]]&"00000000",5)) -> 42320 | W57: {=IF(BalanceN1[[#This Row],[Compte]]="",0,_xlfn.IFNA(INDEX(Plan_Comptable[[Table de Compte]:[Sens]],MATCH(VALUE(LEFT(BalanceN1[[#This Row],[Table]],4)),VALUE(Plan_Comptable[Table de Compte]),0),2),"A"))} -> 0 | X57: =IF(AND(BalanceN1[[#This Row],[Vérif]]="D",BalanceN1[[#This Row],[BS_Credit]]>0),"A",IF(AND(BalanceN1[[#This Row],[Vérif]]="C",BalanceN1[[#This Row],[BS_Debit]]>0),"A","")) | Y57: =IF(AND(BalanceN1[[#This Row],[Vérif]]="D",BalanceN1[[#This Row],[BE_Credit]]>0),"A",IF(AND(BalanceN1[[#This Row],[Vérif]]="C",BalanceN1[[#This Row],[BE_Debit]]>0),"A",""))
A58: 422000 | B58: Personnel rémunérations dues | D58: 983251 | E58: 106926551 | F58: 106078239 | H58: 134939 | I58: =VALUE(LEFT(BalanceN[[#This Row],[Compte]]&"00000000",5)) -> 42200 | J58: {=IF(BalanceN[[#This Row],[Compte]]="",0,_xlfn.IFNA(INDEX(Plan_Comptable[[Table de Compte]:[Sens]],MATCH(VALUE(LEFT(BalanceN[[#This Row],[Table]],4)),VALUE(Plan_Comptable[Table de Compte]),0),2),"A"))} -> C | K58: =IF(AND(BalanceN[[#This Row],[Vérif]]="D",BalanceN[[#This Row],[BS_Credit]]>0),"A",IF(AND(BalanceN[[#This Row],[Vérif]]="C",BalanceN[[#This Row],[BS_Debit]]>0),"A","")) | L58: =IF(AND(BalanceN[[#This Row],[Vérif]]="D",BalanceN[[#This Row],[BE_Credit]]>0),"A",IF(AND(BalanceN[[#This Row],[Vérif]]="C",BalanceN[[#This Row],[BE_Debit]]>0),"A","")) | N58: 427000 | O58: Personnel dépôts | Q58: 55000 | R58: 166500 | S58: 184000 | U58: 72500 | V58: =VALUE(LEFT(BalanceN1[[#This Row],[Compte]]&"00000000",5)) -> 42700 | W58: {=IF(BalanceN1[[#This Row],[Compte]]="",0,_xlfn.IFNA(INDEX(Plan_Comptable[[Table de Compte]:[Sens]],MATCH(VALUE(LEFT(BalanceN1[[#This Row],[Table]],4)),VALUE(Plan_Comptable[Table de Compte]),0),2),"A"))} -> 0 | X58: =IF(AND(BalanceN1[[#This Row],[Vérif]]="D",BalanceN1[[#This Row],[BS_Credit]]>0),"A",IF(AND(BalanceN1[[#This Row],[Vérif]]="C",BalanceN1[[#This Row],[BS_Debit]]>0),"A","")) | Y58: =IF(AND(BalanceN1[[#This Row],[Vérif]]="D",BalanceN1[[#This Row],[BE_Credit]]>0),"A",IF(AND(BalanceN1[[#This Row],[Vérif]]="C",BalanceN1[[#This Row],[BE_Debit]]>0),"A",""))
A59: 423200 | B59: Personnel saisiesarrêts | D59: 40000 | E59: 520000 | F59: 480000 | I59: =VALUE(LEFT(BalanceN[[#This Row],[Compte]]&"00000000",5)) -> 42320 | J59: {=IF(BalanceN[[#This Row],[Compte]]="",0,_xlfn.IFNA(INDEX(Plan_Comptable[[Table de Compte]:[Sens]],MATCH(VALUE(LEFT(BalanceN[[#This Row],[Table]],4)),VALUE(Plan_Comptable[Table de Compte]),0),2),"A"))} -> 0 | K59: =IF(AND(BalanceN[[#This Row],[Vérif]]="D",BalanceN[[#This Row],[BS_Credit]]>0),"A",IF(AND(BalanceN[[#This Row],[Vérif]]="C",BalanceN[[#This Row],[BS_Debit]]>0),"A","")) | L59: =IF(AND(BalanceN[[#This Row],[Vérif]]="D",BalanceN[[#This Row],[BE_Credit]]>0),"A",IF(AND(BalanceN[[#This Row],[Vérif]]="C",BalanceN[[#This Row],[BE_Debit]]>0),"A","")) | N59: 4286 | O59: Pers locaux congés à payer | Q59: 2303892 | R59: 2303892 | S59: 3057458 | U59: 3057458 | V59: =VALUE(LEFT(BalanceN1[[#This Row],[Compte]]&"00000000",5)) -> 42860 | W59: {=IF(BalanceN1[[#This Row],[Compte]]="",0,_xlfn.IFNA(INDEX(Plan_Comptable[[Table de Compte]:[Sens]],MATCH(VALUE(LEFT(BalanceN1[[#This Row],[Table]],4)),VALUE(Plan_Comptable[Table de Compte]),0),2),"A"))} -> 0 | X59: =IF(AND(BalanceN1[[#This Row],[Vérif]]="D",BalanceN1[[#This Row],[BS_Credit]]>0),"A",IF(AND(BalanceN1[[#This Row],[Vérif]]="C",BalanceN1[[#This Row],[BS_Debit]]>0),"A","")) | Y59: =IF(AND(BalanceN1[[#This Row],[Vérif]]="D",BalanceN1[[#This Row],[BE_Credit]]>0),"A",IF(AND(BalanceN1[[#This Row],[Vérif]]="C",BalanceN1[[#This Row],[BE_Debit]]>0),"A",""))
A60: 424200 | B60: Allocations familiales | E60: 56700 | F60: 56700 | I60: =VALUE(LEFT(BalanceN[[#This Row],[Compte]]&"00000000",5)) -> 42420 | J60: {=IF(BalanceN[[#This Row],[Compte]]="",0,_xlfn.IFNA(INDEX(Plan_Comptable[[Table de Compte]:[Sens]],MATCH(VALUE(LEFT(BalanceN[[#This Row],[Table]],4)),VALUE(Plan_Comptable[Table de Compte]),0),2),"A"))} -> 0 | K60: =IF(AND(BalanceN[[#This Row],[Vérif]]="D",BalanceN[[#This Row],[BS_Credit]]>0),"A",IF(AND(BalanceN[[#This Row],[Vérif]]="C",BalanceN[[#This Row],[BS_Debit]]>0),"A","")) | L60: =IF(AND(BalanceN[[#This Row],[Vérif]]="D",BalanceN[[#This Row],[BE_Credit]]>0),"A",IF(AND(BalanceN[[#This Row],[Vérif]]="C",BalanceN[[#This Row],[BE_Debit]]>0),"A","")) | N60: 4286 | O60: Pers non nat congés à payer | Q60: 1351085 | R60: 1351085 | S60: 955634 | U60: 955634 | V60: =VALUE(LEFT(BalanceN1[[#This Row],[Compte]]&"00000000",5)) -> 42860 | W60: {=IF(BalanceN1[[#This Row],[Compte]]="",0,_xlfn.IFNA(INDEX(Plan_Comptable[[Table de Compte]:[Sens]],MATCH(VALUE(LEFT(BalanceN1[[#This Row],[Table]],4)),VALUE(Plan_Comptable[Table de Compte]),0),2),"A"))} -> 0 | X60: =IF(AND(BalanceN1[[#This Row],[Vérif]]="D",BalanceN1[[#This Row],[BS_Credit]]>0),"A",IF(AND(BalanceN1[[#This Row],[Vérif]]="C",BalanceN1[[#This Row],[BS_Debit]]>0),"A","")) | Y60: =IF(AND(BalanceN1[[#This Row],[Vérif]]="D",BalanceN1[[#This Row],[BE_Credit]]>0),"A",IF(AND(BalanceN1[[#This Row],[Vérif]]="C",BalanceN1[[#This Row],[BE_Debit]]>0),"A",""))
A61: 427000 | B61: Personnel dépôts | D61: 72500 | E61: 197000 | F61: 186500 | H61: 62000 | I61: =VALUE(LEFT(BalanceN[[#This Row],[Compte]]&"00000000",5)) -> 42700 | J61: {=IF(BalanceN[[#This Row],[Compte]]="",0,_xlfn.IFNA(INDEX(Plan_Comptable[[Table de Compte]:[Sens]],MATCH(VALUE(LEFT(BalanceN[[#This Row],[Table]],4)),VALUE(Plan_Comptable[Table de Compte]),0),2),"A"))} -> 0 | K61: =IF(AND(BalanceN[[#This Row],[Vérif]]="D",BalanceN[[#This Row],[BS_Credit]]>0),"A",IF(AND(BalanceN[[#This Row],[Vérif]]="C",BalanceN[[#This Row],[BS_Debit]]>0),"A","")) | L61: =IF(AND(BalanceN[[#This Row],[Vérif]]="D",BalanceN[[#This Row],[BE_Credit]]>0),"A",IF(AND(BalanceN[[#This Row],[Vérif]]="C",BalanceN[[#This Row],[BE_Debit]]>0),"A","")) | N61: 4313 | O61: Caisse sécurité sociale | Q61: 979255 | R61: 7316170 | S61: 7112818 | U61: 775903 | V61: =VALUE(LEFT(BalanceN1[[#This Row],[Compte]]&"00000000",5)) -> 43130 | W61: {=IF(BalanceN1[[#This Row],[Compte]]="",0,_xlfn.IFNA(INDEX(Plan_Comptable[[Table de Compte]:[Sens]],MATCH(VALUE(LEFT(BalanceN1[[#This Row],[Table]],4)),VALUE(Plan_Comptable[Table de Compte]),0),2),"A"))} -> 0 | X61: =IF(AND(BalanceN1[[#This Row],[Vérif]]="D",BalanceN1[[#This Row],[BS_Credit]]>0),"A",IF(AND(BalanceN1[[#This Row],[Vérif]]="C",BalanceN1[[#This Row],[BS_Debit]]>0),"A","")) | Y61: =IF(AND(BalanceN1[[#This Row],[Vérif]]="D",BalanceN1[[#This Row],[BE_Credit]]>0),"A",IF(AND(BalanceN1[[#This Row],[Vérif]]="C",BalanceN1[[#This Row],[BE_Debit]]>0),"A",""))
A62: 428101 | B62: Pers locaux congés à payer | D62: 3057458 | E62: 3057458 | F62: 2690099 | H62: 2690099 | I62: =VALUE(LEFT(BalanceN[[#This Row],[Compte]]&"00000000",5)) -> 42810 | J62: {=IF(BalanceN[[#This Row],[Compte]]="",0,_xlfn.IFNA(INDEX(Plan_Comptable[[Table de Compte]:[Sens]],MATCH(VALUE(LEFT(BalanceN[[#This Row],[Table]],4)),VALUE(Plan_Comptable[Table de Compte]),0),2),"A"))} -> 0 | K62: =IF(AND(BalanceN[[#This Row],[Vérif]]="D",BalanceN[[#This Row],[BS_Credit]]>0),"A",IF(AND(BalanceN[[#This Row],[Vérif]]="C",BalanceN[[#This Row],[BS_Debit]]>0),"A","")) | L62: =IF(AND(BalanceN[[#This Row],[Vérif]]="D",BalanceN[[#This Row],[BE_Credit]]>0),"A",IF(AND(BalanceN[[#This Row],[Vérif]]="C",BalanceN[[#This Row],[BE_Debit]]>0),"A","")) | N62: 431300 | O62: Caisse de retraite | Q62: 1161181 | R62: 13328375 | S62: 13417004 | U62: 1249810 | V62: =VALUE(LEFT(BalanceN1[[#This Row],[Compte]]&"00000000",5)) -> 43130 | W62: {=IF(BalanceN1[[#This Row],[Compte]]="",0,_xlfn.IFNA(INDEX(Plan_Comptable[[Table de Compte]:[Sens]],MATCH(VALUE(LEFT(BalanceN1[[#This Row],[Table]],4)),VALUE(Plan_Comptable[Table de Compte]),0),2),"A"))} -> 0 | X62: =IF(AND(BalanceN1[[#This Row],[Vérif]]="D",BalanceN1[[#This Row],[BS_Credit]]>0),"A",IF(AND(BalanceN1[[#This Row],[Vérif]]="C",BalanceN1[[#This Row],[BS_Debit]]>0),"A","")) | Y62: =IF(AND(BalanceN1[[#This Row],[Vérif]]="D",BalanceN1[[#This Row],[BE_Credit]]>0),"A",IF(AND(BalanceN1[[#This Row],[Vérif]]="C",BalanceN1[[#This Row],[BE_Debit]]>0),"A",""))
A63: 428102 | B63: Pers non national congés à payer | D63: 955634 | E63: 955634 | F63: 956541 | H63: 956541 | I63: =VALUE(LEFT(BalanceN[[#This Row],[Compte]]&"00000000",5)) -> 42810 | J63: {=IF(BalanceN[[#This Row],[Compte]]="",0,_xlfn.IFNA(INDEX(Plan_Comptable[[Table de Compte]:[Sens]],MATCH(VALUE(LEFT(BalanceN[[#This Row],[Table]],4)),VALUE(Plan_Comptable[Table de Compte]),0),2),"A"))} -> 0 | K63: =IF(AND(BalanceN[[#This Row],[Vérif]]="D",BalanceN[[#This Row],[BS_Credit]]>0),"A",IF(AND(BalanceN[[#This Row],[Vérif]]="C",BalanceN[[#This Row],[BS_Debit]]>0),"A","")) | L63: =IF(AND(BalanceN[[#This Row],[Vérif]]="D",BalanceN[[#This Row],[BE_Credit]]>0),"A",IF(AND(BalanceN[[#This Row],[Vérif]]="C",BalanceN[[#This Row],[BE_Debit]]>0),"A","")) | N63: 433110 | O63: Mutuelle de sanie | Q63: 587724 | R63: 3657726 | S63: 3540003 | U63: 470001 | V63: =VALUE(LEFT(BalanceN1[[#This Row],[Compte]]&"00000000",5)) -> 43311 | W63: {=IF(BalanceN1[[#This Row],[Compte]]="",0,_xlfn.IFNA(INDEX(Plan_Comptable[[Table de Compte]:[Sens]],MATCH(VALUE(LEFT(BalanceN1[[#This Row],[Table]],4)),VALUE(Plan_Comptable[Table de Compte]),0),2),"A"))} -> 0 | X63: =IF(AND(BalanceN1[[#This Row],[Vérif]]="D",BalanceN1[[#This Row],[BS_Credit]]>0),"A",IF(AND(BalanceN1[[#This Row],[Vérif]]="C",BalanceN1[[#This Row],[BS_Debit]]>0),"A","")) | Y63: =IF(AND(BalanceN1[[#This Row],[Vérif]]="D",BalanceN1[[#This Row],[BE_Credit]]>0),"A",IF(AND(BalanceN1[[#This Row],[Vérif]]="C",BalanceN1[[#This Row],[BE_Debit]]>0),"A",""))
A64: 4313 | B64: Caisse sécurité sociale | D64: 775903 | E64: 7301357 | F64: 7148050 | H64: 622596 | I64: =VALUE(LEFT(BalanceN[[#This Row],[Compte]]&"00000000",5)) -> 43130 | J64: {=IF(BalanceN[[#This Row],[Compte]]="",0,_xlfn.IFNA(INDEX(Plan_Comptable[[Table de Compte]:[Sens]],MATCH(VALUE(LEFT(BalanceN[[#This Row],[Table]],4)),VALUE(Plan_Comptable[Table de Compte]),0),2),"A"))} -> 0 | K64: =IF(AND(BalanceN[[#This Row],[Vérif]]="D",BalanceN[[#This Row],[BS_Credit]]>0),"A",IF(AND(BalanceN[[#This Row],[Vérif]]="C",BalanceN[[#This Row],[BS_Debit]]>0),"A","")) | L64: =IF(AND(BalanceN[[#This Row],[Vérif]]="D",BalanceN[[#This Row],[BE_Credit]]>0),"A",IF(AND(BalanceN[[#This Row],[Vérif]]="C",BalanceN[[#This Row],[BE_Debit]]>0),"A","")) | N64: 438200 | O64: Charges sociales / congés | Q64: 506047 | R64: 506047 | S64: 508585 | U64: 508585 | V64: =VALUE(LEFT(BalanceN1[[#This Row],[Compte]]&"00000000",5)) -> 43820 | W64: {=IF(BalanceN1[[#This Row],[Compte]]="",0,_xlfn.IFNA(INDEX(Plan_Comptable[[Table de Compte]:[Sens]],MATCH(VALUE(LEFT(BalanceN1[[#This Row],[Table]],4)),VALUE(Plan_Comptable[Table de Compte]),0),2),"A"))} -> 0 | X64: =IF(AND(BalanceN1[[#This Row],[Vérif]]="D",BalanceN1[[#This Row],[BS_Credit]]>0),"A",IF(AND(BalanceN1[[#This Row],[Vérif]]="C",BalanceN1[[#This Row],[BS_Debit]]>0),"A","")) | Y64: =IF(AND(BalanceN1[[#This Row],[Vérif]]="D",BalanceN1[[#This Row],[BE_Credit]]>0),"A",IF(AND(BalanceN1[[#This Row],[Vérif]]="C",BalanceN1[[#This Row],[BE_Debit]]>0),"A",""))
A65: 431300 | B65: Caisse de retraite | D65: 1249810 | E65: 13665738 | F65: 13921213 | H65: 1505285 | I65: =VALUE(LEFT(BalanceN[[#This Row],[Compte]]&"00000000",5)) -> 43130 | J65: {=IF(BalanceN[[#This Row],[Compte]]="",0,_xlfn.IFNA(INDEX(Plan_Comptable[[Table de Compte]:[Sens]],MATCH(VALUE(LEFT(BalanceN[[#This Row],[Table]],4)),VALUE(Plan_Comptable[Table de Compte]),0),2),"A"))} -> 0 | K65: =IF(AND(BalanceN[[#This Row],[Vérif]]="D",BalanceN[[#This Row],[BS_Credit]]>0),"A",IF(AND(BalanceN[[#This Row],[Vérif]]="C",BalanceN[[#This Row],[BS_Debit]]>0),"A","")) | L65: =IF(AND(BalanceN[[#This Row],[Vérif]]="D",BalanceN[[#This Row],[BE_Credit]]>0),"A",IF(AND(BalanceN[[#This Row],[Vérif]]="C",BalanceN[[#This Row],[BE_Debit]]>0),"A","")) | N65: 441 | O65: Etat impôt sur les sociétés | Q65: 9098000 | R65: 9098000 | S65: 23411413 | U65: 23411413 | V65: =VALUE(LEFT(BalanceN1[[#This Row],[Compte]]&"00000000",5)) -> 44100 | W65: {=IF(BalanceN1[[#This Row],[Compte]]="",0,_xlfn.IFNA(INDEX(Plan_Comptable[[Table de Compte]:[Sens]],MATCH(VALUE(LEFT(BalanceN1[[#This Row],[Table]],4)),VALUE(Plan_Comptable[Table de Compte]),0),2),"A"))} -> 0 | X65: =IF(AND(BalanceN1[[#This Row],[Vérif]]="D",BalanceN1[[#This Row],[BS_Credit]]>0),"A",IF(AND(BalanceN1[[#This Row],[Vérif]]="C",BalanceN1[[#This Row],[BS_Debit]]>0),"A","")) | Y65: =IF(AND(BalanceN1[[#This Row],[Vérif]]="D",BalanceN1[[#This Row],[BE_Credit]]>0),"A",IF(AND(BalanceN1[[#This Row],[Vérif]]="C",BalanceN1[[#This Row],[BE_Debit]]>0),"A",""))
A66: 433110 | B66: Mutuelle de sante | D66: 470001 | E66: 3704942 | F66: 3539940 | H66: 304999 | I66: =VALUE(LEFT(BalanceN[[#This Row],[Compte]]&"00000000",5)) -> 43311 | J66: {=IF(BalanceN[[#This Row],[Compte]]="",0,_xlfn.IFNA(INDEX(Plan_Comptable[[Table de Compte]:[Sens]],MATCH(VALUE(LEFT(BalanceN[[#This Row],[Table]],4)),VALUE(Plan_Comptable[Table de Compte]),0),2),"A"))} -> 0 | K66: =IF(AND(BalanceN[[#This Row],[Vérif]]="D",BalanceN[[#This Row],[BS_Credit]]>0),"A",IF(AND(BalanceN[[#This Row],[Vérif]]="C",BalanceN[[#This Row],[BS_Debit]]>0),"A","")) | L66: =IF(AND(BalanceN[[#This Row],[Vérif]]="D",BalanceN[[#This Row],[BE_Credit]]>0),"A",IF(AND(BalanceN[[#This Row],[Vérif]]="C",BalanceN[[#This Row],[BE_Debit]]>0),"A","")) | N66: 442100 | O66: Etat impôts et taxes | Q66: 2752200 | R66: 114048 | S66: 574992 | U66: 3213144 | V66: =VALUE(LEFT(BalanceN1[[#This Row],[Compte]]&"00000000",5)) -> 44210 | W66: {=IF(BalanceN1[[#This Row],[Compte]]="",0,_xlfn.IFNA(INDEX(Plan_Comptable[[Table de Compte]:[Sens]],MATCH(VALUE(LEFT(BalanceN1[[#This Row],[Table]],4)),VALUE(Plan_Comptable[Table de Compte]),0),2),"A"))} -> 0 | X66: =IF(AND(BalanceN1[[#This Row],[Vérif]]="D",BalanceN1[[#This Row],[BS_Credit]]>0),"A",IF(AND(BalanceN1[[#This Row],[Vérif]]="C",BalanceN1[[#This Row],[BS_Debit]]>0),"A","")) | Y66: =IF(AND(BalanceN1[[#This Row],[Vérif]]="D",BalanceN1[[#This Row],[BE_Credit]]>0),"A",IF(AND(BalanceN1[[#This Row],[Vérif]]="C",BalanceN1[[#This Row],[BE_Debit]]>0),"A",""))
A67: 438200 | B67: Charges sociales / congés | D67: 508585 | E67: 508585 | F67: 479581 | H67: 479581 | I67: =VALUE(LEFT(BalanceN[[#This Row],[Compte]]&"00000000",5)) -> 43820 | J67: {=IF(BalanceN[[#This Row],[Compte]]="",0,_xlfn.IFNA(INDEX(Plan_Comptable[[Table de Compte]:[Sens]],MATCH(VALUE(LEFT(BalanceN[[#This Row],[Table]],4)),VALUE(Plan_Comptable[Table de Compte]),0),2),"A"))} -> 0 | K67: =IF(AND(BalanceN[[#This Row],[Vérif]]="D",BalanceN[[#This Row],[BS_Credit]]>0),"A",IF(AND(BalanceN[[#This Row],[Vérif]]="C",BalanceN[[#This Row],[BS_Debit]]>0),"A","")) | L67: =IF(AND(BalanceN[[#This Row],[Vérif]]="D",BalanceN[[#This Row],[BE_Credit]]>0),"A",IF(AND(BalanceN[[#This Row],[Vérif]]="C",BalanceN[[#This Row],[BE_Debit]]>0),"A","")) | N67: 443200 | O67: Tva facturée / prestation services | Q67: 54049 | R67: 252049 | S67: 287781 | U67: 89781 | V67: =VALUE(LEFT(BalanceN1[[#This Row],[Compte]]&"00000000",5)) -> 44320 | W67: {=IF(BalanceN1[[#This Row],[Compte]]="",0,_xlfn.IFNA(INDEX(Plan_Comptable[[Table de Compte]:[Sens]],MATCH(VALUE(LEFT(BalanceN1[[#This Row],[Table]],4)),VALUE(Plan_Comptable[Table de Compte]),0),2),"A"))} -> 0 | X67: =IF(AND(BalanceN1[[#This Row],[Vérif]]="D",BalanceN1[[#This Row],[BS_Credit]]>0),"A",IF(AND(BalanceN1[[#This Row],[Vérif]]="C",BalanceN1[[#This Row],[BS_Debit]]>0),"A","")) | Y67: =IF(AND(BalanceN1[[#This Row],[Vérif]]="D",BalanceN1[[#This Row],[BE_Credit]]>0),"A",IF(AND(BalanceN1[[#This Row],[Vérif]]="C",BalanceN1[[#This Row],[BE_Debit]]>0),"A",""))
A68: 441 | B68: Etat impôt sur les sociétés | D68: 23411413 | E68: 23411413 | F68: 31102200 | H68: 31102200 | I68: =VALUE(LEFT(BalanceN[[#This Row],[Compte]]&"00000000",5)) -> 44100 | J68: {=IF(BalanceN[[#This Row],[Compte]]="",0,_xlfn.IFNA(INDEX(Plan_Comptable[[Table de Compte]:[Sens]],MATCH(VALUE(LEFT(BalanceN[[#This Row],[Table]],4)),VALUE(Plan_Comptable[Table de Compte]),0),2),"A"))} -> 0 | K68: =IF(AND(BalanceN[[#This Row],[Vérif]]="D",BalanceN[[#This Row],[BS_Credit]]>0),"A",IF(AND(BalanceN[[#This Row],[Vérif]]="C",BalanceN[[#This Row],[BS_Debit]]>0),"A","")) | L68: =IF(AND(BalanceN[[#This Row],[Vérif]]="D",BalanceN[[#This Row],[BE_Credit]]>0),"A",IF(AND(BalanceN[[#This Row],[Vérif]]="C",BalanceN[[#This Row],[BE_Debit]]>0),"A","")) | N68: 4472 | O68: Etat impôts retenue à la source personnel | Q68: 596627 | R68: 12424778 | S68: 12894469 | U68: 1066318 | V68: =VALUE(LEFT(BalanceN1[[#This Row],[Compte]]&"00000000",5)) -> 44720 | W68: {=IF(BalanceN1[[#This Row],[Compte]]="",0,_xlfn.IFNA(INDEX(Plan_Comptable[[Table de Compte]:[Sens]],MATCH(VALUE(LEFT(BalanceN1[[#This Row],[Table]],4)),VALUE(Plan_Comptable[Table de Compte]),0),2),"A"))} -> 0 | X68: =IF(AND(BalanceN1[[#This Row],[Vérif]]="D",BalanceN1[[#This Row],[BS_Credit]]>0),"A",IF(AND(BalanceN1[[#This Row],[Vérif]]="C",BalanceN1[[#This Row],[BS_Debit]]>0),"A","")) | Y68: =IF(AND(BalanceN1[[#This Row],[Vérif]]="D",BalanceN1[[#This Row],[BE_Credit]]>0),"A",IF(AND(BalanceN1[[#This Row],[Vérif]]="C",BalanceN1[[#This Row],[BE_Debit]]>0),"A",""))
A69: 442100 | B69: Etat impôts et taxes | D69: 3213144 | F69: 456192 | H69: 3669336 | I69: =VALUE(LEFT(BalanceN[[#This Row],[Compte]]&"00000000",5)) -> 44210 | J69: {=IF(BalanceN[[#This Row],[Compte]]="",0,_xlfn.IFNA(INDEX(Plan_Comptable[[Table de Compte]:[Sens]],MATCH(VALUE(LEFT(BalanceN[[#This Row],[Table]],4)),VALUE(Plan_Comptable[Table de Compte]),0),2),"A"))} -> 0 | K69: =IF(AND(BalanceN[[#This Row],[Vérif]]="D",BalanceN[[#This Row],[BS_Credit]]>0),"A",IF(AND(BalanceN[[#This Row],[Vérif]]="C",BalanceN[[#This Row],[BS_Debit]]>0),"A","")) | L69: =IF(AND(BalanceN[[#This Row],[Vérif]]="D",BalanceN[[#This Row],[BE_Credit]]>0),"A",IF(AND(BalanceN[[#This Row],[Vérif]]="C",BalanceN[[#This Row],[BE_Debit]]>0),"A","")) | N69: 447200 | O69: Etal retenue à la source prestataire | Q69: 90750 | R69: 870129 | S69: 895879 | U69: 116500 | V69: =VALUE(LEFT(BalanceN1[[#This Row],[Compte]]&"00000000",5)) -> 44720 | W69: {=IF(BalanceN1[[#This Row],[Compte]]="",0,_xlfn.IFNA(INDEX(Plan_Comptable[[Table de Compte]:[Sens]],MATCH(VALUE(LEFT(BalanceN1[[#This Row],[Table]],4)),VALUE(Plan_Comptable[Table de Compte]),0),2),"A"))} -> 0 | X69: =IF(AND(BalanceN1[[#This Row],[Vérif]]="D",BalanceN1[[#This Row],[BS_Credit]]>0),"A",IF(AND(BalanceN1[[#This Row],[Vérif]]="C",BalanceN1[[#This Row],[BS_Debit]]>0),"A","")) | Y69: =IF(AND(BalanceN1[[#This Row],[Vérif]]="D",BalanceN1[[#This Row],[BE_Credit]]>0),"A",IF(AND(BalanceN1[[#This Row],[Vérif]]="C",BalanceN1[[#This Row],[BE_Debit]]>0),"A",""))
A70: 443200 | B70: Etat tva facrurée | D70: 89781 | E70: 316062 | F70: 226281 | I70: =VALUE(LEFT(BalanceN[[#This Row],[Compte]]&"00000000",5)) -> 44320 | J70: {=IF(BalanceN[[#This Row],[Compte]]="",0,_xlfn.IFNA(INDEX(Plan_Comptable[[Table de Compte]:[Sens]],MATCH(VALUE(LEFT(BalanceN[[#This Row],[Table]],4)),VALUE(Plan_Comptable[Table de Compte]),0),2),"A"))} -> 0 | K70: =IF(AND(BalanceN[[#This Row],[Vérif]]="D",BalanceN[[#This Row],[BS_Credit]]>0),"A",IF(AND(BalanceN[[#This Row],[Vérif]]="C",BalanceN[[#This Row],[BS_Debit]]>0),"A","")) | L70: =IF(AND(BalanceN[[#This Row],[Vérif]]="D",BalanceN[[#This Row],[BE_Credit]]>0),"A",IF(AND(BalanceN[[#This Row],[Vérif]]="C",BalanceN[[#This Row],[BE_Debit]]>0),"A","")) | N70: 4621 | O70: Compte courant associés | Q70: 10336159 | R70: 40643970 | S70: 40246770 | U70: 9938959 | V70: =VALUE(LEFT(BalanceN1[[#This Row],[Compte]]&"00000000",5)) -> 46210 | W70: {=IF(BalanceN1[[#This Row],[Compte]]="",0,_xlfn.IFNA(INDEX(Plan_Comptable[[Table de Compte]:[Sens]],MATCH(VALUE(LEFT(BalanceN1[[#This Row],[Table]],4)),VALUE(Plan_Comptable[Table de Compte]),0),2),"A"))} -> 0 | X70: =IF(AND(BalanceN1[[#This Row],[Vérif]]="D",BalanceN1[[#This Row],[BS_Credit]]>0),"A",IF(AND(BalanceN1[[#This Row],[Vérif]]="C",BalanceN1[[#This Row],[BS_Debit]]>0),"A","")) | Y70: =IF(AND(BalanceN1[[#This Row],[Vérif]]="D",BalanceN1[[#This Row],[BE_Credit]]>0),"A",IF(AND(BalanceN1[[#This Row],[Vérif]]="C",BalanceN1[[#This Row],[BE_Debit]]>0),"A",""))
A71: 444100 | B71: Etat tva due | E71: 226281 | F71: 226281 | I71: =VALUE(LEFT(BalanceN[[#This Row],[Compte]]&"00000000",5)) -> 44410 | J71: {=IF(BalanceN[[#This Row],[Compte]]="",0,_xlfn.IFNA(INDEX(Plan_Comptable[[Table de Compte]:[Sens]],MATCH(VALUE(LEFT(BalanceN[[#This Row],[Table]],4)),VALUE(Plan_Comptable[Table de Compte]),0),2),"A"))} -> 0 | K71: =IF(AND(BalanceN[[#This Row],[Vérif]]="D",BalanceN[[#This Row],[BS_Credit]]>0),"A",IF(AND(BalanceN[[#This Row],[Vérif]]="C",BalanceN[[#This Row],[BS_Debit]]>0),"A","")) | L71: =IF(AND(BalanceN[[#This Row],[Vérif]]="D",BalanceN[[#This Row],[BE_Credit]]>0),"A",IF(AND(BalanceN[[#This Row],[Vérif]]="C",BalanceN[[#This Row],[BE_Debit]]>0),"A","")) | N71: 465000 | O71: Compte courant associés | R71: 40000000 | S71: 40000000 | V71: =VALUE(LEFT(BalanceN1[[#This Row],[Compte]]&"00000000",5)) -> 46500 | W71: {=IF(BalanceN1[[#This Row],[Compte]]="",0,_xlfn.IFNA(INDEX(Plan_Comptable[[Table de Compte]:[Sens]],MATCH(VALUE(LEFT(BalanceN1[[#This Row],[Table]],4)),VALUE(Plan_Comptable[Table de Compte]),0),2),"A"))} -> 0 | X71: =IF(AND(BalanceN1[[#This Row],[Vérif]]="D",BalanceN1[[#This Row],[BS_Credit]]>0),"A",IF(AND(BalanceN1[[#This Row],[Vérif]]="C",BalanceN1[[#This Row],[BS_Debit]]>0),"A","")) | Y71: =IF(AND(BalanceN1[[#This Row],[Vérif]]="D",BalanceN1[[#This Row],[BE_Credit]]>0),"A",IF(AND(BalanceN1[[#This Row],[Vérif]]="C",BalanceN1[[#This Row],[BE_Debit]]>0),"A",""))
A72: 4472 | B72: Etal impôts retenue à la source | D72: 1182818 | E72: 15162688 | F72: 15120541 | H72: 1140671 | I72: =VALUE(LEFT(BalanceN[[#This Row],[Compte]]&"00000000",5)) -> 44720 | J72: {=IF(BalanceN[[#This Row],[Compte]]="",0,_xlfn.IFNA(INDEX(Plan_Comptable[[Table de Compte]:[Sens]],MATCH(VALUE(LEFT(BalanceN[[#This Row],[Table]],4)),VALUE(Plan_Comptable[Table de Compte]),0),2),"A"))} -> 0 | K72: =IF(AND(BalanceN[[#This Row],[Vérif]]="D",BalanceN[[#This Row],[BS_Credit]]>0),"A",IF(AND(BalanceN[[#This Row],[Vérif]]="C",BalanceN[[#This Row],[BS_Debit]]>0),"A","")) | L72: =IF(AND(BalanceN[[#This Row],[Vérif]]="D",BalanceN[[#This Row],[BE_Credit]]>0),"A",IF(AND(BalanceN[[#This Row],[Vérif]]="C",BalanceN[[#This Row],[BE_Debit]]>0),"A","")) | N72: 471100 | O72: Débiteurs divers | Q72: 10000000 | R72: 10650000 | S72: 200000 | T72: 450000 | V72: =VALUE(LEFT(BalanceN1[[#This Row],[Compte]]&"00000000",5)) -> 47110 | W72: {=IF(BalanceN1[[#This Row],[Compte]]="",0,_xlfn.IFNA(INDEX(Plan_Comptable[[Table de Compte]:[Sens]],MATCH(VALUE(LEFT(BalanceN1[[#This Row],[Table]],4)),VALUE(Plan_Comptable[Table de Compte]),0),2),"A"))} -> 0 | X72: =IF(AND(BalanceN1[[#This Row],[Vérif]]="D",BalanceN1[[#This Row],[BS_Credit]]>0),"A",IF(AND(BalanceN1[[#This Row],[Vérif]]="C",BalanceN1[[#This Row],[BS_Debit]]>0),"A","")) | Y72: =IF(AND(BalanceN1[[#This Row],[Vérif]]="D",BalanceN1[[#This Row],[BE_Credit]]>0),"A",IF(AND(BalanceN1[[#This Row],[Vérif]]="C",BalanceN1[[#This Row],[BE_Debit]]>0),"A",""))
A73: 4621 | B73: Compte courant associés | D73: 9938959 | E73: 33999957 | F73: 4060998 | G73: 20000000 | I73: =VALUE(LEFT(BalanceN[[#This Row],[Compte]]&"00000000",5)) -> 46210 | J73: {=IF(BalanceN[[#This Row],[Compte]]="",0,_xlfn.IFNA(INDEX(Plan_Comptable[[Table de Compte]:[Sens]],MATCH(VALUE(LEFT(BalanceN[[#This Row],[Table]],4)),VALUE(Plan_Comptable[Table de Compte]),0),2),"A"))} -> 0 | K73: =IF(AND(BalanceN[[#This Row],[Vérif]]="D",BalanceN[[#This Row],[BS_Credit]]>0),"A",IF(AND(BalanceN[[#This Row],[Vérif]]="C",BalanceN[[#This Row],[BS_Debit]]>0),"A","")) | L73: =IF(AND(BalanceN[[#This Row],[Vérif]]="D",BalanceN[[#This Row],[BE_Credit]]>0),"A",IF(AND(BalanceN[[#This Row],[Vérif]]="C",BalanceN[[#This Row],[BE_Debit]]>0),"A","")) | N73: 471300 | O73: Crédileurs divers | Q73: 530000 | R73: 4120000 | S73: 4300000 | U73: 710000 | V73: =VALUE(LEFT(BalanceN1[[#This Row],[Compte]]&"00000000",5)) -> 47130 | W73: {=IF(BalanceN1[[#This Row],[Compte]]="",0,_xlfn.IFNA(INDEX(Plan_Comptable[[Table de Compte]:[Sens]],MATCH(VALUE(LEFT(BalanceN1[[#This Row],[Table]],4)),VALUE(Plan_Comptable[Table de Compte]),0),2),"A"))} -> 0 | X73: =IF(AND(BalanceN1[[#This Row],[Vérif]]="D",BalanceN1[[#This Row],[BS_Credit]]>0),"A",IF(AND(BalanceN1[[#This Row],[Vérif]]="C",BalanceN1[[#This Row],[BS_Debit]]>0),"A","")) | Y73: =IF(AND(BalanceN1[[#This Row],[Vérif]]="D",BalanceN1[[#This Row],[BE_Credit]]>0),"A",IF(AND(BalanceN1[[#This Row],[Vérif]]="C",BalanceN1[[#This Row],[BE_Debit]]>0),"A",""))
A74: 465000 | B74: Associés dividendes à payer | E74: 90000000 | F74: 90000000 | I74: =VALUE(LEFT(BalanceN[[#This Row],[Compte]]&"00000000",5)) -> 46500 | J74: {=IF(BalanceN[[#This Row],[Compte]]="",0,_xlfn.IFNA(INDEX(Plan_Comptable[[Table de Compte]:[Sens]],MATCH(VALUE(LEFT(BalanceN[[#This Row],[Table]],4)),VALUE(Plan_Comptable[Table de Compte]),0),2),"A"))} -> 0 | K74: =IF(AND(BalanceN[[#This Row],[Vérif]]="D",BalanceN[[#This Row],[BS_Credit]]>0),"A",IF(AND(BalanceN[[#This Row],[Vérif]]="C",BalanceN[[#This Row],[BS_Debit]]>0),"A","")) | L74: =IF(AND(BalanceN[[#This Row],[Vérif]]="D",BalanceN[[#This Row],[BE_Credit]]>0),"A",IF(AND(BalanceN[[#This Row],[Vérif]]="C",BalanceN[[#This Row],[BE_Debit]]>0),"A","")) | N74: 476000 | O74: Charges constatées d'avance | P74: 2255622 | R74: 5310480 | S74: 6168003 | T74: 1398099 | V74: =VALUE(LEFT(BalanceN1[[#This Row],[Compte]]&"00000000",5)) -> 47600 | W74: {=IF(BalanceN1[[#This Row],[Compte]]="",0,_xlfn.IFNA(INDEX(Plan_Comptable[[Table de Compte]:[Sens]],MATCH(VALUE(LEFT(BalanceN1[[#This Row],[Table]],4)),VALUE(Plan_Comptable[Table de Compte]),0),2),"A"))} -> D | X74: =IF(AND(BalanceN1[[#This Row],[Vérif]]="D",BalanceN1[[#This Row],[BS_Credit]]>0),"A",IF(AND(BalanceN1[[#This Row],[Vérif]]="C",BalanceN1[[#This Row],[BS_Debit]]>0),"A","")) | Y74: =IF(AND(BalanceN1[[#This Row],[Vérif]]="D",BalanceN1[[#This Row],[BE_Credit]]>0),"A",IF(AND(BalanceN1[[#This Row],[Vérif]]="C",BalanceN1[[#This Row],[BE_Debit]]>0),"A",""))
A75: 467000 | B75: Apporteurs restant dfi sur capital appel é | E75: 200000000 | F75: 200000000 | I75: =VALUE(LEFT(BalanceN[[#This Row],[Compte]]&"00000000",5)) -> 46700 | J75: {=IF(BalanceN[[#This Row],[Compte]]="",0,_xlfn.IFNA(INDEX(Plan_Comptable[[Table de Compte]:[Sens]],MATCH(VALUE(LEFT(BalanceN[[#This Row],[Table]],4)),VALUE(Plan_Comptable[Table de Compte]),0),2),"A"))} -> 0 | K75: =IF(AND(BalanceN[[#This Row],[Vérif]]="D",BalanceN[[#This Row],[BS_Credit]]>0),"A",IF(AND(BalanceN[[#This Row],[Vérif]]="C",BalanceN[[#This Row],[BS_Debit]]>0),"A","")) | L75: =IF(AND(BalanceN[[#This Row],[Vérif]]="D",BalanceN[[#This Row],[BE_Credit]]>0),"A",IF(AND(BalanceN[[#This Row],[Vérif]]="C",BalanceN[[#This Row],[BE_Debit]]>0),"A","")) | N75: 477000 | O75: Produits constatés d'avance | R75: 1056000 | S75: 1056000 | V75: =VALUE(LEFT(BalanceN1[[#This Row],[Compte]]&"00000000",5)) -> 47700 | W75: {=IF(BalanceN1[[#This Row],[Compte]]="",0,_xlfn.IFNA(INDEX(Plan_Comptable[[Table de Compte]:[Sens]],MATCH(VALUE(LEFT(BalanceN1[[#This Row],[Table]],4)),VALUE(Plan_Comptable[Table de Compte]),0),2),"A"))} -> C | X75: =IF(AND(BalanceN1[[#This Row],[Vérif]]="D",BalanceN1[[#This Row],[BS_Credit]]>0),"A",IF(AND(BalanceN1[[#This Row],[Vérif]]="C",BalanceN1[[#This Row],[BS_Debit]]>0),"A","")) | Y75: =IF(AND(BalanceN1[[#This Row],[Vérif]]="D",BalanceN1[[#This Row],[BE_Credit]]>0),"A",IF(AND(BalanceN1[[#This Row],[Vérif]]="C",BalanceN1[[#This Row],[BE_Debit]]>0),"A",""))
A76: 471100 | B76: Débiteurs divers | C76: 450000 | E76: 13050 | F76: 463050 | I76: =VALUE(LEFT(BalanceN[[#This Row],[Compte]]&"00000000",5)) -> 47110 | J76: {=IF(BalanceN[[#This Row],[Compte]]="",0,_xlfn.IFNA(INDEX(Plan_Comptable[[Table de Compte]:[Sens]],MATCH(VALUE(LEFT(BalanceN[[#This Row],[Table]],4)),VALUE(Plan_Comptable[Table de Compte]),0),2),"A"))} -> 0 | K76: =IF(AND(BalanceN[[#This Row],[Vérif]]="D",BalanceN[[#This Row],[BS_Credit]]>0),"A",IF(AND(BalanceN[[#This Row],[Vérif]]="C",BalanceN[[#This Row],[BS_Debit]]>0),"A","")) | L76: =IF(AND(BalanceN[[#This Row],[Vérif]]="D",BalanceN[[#This Row],[BE_Credit]]>0),"A",IF(AND(BalanceN[[#This Row],[Vérif]]="C",BalanceN[[#This Row],[BE_Debit]]>0),"A","")) | N76: 481800 | O76: Fours d'invest. Fnp | S76: 399942 | U76: 399942 | V76: =VALUE(LEFT(BalanceN1[[#This Row],[Compte]]&"00000000",5)) -> 48180 | W76: {=IF(BalanceN1[[#This Row],[Compte]]="",0,_xlfn.IFNA(INDEX(Plan_Comptable[[Table de Compte]:[Sens]],MATCH(VALUE(LEFT(BalanceN1[[#This Row],[Table]],4)),VALUE(Plan_Comptable[Table de Compte]),0),2),"A"))} -> C | X76: =IF(AND(BalanceN1[[#This Row],[Vérif]]="D",BalanceN1[[#This Row],[BS_Credit]]>0),"A",IF(AND(BalanceN1[[#This Row],[Vérif]]="C",BalanceN1[[#This Row],[BS_Debit]]>0),"A","")) | Y76: =IF(AND(BalanceN1[[#This Row],[Vérif]]="D",BalanceN1[[#This Row],[BE_Credit]]>0),"A",IF(AND(BalanceN1[[#This Row],[Vérif]]="C",BalanceN1[[#This Row],[BE_Debit]]>0),"A",""))
A77: 471300 | B77: Créditeurs divers | D77: 710000 | E77: 3330000 | F77: 3240000 | H77: 620000 | I77: =VALUE(LEFT(BalanceN[[#This Row],[Compte]]&"00000000",5)) -> 47130 | J77: {=IF(BalanceN[[#This Row],[Compte]]="",0,_xlfn.IFNA(INDEX(Plan_Comptable[[Table de Compte]:[Sens]],MATCH(VALUE(LEFT(BalanceN[[#This Row],[Table]],4)),VALUE(Plan_Comptable[Table de Compte]),0),2),"A"))} -> 0 | K77: =IF(AND(BalanceN[[#This Row],[Vérif]]="D",BalanceN[[#This Row],[BS_Credit]]>0),"A",IF(AND(BalanceN[[#This Row],[Vérif]]="C",BalanceN[[#This Row],[BS_Debit]]>0),"A","")) | L77: =IF(AND(BalanceN[[#This Row],[Vérif]]="D",BalanceN[[#This Row],[BE_Credit]]>0),"A",IF(AND(BalanceN[[#This Row],[Vérif]]="C",BalanceN[[#This Row],[BE_Debit]]>0),"A","")) | N77: 482200 | O77: Frs invest. effets à payer | Q77: 1218333 | R77: 1218333 | V77: =VALUE(LEFT(BalanceN1[[#This Row],[Compte]]&"00000000",5)) -> 48220 | W77: {=IF(BalanceN1[[#This Row],[Compte]]="",0,_xlfn.IFNA(INDEX(Plan_Comptable[[Table de Compte]:[Sens]],MATCH(VALUE(LEFT(BalanceN1[[#This Row],[Table]],4)),VALUE(Plan_Comptable[Table de Compte]),0),2),"A"))} -> C | X77: =IF(AND(BalanceN1[[#This Row],[Vérif]]="D",BalanceN1[[#This Row],[BS_Credit]]>0),"A",IF(AND(BalanceN1[[#This Row],[Vérif]]="C",BalanceN1[[#This Row],[BS_Debit]]>0),"A","")) | Y77: =IF(AND(BalanceN1[[#This Row],[Vérif]]="D",BalanceN1[[#This Row],[BE_Credit]]>0),"A",IF(AND(BalanceN1[[#This Row],[Vérif]]="C",BalanceN1[[#This Row],[BE_Debit]]>0),"A",""))
A78: 476000 | B78: Charges constatées d'avance | C78: 1398099 | E78: 6817087 | F78: 6951322 | G78: 1263864 | I78: =VALUE(LEFT(BalanceN[[#This Row],[Compte]]&"00000000",5)) -> 47600 | J78: {=IF(BalanceN[[#This Row],[Compte]]="",0,_xlfn.IFNA(INDEX(Plan_Comptable[[Table de Compte]:[Sens]],MATCH(VALUE(LEFT(BalanceN[[#This Row],[Table]],4)),VALUE(Plan_Comptable[Table de Compte]),0),2),"A"))} -> D | K78: =IF(AND(BalanceN[[#This Row],[Vérif]]="D",BalanceN[[#This Row],[BS_Credit]]>0),"A",IF(AND(BalanceN[[#This Row],[Vérif]]="C",BalanceN[[#This Row],[BS_Debit]]>0),"A","")) | L78: =IF(AND(BalanceN[[#This Row],[Vérif]]="D",BalanceN[[#This Row],[BE_Credit]]>0),"A",IF(AND(BalanceN[[#This Row],[Vérif]]="C",BalanceN[[#This Row],[BE_Debit]]>0),"A","")) | N78: 485100 | O78: Créances sur cessions d'immobilisations | P78: 620000 | S78: 240000 | T78: 380000 | V78: =VALUE(LEFT(BalanceN1[[#This Row],[Compte]]&"00000000",5)) -> 48510 | W78: {=IF(BalanceN1[[#This Row],[Compte]]="",0,_xlfn.IFNA(INDEX(Plan_Comptable[[Table de Compte]:[Sens]],MATCH(VALUE(LEFT(BalanceN1[[#This Row],[Table]],4)),VALUE(Plan_Comptable[Table de Compte]),0),2),"A"))} -> D | X78: =IF(AND(BalanceN1[[#This Row],[Vérif]]="D",BalanceN1[[#This Row],[BS_Credit]]>0),"A",IF(AND(BalanceN1[[#This Row],[Vérif]]="C",BalanceN1[[#This Row],[BS_Debit]]>0),"A","")) | Y78: =IF(AND(BalanceN1[[#This Row],[Vérif]]="D",BalanceN1[[#This Row],[BE_Credit]]>0),"A",IF(AND(BalanceN1[[#This Row],[Vérif]]="C",BalanceN1[[#This Row],[BE_Debit]]>0),"A",""))
A79: 477000 | B79: Produits constatés d'avance | E79: 10560000 | F79: 10560000 | I79: =VALUE(LEFT(BalanceN[[#This Row],[Compte]]&"00000000",5)) -> 47700 | J79: {=IF(BalanceN[[#This Row],[Compte]]="",0,_xlfn.IFNA(INDEX(Plan_Comptable[[Table de Compte]:[Sens]],MATCH(VALUE(LEFT(BalanceN[[#This Row],[Table]],4)),VALUE(Plan_Comptable[Table de Compte]),0),2),"A"))} -> C | K79: =IF(AND(BalanceN[[#This Row],[Vérif]]="D",BalanceN[[#This Row],[BS_Credit]]>0),"A",IF(AND(BalanceN[[#This Row],[Vérif]]="C",BalanceN[[#This Row],[BS_Debit]]>0),"A","")) | L79: =IF(AND(BalanceN[[#This Row],[Vérif]]="D",BalanceN[[#This Row],[BE_Credit]]>0),"A",IF(AND(BalanceN[[#This Row],[Vérif]]="C",BalanceN[[#This Row],[BE_Debit]]>0),"A","")) | N79: 4912 | O79: Dépréciations comptes clts | Q79: 31677520 | U79: 31677520 | V79: =VALUE(LEFT(BalanceN1[[#This Row],[Compte]]&"00000000",5)) -> 49120 | W79: {=IF(BalanceN1[[#This Row],[Compte]]="",0,_xlfn.IFNA(INDEX(Plan_Comptable[[Table de Compte]:[Sens]],MATCH(VALUE(LEFT(BalanceN1[[#This Row],[Table]],4)),VALUE(Plan_Comptable[Table de Compte]),0),2),"A"))} -> C | X79: =IF(AND(BalanceN1[[#This Row],[Vérif]]="D",BalanceN1[[#This Row],[BS_Credit]]>0),"A",IF(AND(BalanceN1[[#This Row],[Vérif]]="C",BalanceN1[[#This Row],[BS_Debit]]>0),"A","")) | Y79: =IF(AND(BalanceN1[[#This Row],[Vérif]]="D",BalanceN1[[#This Row],[BE_Credit]]>0),"A",IF(AND(BalanceN1[[#This Row],[Vérif]]="C",BalanceN1[[#This Row],[BE_Debit]]>0),"A",""))
A80: 478100 | B80: Ecart conversion créances clients | E80: 15000000 | G80: 15000000 | I80: =VALUE(LEFT(BalanceN[[#This Row],[Compte]]&"00000000",5)) -> 47810 | J80: {=IF(BalanceN[[#This Row],[Compte]]="",0,_xlfn.IFNA(INDEX(Plan_Comptable[[Table de Compte]:[Sens]],MATCH(VALUE(LEFT(BalanceN[[#This Row],[Table]],4)),VALUE(Plan_Comptable[Table de Compte]),0),2),"A"))} -> D | K80: =IF(AND(BalanceN[[#This Row],[Vérif]]="D",BalanceN[[#This Row],[BS_Credit]]>0),"A",IF(AND(BalanceN[[#This Row],[Vérif]]="C",BalanceN[[#This Row],[BS_Debit]]>0),"A","")) | L80: =IF(AND(BalanceN[[#This Row],[Vérif]]="D",BalanceN[[#This Row],[BE_Credit]]>0),"A",IF(AND(BalanceN[[#This Row],[Vérif]]="C",BalanceN[[#This Row],[BE_Debit]]>0),"A","")) | N80: 5211 | O80: Banques | P80: 18485559 | R80: 1864651283 | S80: 1814012866 | T80: 69123976 | V80: =VALUE(LEFT(BalanceN1[[#This Row],[Compte]]&"00000000",5)) -> 52110 | W80: {=IF(BalanceN1[[#This Row],[Compte]]="",0,_xlfn.IFNA(INDEX(Plan_Comptable[[Table de Compte]:[Sens]],MATCH(VALUE(LEFT(BalanceN1[[#This Row],[Table]],4)),VALUE(Plan_Comptable[Table de Compte]),0),2),"A"))} -> 0 | X80: =IF(AND(BalanceN1[[#This Row],[Vérif]]="D",BalanceN1[[#This Row],[BS_Credit]]>0),"A",IF(AND(BalanceN1[[#This Row],[Vérif]]="C",BalanceN1[[#This Row],[BS_Debit]]>0),"A","")) | Y80: =IF(AND(BalanceN1[[#This Row],[Vérif]]="D",BalanceN1[[#This Row],[BE_Credit]]>0),"A",IF(AND(BalanceN1[[#This Row],[Vérif]]="C",BalanceN1[[#This Row],[BE_Debit]]>0),"A",""))
A81: 479400 | B81: Ecart conversion emprunts | F81: 2500925 | H81: 2500925 | I81: =VALUE(LEFT(BalanceN[[#This Row],[Compte]]&"00000000",5)) -> 47940 | J81: {=IF(BalanceN[[#This Row],[Compte]]="",0,_xlfn.IFNA(INDEX(Plan_Comptable[[Table de Compte]:[Sens]],MATCH(VALUE(LEFT(BalanceN[[#This Row],[Table]],4)),VALUE(Plan_Comptable[Table de Compte]),0),2),"A"))} -> C | K81: =IF(AND(BalanceN[[#This Row],[Vérif]]="D",BalanceN[[#This Row],[BS_Credit]]>0),"A",IF(AND(BalanceN[[#This Row],[Vérif]]="C",BalanceN[[#This Row],[BS_Debit]]>0),"A","")) | L81: =IF(AND(BalanceN[[#This Row],[Vérif]]="D",BalanceN[[#This Row],[BE_Credit]]>0),"A",IF(AND(BalanceN[[#This Row],[Vérif]]="C",BalanceN[[#This Row],[BE_Debit]]>0),"A","")) | N81: 571100 | O81: Caisse | P81: 15109845 | R81: 164971903 | S81: 174621567 | T81: 5460181 | V81: =VALUE(LEFT(BalanceN1[[#This Row],[Compte]]&"00000000",5)) -> 57110 | W81: {=IF(BalanceN1[[#This Row],[Compte]]="",0,_xlfn.IFNA(INDEX(Plan_Comptable[[Table de Compte]:[Sens]],MATCH(VALUE(LEFT(BalanceN1[[#This Row],[Table]],4)),VALUE(Plan_Comptable[Table de Compte]),0),2),"A"))} -> D | X81: =IF(AND(BalanceN1[[#This Row],[Vérif]]="D",BalanceN1[[#This Row],[BS_Credit]]>0),"A",IF(AND(BalanceN1[[#This Row],[Vérif]]="C",BalanceN1[[#This Row],[BS_Debit]]>0),"A","")) | Y81: =IF(AND(BalanceN1[[#This Row],[Vérif]]="D",BalanceN1[[#This Row],[BE_Credit]]>0),"A",IF(AND(BalanceN1[[#This Row],[Vérif]]="C",BalanceN1[[#This Row],[BE_Debit]]>0),"A",""))
A82: 481200 | B82: Frs invest Immobilisation cotporelle | E82: 7000000 | F82: 163250000 | H82: 156250000 | I82: =VALUE(LEFT(BalanceN[[#This Row],[Compte]]&"00000000",5)) -> 48120 | J82: {=IF(BalanceN[[#This Row],[Compte]]="",0,_xlfn.IFNA(INDEX(Plan_Comptable[[Table de Compte]:[Sens]],MATCH(VALUE(LEFT(BalanceN[[#This Row],[Table]],4)),VALUE(Plan_Comptable[Table de Compte]),0),2),"A"))} -> C | K82: =IF(AND(BalanceN[[#This Row],[Vérif]]="D",BalanceN[[#This Row],[BS_Credit]]>0),"A",IF(AND(BalanceN[[#This Row],[Vérif]]="C",BalanceN[[#This Row],[BS_Debit]]>0),"A","")) | L82: =IF(AND(BalanceN[[#This Row],[Vérif]]="D",BalanceN[[#This Row],[BE_Credit]]>0),"A",IF(AND(BalanceN[[#This Row],[Vérif]]="C",BalanceN[[#This Row],[BE_Debit]]>0),"A","")) | N82: 585000 | O82: Virements de fonds | R82: 155673628 | S82: 155673628 | V82: =VALUE(LEFT(BalanceN1[[#This Row],[Compte]]&"00000000",5)) -> 58500 | W82: {=IF(BalanceN1[[#This Row],[Compte]]="",0,_xlfn.IFNA(INDEX(Plan_Comptable[[Table de Compte]:[Sens]],MATCH(VALUE(LEFT(BalanceN1[[#This Row],[Table]],4)),VALUE(Plan_Comptable[Table de Compte]),0),2),"A"))} -> 0 | X82: =IF(AND(BalanceN1[[#This Row],[Vérif]]="D",BalanceN1[[#This Row],[BS_Credit]]>0),"A",IF(AND(BalanceN1[[#This Row],[Vérif]]="C",BalanceN1[[#This Row],[BS_Debit]]>0),"A","")) | Y82: =IF(AND(BalanceN1[[#This Row],[Vérif]]="D",BalanceN1[[#This Row],[BE_Credit]]>0),"A",IF(AND(BalanceN1[[#This Row],[Vérif]]="C",BalanceN1[[#This Row],[BE_Debit]]>0),"A",""))
A83: 481800 | B83: Frs invest. Fnp | D83: 399942 | H83: 399942 | I83: =VALUE(LEFT(BalanceN[[#This Row],[Compte]]&"00000000",5)) -> 48180 | J83: {=IF(BalanceN[[#This Row],[Compte]]="",0,_xlfn.IFNA(INDEX(Plan_Comptable[[Table de Compte]:[Sens]],MATCH(VALUE(LEFT(BalanceN[[#This Row],[Table]],4)),VALUE(Plan_Comptable[Table de Compte]),0),2),"A"))} -> C | K83: =IF(AND(BalanceN[[#This Row],[Vérif]]="D",BalanceN[[#This Row],[BS_Credit]]>0),"A",IF(AND(BalanceN[[#This Row],[Vérif]]="C",BalanceN[[#This Row],[BS_Debit]]>0),"A","")) | L83: =IF(AND(BalanceN[[#This Row],[Vérif]]="D",BalanceN[[#This Row],[BE_Credit]]>0),"A",IF(AND(BalanceN[[#This Row],[Vérif]]="C",BalanceN[[#This Row],[BE_Debit]]>0),"A","")) | N83: 602100 | O83: Achats matières premières | R83: 955664862 | S83: 1079390 | T83: 954585472 | V83: =VALUE(LEFT(BalanceN1[[#This Row],[Compte]]&"00000000",5)) -> 60210 | W83: {=IF(BalanceN1[[#This Row],[Compte]]="",0,_xlfn.IFNA(INDEX(Plan_Comptable[[Table de Compte]:[Sens]],MATCH(VALUE(LEFT(BalanceN1[[#This Row],[Table]],4)),VALUE(Plan_Comptable[Table de Compte]),0),2),"A"))} -> 0 | X83: =IF(AND(BalanceN1[[#This Row],[Vérif]]="D",BalanceN1[[#This Row],[BS_Credit]]>0),"A",IF(AND(BalanceN1[[#This Row],[Vérif]]="C",BalanceN1[[#This Row],[BS_Debit]]>0),"A","")) | Y83: =IF(AND(BalanceN1[[#This Row],[Vérif]]="D",BalanceN1[[#This Row],[BE_Credit]]>0),"A",IF(AND(BalanceN1[[#This Row],[Vérif]]="C",BalanceN1[[#This Row],[BE_Debit]]>0),"A",""))
A84: 485100 | B84: Créances sur cessions d'immobilisations | C84: 380000 | F84: 240000 | G84: 140000 | I84: =VALUE(LEFT(BalanceN[[#This Row],[Compte]]&"00000000",5)) -> 48510 | J84: {=IF(BalanceN[[#This Row],[Compte]]="",0,_xlfn.IFNA(INDEX(Plan_Comptable[[Table de Compte]:[Sens]],MATCH(VALUE(LEFT(BalanceN[[#This Row],[Table]],4)),VALUE(Plan_Comptable[Table de Compte]),0),2),"A"))} -> D | K84: =IF(AND(BalanceN[[#This Row],[Vérif]]="D",BalanceN[[#This Row],[BS_Credit]]>0),"A",IF(AND(BalanceN[[#This Row],[Vérif]]="C",BalanceN[[#This Row],[BS_Debit]]>0),"A","")) | L84: =IF(AND(BalanceN[[#This Row],[Vérif]]="D",BalanceN[[#This Row],[BE_Credit]]>0),"A",IF(AND(BalanceN[[#This Row],[Vérif]]="C",BalanceN[[#This Row],[BE_Debit]]>0),"A","")) | N84: 603201 | O84: Variation stockmatières premières | R84: 10552040 | S84: 7721440 | T84: 2830600 | V84: =VALUE(LEFT(BalanceN1[[#This Row],[Compte]]&"00000000",5)) -> 60320 | W84: {=IF(BalanceN1[[#This Row],[Compte]]="",0,_xlfn.IFNA(INDEX(Plan_Comptable[[Table de Compte]:[Sens]],MATCH(VALUE(LEFT(BalanceN1[[#This Row],[Table]],4)),VALUE(Plan_Comptable[Table de Compte]),0),2),"A"))} -> 0 | X84: =IF(AND(BalanceN1[[#This Row],[Vérif]]="D",BalanceN1[[#This Row],[BS_Credit]]>0),"A",IF(AND(BalanceN1[[#This Row],[Vérif]]="C",BalanceN1[[#This Row],[BS_Debit]]>0),"A","")) | Y84: =IF(AND(BalanceN1[[#This Row],[Vérif]]="D",BalanceN1[[#This Row],[BE_Credit]]>0),"A",IF(AND(BalanceN1[[#This Row],[Vérif]]="C",BalanceN1[[#This Row],[BE_Debit]]>0),"A",""))
A85: 488000 | B85: Autres créances HAO | E85: 2000000 | G85: 2000000 | I85: =VALUE(LEFT(BalanceN[[#This Row],[Compte]]&"00000000",5)) -> 48800 | J85: {=IF(BalanceN[[#This Row],[Compte]]="",0,_xlfn.IFNA(INDEX(Plan_Comptable[[Table de Compte]:[Sens]],MATCH(VALUE(LEFT(BalanceN[[#This Row],[Table]],4)),VALUE(Plan_Comptable[Table de Compte]),0),2),"A"))} -> D | K85: =IF(AND(BalanceN[[#This Row],[Vérif]]="D",BalanceN[[#This Row],[BS_Credit]]>0),"A",IF(AND(BalanceN[[#This Row],[Vérif]]="C",BalanceN[[#This Row],[BS_Debit]]>0),"A","")) | L85: =IF(AND(BalanceN[[#This Row],[Vérif]]="D",BalanceN[[#This Row],[BE_Credit]]>0),"A",IF(AND(BalanceN[[#This Row],[Vérif]]="C",BalanceN[[#This Row],[BE_Debit]]>0),"A","")) | N85: 603302 | O85: Variation stock emballage | R85: 6262346 | S85: 8146993 | U85: 1884647 | V85: =VALUE(LEFT(BalanceN1[[#This Row],[Compte]]&"00000000",5)) -> 60330 | W85: {=IF(BalanceN1[[#This Row],[Compte]]="",0,_xlfn.IFNA(INDEX(Plan_Comptable[[Table de Compte]:[Sens]],MATCH(VALUE(LEFT(BalanceN1[[#This Row],[Table]],4)),VALUE(Plan_Comptable[Table de Compte]),0),2),"A"))} -> 0 | X85: =IF(AND(BalanceN1[[#This Row],[Vérif]]="D",BalanceN1[[#This Row],[BS_Credit]]>0),"A",IF(AND(BalanceN1[[#This Row],[Vérif]]="C",BalanceN1[[#This Row],[BS_Debit]]>0),"A","")) | Y85: =IF(AND(BalanceN1[[#This Row],[Vérif]]="D",BalanceN1[[#This Row],[BE_Credit]]>0),"A",IF(AND(BalanceN1[[#This Row],[Vérif]]="C",BalanceN1[[#This Row],[BE_Debit]]>0),"A",""))
A86: 4912 | B86: Dépréciations comptes clients | D86: 31677520 | H86: 31677520 | I86: =VALUE(LEFT(BalanceN[[#This Row],[Compte]]&"00000000",5)) -> 49120 | J86: {=IF(BalanceN[[#This Row],[Compte]]="",0,_xlfn.IFNA(INDEX(Plan_Comptable[[Table de Compte]:[Sens]],MATCH(VALUE(LEFT(BalanceN[[#This Row],[Table]],4)),VALUE(Plan_Comptable[Table de Compte]),0),2),"A"))} -> C | K86: =IF(AND(BalanceN[[#This Row],[Vérif]]="D",BalanceN[[#This Row],[BS_Credit]]>0),"A",IF(AND(BalanceN[[#This Row],[Vérif]]="C",BalanceN[[#This Row],[BS_Debit]]>0),"A","")) | L86: =IF(AND(BalanceN[[#This Row],[Vérif]]="D",BalanceN[[#This Row],[BE_Credit]]>0),"A",IF(AND(BalanceN[[#This Row],[Vérif]]="C",BalanceN[[#This Row],[BE_Debit]]>0),"A","")) | N86: 604200 | O86: Achats carburant | R86: 12683576 | T86: 12683576 | V86: =VALUE(LEFT(BalanceN1[[#This Row],[Compte]]&"00000000",5)) -> 60420 | W86: {=IF(BalanceN1[[#This Row],[Compte]]="",0,_xlfn.IFNA(INDEX(Plan_Comptable[[Table de Compte]:[Sens]],MATCH(VALUE(LEFT(BalanceN1[[#This Row],[Table]],4)),VALUE(Plan_Comptable[Table de Compte]),0),2),"A"))} -> 0 | X86: =IF(AND(BalanceN1[[#This Row],[Vérif]]="D",BalanceN1[[#This Row],[BS_Credit]]>0),"A",IF(AND(BalanceN1[[#This Row],[Vérif]]="C",BalanceN1[[#This Row],[BS_Debit]]>0),"A","")) | Y86: =IF(AND(BalanceN1[[#This Row],[Vérif]]="D",BalanceN1[[#This Row],[BE_Credit]]>0),"A",IF(AND(BalanceN1[[#This Row],[Vérif]]="C",BalanceN1[[#This Row],[BE_Debit]]>0),"A",""))
A87: 5211 | B87: Banques | C87: 69123976 | E87: 2247552500 | F87: 2195523485 | G87: 121152991 | I87: =VALUE(LEFT(BalanceN[[#This Row],[Compte]]&"00000000",5)) -> 52110 | J87: {=IF(BalanceN[[#This Row],[Compte]]="",0,_xlfn.IFNA(INDEX(Plan_Comptable[[Table de Compte]:[Sens]],MATCH(VALUE(LEFT(BalanceN[[#This Row],[Table]],4)),VALUE(Plan_Comptable[Table de Compte]),0),2),"A"))} -> 0 | K87: =IF(AND(BalanceN[[#This Row],[Vérif]]="D",BalanceN[[#This Row],[BS_Credit]]>0),"A",IF(AND(BalanceN[[#This Row],[Vérif]]="C",BalanceN[[#This Row],[BS_Debit]]>0),"A","")) | L87: =IF(AND(BalanceN[[#This Row],[Vérif]]="D",BalanceN[[#This Row],[BE_Credit]]>0),"A",IF(AND(BalanceN[[#This Row],[Vérif]]="C",BalanceN[[#This Row],[BE_Debit]]>0),"A","")) | N87: 604300 | O87: Produits d'entretien | R87: 1144000 | T87: 1144000 | V87: =VALUE(LEFT(BalanceN1[[#This Row],[Compte]]&"00000000",5)) -> 60430 | W87: {=IF(BalanceN1[[#This Row],[Compte]]="",0,_xlfn.IFNA(INDEX(Plan_Comptable[[Table de Compte]:[Sens]],MATCH(VALUE(LEFT(BalanceN1[[#This Row],[Table]],4)),VALUE(Plan_Comptable[Table de Compte]),0),2),"A"))} -> 0 | X87: =IF(AND(BalanceN1[[#This Row],[Vérif]]="D",BalanceN1[[#This Row],[BS_Credit]]>0),"A",IF(AND(BalanceN1[[#This Row],[Vérif]]="C",BalanceN1[[#This Row],[BS_Debit]]>0),"A","")) | Y87: =IF(AND(BalanceN1[[#This Row],[Vérif]]="D",BalanceN1[[#This Row],[BE_Credit]]>0),"A",IF(AND(BalanceN1[[#This Row],[Vérif]]="C",BalanceN1[[#This Row],[BE_Debit]]>0),"A",""))
A88: 571100 | B88: Caisse | C88: 5460181 | E88: 141403437 | F88: 144919482 | G88: 1944136 | I88: =VALUE(LEFT(BalanceN[[#This Row],[Compte]]&"00000000",5)) -> 57110 | J88: {=IF(BalanceN[[#This Row],[Compte]]="",0,_xlfn.IFNA(INDEX(Plan_Comptable[[Table de Compte]:[Sens]],MATCH(VALUE(LEFT(BalanceN[[#This Row],[Table]],4)),VALUE(Plan_Comptable[Table de Compte]),0),2),"A"))} -> D | K88: =IF(AND(BalanceN[[#This Row],[Vérif]]="D",BalanceN[[#This Row],[BS_Credit]]>0),"A",IF(AND(BalanceN[[#This Row],[Vérif]]="C",BalanceN[[#This Row],[BS_Debit]]>0),"A","")) | L88: =IF(AND(BalanceN[[#This Row],[Vérif]]="D",BalanceN[[#This Row],[BE_Credit]]>0),"A",IF(AND(BalanceN[[#This Row],[Vérif]]="C",BalanceN[[#This Row],[BE_Debit]]>0),"A","")) | N88: 605100 | O88: Eau | R88: 6125987 | S88: 1466738 | T88: 4659249 | V88: =VALUE(LEFT(BalanceN1[[#This Row],[Compte]]&"00000000",5)) -> 60510 | W88: {=IF(BalanceN1[[#This Row],[Compte]]="",0,_xlfn.IFNA(INDEX(Plan_Comptable[[Table de Compte]:[Sens]],MATCH(VALUE(LEFT(BalanceN1[[#This Row],[Table]],4)),VALUE(Plan_Comptable[Table de Compte]),0),2),"A"))} -> 0 | X88: =IF(AND(BalanceN1[[#This Row],[Vérif]]="D",BalanceN1[[#This Row],[BS_Credit]]>0),"A",IF(AND(BalanceN1[[#This Row],[Vérif]]="C",BalanceN1[[#This Row],[BS_Debit]]>0),"A","")) | Y88: =IF(AND(BalanceN1[[#This Row],[Vérif]]="D",BalanceN1[[#This Row],[BE_Credit]]>0),"A",IF(AND(BalanceN1[[#This Row],[Vérif]]="C",BalanceN1[[#This Row],[BE_Debit]]>0),"A",""))
A89: 585000 | B89: Virements defonds | E89: 144502048 | F89: 144502048 | I89: =VALUE(LEFT(BalanceN[[#This Row],[Compte]]&"00000000",5)) -> 58500 | J89: {=IF(BalanceN[[#This Row],[Compte]]="",0,_xlfn.IFNA(INDEX(Plan_Comptable[[Table de Compte]:[Sens]],MATCH(VALUE(LEFT(BalanceN[[#This Row],[Table]],4)),VALUE(Plan_Comptable[Table de Compte]),0),2),"A"))} -> 0 | K89: =IF(AND(BalanceN[[#This Row],[Vérif]]="D",BalanceN[[#This Row],[BS_Credit]]>0),"A",IF(AND(BalanceN[[#This Row],[Vérif]]="C",BalanceN[[#This Row],[BS_Debit]]>0),"A","")) | L89: =IF(AND(BalanceN[[#This Row],[Vérif]]="D",BalanceN[[#This Row],[BE_Credit]]>0),"A",IF(AND(BalanceN[[#This Row],[Vérif]]="C",BalanceN[[#This Row],[BE_Debit]]>0),"A","")) | N89: 605200 | O89: Electricité | R89: 36907753 | S89: 15147134 | T89: 21760619 | V89: =VALUE(LEFT(BalanceN1[[#This Row],[Compte]]&"00000000",5)) -> 60520 | W89: {=IF(BalanceN1[[#This Row],[Compte]]="",0,_xlfn.IFNA(INDEX(Plan_Comptable[[Table de Compte]:[Sens]],MATCH(VALUE(LEFT(BalanceN1[[#This Row],[Table]],4)),VALUE(Plan_Comptable[Table de Compte]),0),2),"A"))} -> 0 | X89: =IF(AND(BalanceN1[[#This Row],[Vérif]]="D",BalanceN1[[#This Row],[BS_Credit]]>0),"A",IF(AND(BalanceN1[[#This Row],[Vérif]]="C",BalanceN1[[#This Row],[BS_Debit]]>0),"A","")) | Y89: =IF(AND(BalanceN1[[#This Row],[Vérif]]="D",BalanceN1[[#This Row],[BE_Credit]]>0),"A",IF(AND(BalanceN1[[#This Row],[Vérif]]="C",BalanceN1[[#This Row],[BE_Debit]]>0),"A",""))
A90: 601100 | B90: Achats marchandises | E90: 75000000 | G90: 75000000 | I90: =VALUE(LEFT(BalanceN[[#This Row],[Compte]]&"00000000",5)) -> 60110 | J90: {=IF(BalanceN[[#This Row],[Compte]]="",0,_xlfn.IFNA(INDEX(Plan_Comptable[[Table de Compte]:[Sens]],MATCH(VALUE(LEFT(BalanceN[[#This Row],[Table]],4)),VALUE(Plan_Comptable[Table de Compte]),0),2),"A"))} -> 0 | K90: =IF(AND(BalanceN[[#This Row],[Vérif]]="D",BalanceN[[#This Row],[BS_Credit]]>0),"A",IF(AND(BalanceN[[#This Row],[Vérif]]="C",BalanceN[[#This Row],[BS_Debit]]>0),"A","")) | L90: =IF(AND(BalanceN[[#This Row],[Vérif]]="D",BalanceN[[#This Row],[BE_Credit]]>0),"A",IF(AND(BalanceN[[#This Row],[Vérif]]="C",BalanceN[[#This Row],[BE_Debit]]>0),"A","")) | N90: 605300 | O90: Autres énergies gaz | R90: 6618773 | S90: 6618773 | V90: =VALUE(LEFT(BalanceN1[[#This Row],[Compte]]&"00000000",5)) -> 60530 | W90: {=IF(BalanceN1[[#This Row],[Compte]]="",0,_xlfn.IFNA(INDEX(Plan_Comptable[[Table de Compte]:[Sens]],MATCH(VALUE(LEFT(BalanceN1[[#This Row],[Table]],4)),VALUE(Plan_Comptable[Table de Compte]),0),2),"A"))} -> 0 | X90: =IF(AND(BalanceN1[[#This Row],[Vérif]]="D",BalanceN1[[#This Row],[BS_Credit]]>0),"A",IF(AND(BalanceN1[[#This Row],[Vérif]]="C",BalanceN1[[#This Row],[BS_Debit]]>0),"A","")) | Y90: =IF(AND(BalanceN1[[#This Row],[Vérif]]="D",BalanceN1[[#This Row],[BE_Credit]]>0),"A",IF(AND(BalanceN1[[#This Row],[Vérif]]="C",BalanceN1[[#This Row],[BE_Debit]]>0),"A",""))
A91: 602100 | B91: Achats matières dans la région | E91: 924957492 | F91: 1770650 | G91: 923186842 | I91: =VALUE(LEFT(BalanceN[[#This Row],[Compte]]&"00000000",5)) -> 60210 | J91: {=IF(BalanceN[[#This Row],[Compte]]="",0,_xlfn.IFNA(INDEX(Plan_Comptable[[Table de Compte]:[Sens]],MATCH(VALUE(LEFT(BalanceN[[#This Row],[Table]],4)),VALUE(Plan_Comptable[Table de Compte]),0),2),"A"))} -> 0 | K91: =IF(AND(BalanceN[[#This Row],[Vérif]]="D",BalanceN[[#This Row],[BS_Credit]]>0),"A",IF(AND(BalanceN[[#This Row],[Vérif]]="C",BalanceN[[#This Row],[BS_Debit]]>0),"A","")) | L91: =IF(AND(BalanceN[[#This Row],[Vérif]]="D",BalanceN[[#This Row],[BE_Credit]]>0),"A",IF(AND(BalanceN[[#This Row],[Vérif]]="C",BalanceN[[#This Row],[BE_Debit]]>0),"A","")) | N91: 605400 | O91: Fourniture entretien non stockables | R91: 2249226 | S91: 69600 | T91: 2179626 | V91: =VALUE(LEFT(BalanceN1[[#This Row],[Compte]]&"00000000",5)) -> 60540 | W91: {=IF(BalanceN1[[#This Row],[Compte]]="",0,_xlfn.IFNA(INDEX(Plan_Comptable[[Table de Compte]:[Sens]],MATCH(VALUE(LEFT(BalanceN1[[#This Row],[Table]],4)),VALUE(Plan_Comptable[Table de Compte]),0),2),"A"))} -> 0 | X91: =IF(AND(BalanceN1[[#This Row],[Vérif]]="D",BalanceN1[[#This Row],[BS_Credit]]>0),"A",IF(AND(BalanceN1[[#This Row],[Vérif]]="C",BalanceN1[[#This Row],[BS_Debit]]>0),"A","")) | Y91: =IF(AND(BalanceN1[[#This Row],[Vérif]]="D",BalanceN1[[#This Row],[BE_Credit]]>0),"A",IF(AND(BalanceN1[[#This Row],[Vérif]]="C",BalanceN1[[#This Row],[BE_Debit]]>0),"A",""))
A92: 602210 | B92: Achats fournitures | E92: 5116850 | G92: 5116850 | I92: =VALUE(LEFT(BalanceN[[#This Row],[Compte]]&"00000000",5)) -> 60221 | J92: {=IF(BalanceN[[#This Row],[Compte]]="",0,_xlfn.IFNA(INDEX(Plan_Comptable[[Table de Compte]:[Sens]],MATCH(VALUE(LEFT(BalanceN[[#This Row],[Table]],4)),VALUE(Plan_Comptable[Table de Compte]),0),2),"A"))} -> 0 | K92: =IF(AND(BalanceN[[#This Row],[Vérif]]="D",BalanceN[[#This Row],[BS_Credit]]>0),"A",IF(AND(BalanceN[[#This Row],[Vérif]]="C",BalanceN[[#This Row],[BS_Debit]]>0),"A","")) | L92: =IF(AND(BalanceN[[#This Row],[Vérif]]="D",BalanceN[[#This Row],[BE_Credit]]>0),"A",IF(AND(BalanceN[[#This Row],[Vérif]]="C",BalanceN[[#This Row],[BE_Debit]]>0),"A","")) | N92: 605500 | O92: Fourniture de bureau | R92: 5047450 | S92: 12500 | T92: 5034950 | V92: =VALUE(LEFT(BalanceN1[[#This Row],[Compte]]&"00000000",5)) -> 60550 | W92: {=IF(BalanceN1[[#This Row],[Compte]]="",0,_xlfn.IFNA(INDEX(Plan_Comptable[[Table de Compte]:[Sens]],MATCH(VALUE(LEFT(BalanceN1[[#This Row],[Table]],4)),VALUE(Plan_Comptable[Table de Compte]),0),2),"A"))} -> 0 | X92: =IF(AND(BalanceN1[[#This Row],[Vérif]]="D",BalanceN1[[#This Row],[BS_Credit]]>0),"A",IF(AND(BalanceN1[[#This Row],[Vérif]]="C",BalanceN1[[#This Row],[BS_Debit]]>0),"A","")) | Y92: =IF(AND(BalanceN1[[#This Row],[Vérif]]="D",BalanceN1[[#This Row],[BE_Credit]]>0),"A",IF(AND(BalanceN1[[#This Row],[Vérif]]="C",BalanceN1[[#This Row],[BE_Debit]]>0),"A",""))
A93: 603100 | B93: Variations stocks de marchandises | F93: 5000000 | H93: 5000000 | I93: =VALUE(LEFT(BalanceN[[#This Row],[Compte]]&"00000000",5)) -> 60310 | J93: {=IF(BalanceN[[#This Row],[Compte]]="",0,_xlfn.IFNA(INDEX(Plan_Comptable[[Table de Compte]:[Sens]],MATCH(VALUE(LEFT(BalanceN[[#This Row],[Table]],4)),VALUE(Plan_Comptable[Table de Compte]),0),2),"A"))} -> 0 | K93: =IF(AND(BalanceN[[#This Row],[Vérif]]="D",BalanceN[[#This Row],[BS_Credit]]>0),"A",IF(AND(BalanceN[[#This Row],[Vérif]]="C",BalanceN[[#This Row],[BS_Debit]]>0),"A","")) | L93: =IF(AND(BalanceN[[#This Row],[Vérif]]="D",BalanceN[[#This Row],[BE_Credit]]>0),"A",IF(AND(BalanceN[[#This Row],[Vérif]]="C",BalanceN[[#This Row],[BE_Debit]]>0),"A","")) | N93: 605600 | O93: Achats de petit matériel &outillage | R93: 11441377 | T93: 11441377 | V93: =VALUE(LEFT(BalanceN1[[#This Row],[Compte]]&"00000000",5)) -> 60560 | W93: {=IF(BalanceN1[[#This Row],[Compte]]="",0,_xlfn.IFNA(INDEX(Plan_Comptable[[Table de Compte]:[Sens]],MATCH(VALUE(LEFT(BalanceN1[[#This Row],[Table]],4)),VALUE(Plan_Comptable[Table de Compte]),0),2),"A"))} -> 0 | X93: =IF(AND(BalanceN1[[#This Row],[Vérif]]="D",BalanceN1[[#This Row],[BS_Credit]]>0),"A",IF(AND(BalanceN1[[#This Row],[Vérif]]="C",BalanceN1[[#This Row],[BS_Debit]]>0),"A","")) | Y93: =IF(AND(BalanceN1[[#This Row],[Vérif]]="D",BalanceN1[[#This Row],[BE_Credit]]>0),"A",IF(AND(BalanceN1[[#This Row],[Vérif]]="C",BalanceN1[[#This Row],[BE_Debit]]>0),"A",""))
A94: 603201 | B94: Variation stocks matières premières | E94: 57775035 | F94: 57881451 | H94: 106416 | I94: =VALUE(LEFT(BalanceN[[#This Row],[Compte]]&"00000000",5)) -> 60320 | J94: {=IF(BalanceN[[#This Row],[Compte]]="",0,_xlfn.IFNA(INDEX(Plan_Comptable[[Table de Compte]:[Sens]],MATCH(VALUE(LEFT(BalanceN[[#This Row],[Table]],4)),VALUE(Plan_Comptable[Table de Compte]),0),2),"A"))} -> 0 | K94: =IF(AND(BalanceN[[#This Row],[Vérif]]="D",BalanceN[[#This Row],[BS_Credit]]>0),"A",IF(AND(BalanceN[[#This Row],[Vérif]]="C",BalanceN[[#This Row],[BS_Debit]]>0),"A","")) | L94: =IF(AND(BalanceN[[#This Row],[Vérif]]="D",BalanceN[[#This Row],[BE_Credit]]>0),"A",IF(AND(BalanceN[[#This Row],[Vérif]]="C",BalanceN[[#This Row],[BE_Debit]]>0),"A","")) | N94: 605700 | O94: Achats d'études prestations service | R94: 505000 | T94: 505000 | V94: =VALUE(LEFT(BalanceN1[[#This Row],[Compte]]&"00000000",5)) -> 60570 | W94: {=IF(BalanceN1[[#This Row],[Compte]]="",0,_xlfn.IFNA(INDEX(Plan_Comptable[[Table de Compte]:[Sens]],MATCH(VALUE(LEFT(BalanceN1[[#This Row],[Table]],4)),VALUE(Plan_Comptable[Table de Compte]),0),2),"A"))} -> 0 | X94: =IF(AND(BalanceN1[[#This Row],[Vérif]]="D",BalanceN1[[#This Row],[BS_Credit]]>0),"A",IF(AND(BalanceN1[[#This Row],[Vérif]]="C",BalanceN1[[#This Row],[BS_Debit]]>0),"A","")) | Y94: =IF(AND(BalanceN1[[#This Row],[Vérif]]="D",BalanceN1[[#This Row],[BE_Credit]]>0),"A",IF(AND(BalanceN1[[#This Row],[Vérif]]="C",BalanceN1[[#This Row],[BE_Debit]]>0),"A",""))
A95: 603302 | B95: Variation stocks emballages | E95: 79288966 | F95: 76874255 | G95: 2414711 | I95: =VALUE(LEFT(BalanceN[[#This Row],[Compte]]&"00000000",5)) -> 60330 | J95: {=IF(BalanceN[[#This Row],[Compte]]="",0,_xlfn.IFNA(INDEX(Plan_Comptable[[Table de Compte]:[Sens]],MATCH(VALUE(LEFT(BalanceN[[#This Row],[Table]],4)),VALUE(Plan_Comptable[Table de Compte]),0),2),"A"))} -> 0 | K95: =IF(AND(BalanceN[[#This Row],[Vérif]]="D",BalanceN[[#This Row],[BS_Credit]]>0),"A",IF(AND(BalanceN[[#This Row],[Vérif]]="C",BalanceN[[#This Row],[BS_Debit]]>0),"A","")) | L95: =IF(AND(BalanceN[[#This Row],[Vérif]]="D",BalanceN[[#This Row],[BE_Credit]]>0),"A",IF(AND(BalanceN[[#This Row],[Vérif]]="C",BalanceN[[#This Row],[BE_Debit]]>0),"A","")) | N95: 605800 | O95: Petits équipements | R95: 420025 | T95: 420025 | V95: =VALUE(LEFT(BalanceN1[[#This Row],[Compte]]&"00000000",5)) -> 60580 | W95: {=IF(BalanceN1[[#This Row],[Compte]]="",0,_xlfn.IFNA(INDEX(Plan_Comptable[[Table de Compte]:[Sens]],MATCH(VALUE(LEFT(BalanceN1[[#This Row],[Table]],4)),VALUE(Plan_Comptable[Table de Compte]),0),2),"A"))} -> 0 | X95: =IF(AND(BalanceN1[[#This Row],[Vérif]]="D",BalanceN1[[#This Row],[BS_Credit]]>0),"A",IF(AND(BalanceN1[[#This Row],[Vérif]]="C",BalanceN1[[#This Row],[BS_Debit]]>0),"A","")) | Y95: =IF(AND(BalanceN1[[#This Row],[Vérif]]="D",BalanceN1[[#This Row],[BE_Credit]]>0),"A",IF(AND(BalanceN1[[#This Row],[Vérif]]="C",BalanceN1[[#This Row],[BE_Debit]]>0),"A",""))
A96: 604200 | B96: Achats carburant | E96: 21691425 | F96: 10431949 | G96: 11259476 | I96: =VALUE(LEFT(BalanceN[[#This Row],[Compte]]&"00000000",5)) -> 60420 | J96: {=IF(BalanceN[[#This Row],[Compte]]="",0,_xlfn.IFNA(INDEX(Plan_Comptable[[Table de Compte]:[Sens]],MATCH(VALUE(LEFT(BalanceN[[#This Row],[Table]],4)),VALUE(Plan_Comptable[Table de Compte]),0),2),"A"))} -> 0 | K96: =IF(AND(BalanceN[[#This Row],[Vérif]]="D",BalanceN[[#This Row],[BS_Credit]]>0),"A",IF(AND(BalanceN[[#This Row],[Vérif]]="C",BalanceN[[#This Row],[BS_Debit]]>0),"A","")) | L96: =IF(AND(BalanceN[[#This Row],[Vérif]]="D",BalanceN[[#This Row],[BE_Credit]]>0),"A",IF(AND(BalanceN[[#This Row],[Vérif]]="C",BalanceN[[#This Row],[BE_Debit]]>0),"A","")) | N96: 608100 | O96: Emballages perdus | R96: 101311095 | S96: 19000 | T96: 101292095 | V96: =VALUE(LEFT(BalanceN1[[#This Row],[Compte]]&"00000000",5)) -> 60810 | W96: {=IF(BalanceN1[[#This Row],[Compte]]="",0,_xlfn.IFNA(INDEX(Plan_Comptable[[Table de Compte]:[Sens]],MATCH(VALUE(LEFT(BalanceN1[[#This Row],[Table]],4)),VALUE(Plan_Comptable[Table de Compte]),0),2),"A"))} -> 0 | X96: =IF(AND(BalanceN1[[#This Row],[Vérif]]="D",BalanceN1[[#This Row],[BS_Credit]]>0),"A",IF(AND(BalanceN1[[#This Row],[Vérif]]="C",BalanceN1[[#This Row],[BS_Debit]]>0),"A","")) | Y96: =IF(AND(BalanceN1[[#This Row],[Vérif]]="D",BalanceN1[[#This Row],[BE_Credit]]>0),"A",IF(AND(BalanceN1[[#This Row],[Vérif]]="C",BalanceN1[[#This Row],[BE_Debit]]>0),"A",""))
A97: 605100 | B97: Eau | E97: 10895715 | F97: 5387895 | G97: 5507820 | I97: =VALUE(LEFT(BalanceN[[#This Row],[Compte]]&"00000000",5)) -> 60510 | J97: {=IF(BalanceN[[#This Row],[Compte]]="",0,_xlfn.IFNA(INDEX(Plan_Comptable[[Table de Compte]:[Sens]],MATCH(VALUE(LEFT(BalanceN[[#This Row],[Table]],4)),VALUE(Plan_Comptable[Table de Compte]),0),2),"A"))} -> 0 | K97: =IF(AND(BalanceN[[#This Row],[Vérif]]="D",BalanceN[[#This Row],[BS_Credit]]>0),"A",IF(AND(BalanceN[[#This Row],[Vérif]]="C",BalanceN[[#This Row],[BS_Debit]]>0),"A","")) | L97: =IF(AND(BalanceN[[#This Row],[Vérif]]="D",BalanceN[[#This Row],[BE_Credit]]>0),"A",IF(AND(BalanceN[[#This Row],[Vérif]]="C",BalanceN[[#This Row],[BE_Debit]]>0),"A","")) | N97: 612000 | O97: Transports sur ventes | R97: 346376807 | S97: 18382446 | T97: 327994361 | V97: =VALUE(LEFT(BalanceN1[[#This Row],[Compte]]&"00000000",5)) -> 61200 | W97: {=IF(BalanceN1[[#This Row],[Compte]]="",0,_xlfn.IFNA(INDEX(Plan_Comptable[[Table de Compte]:[Sens]],MATCH(VALUE(LEFT(BalanceN1[[#This Row],[Table]],4)),VALUE(Plan_Comptable[Table de Compte]),0),2),"A"))} -> 0 | X97: =IF(AND(BalanceN1[[#This Row],[Vérif]]="D",BalanceN1[[#This Row],[BS_Credit]]>0),"A",IF(AND(BalanceN1[[#This Row],[Vérif]]="C",BalanceN1[[#This Row],[BS_Debit]]>0),"A","")) | Y97: =IF(AND(BalanceN1[[#This Row],[Vérif]]="D",BalanceN1[[#This Row],[BE_Credit]]>0),"A",IF(AND(BalanceN1[[#This Row],[Vérif]]="C",BalanceN1[[#This Row],[BE_Debit]]>0),"A",""))
A98: 605200 | B98: Electricité | E98: 56706955 | F98: 32760604 | G98: 23946351 | I98: =VALUE(LEFT(BalanceN[[#This Row],[Compte]]&"00000000",5)) -> 60520 | J98: {=IF(BalanceN[[#This Row],[Compte]]="",0,_xlfn.IFNA(INDEX(Plan_Comptable[[Table de Compte]:[Sens]],MATCH(VALUE(LEFT(BalanceN[[#This Row],[Table]],4)),VALUE(Plan_Comptable[Table de Compte]),0),2),"A"))} -> 0 | K98: =IF(AND(BalanceN[[#This Row],[Vérif]]="D",BalanceN[[#This Row],[BS_Credit]]>0),"A",IF(AND(BalanceN[[#This Row],[Vérif]]="C",BalanceN[[#This Row],[BS_Debit]]>0),"A","")) | L98: =IF(AND(BalanceN[[#This Row],[Vérif]]="D",BalanceN[[#This Row],[BE_Credit]]>0),"A",IF(AND(BalanceN[[#This Row],[Vérif]]="C",BalanceN[[#This Row],[BE_Debit]]>0),"A","")) | N98: 616000 | O98: Transport de pLis | R98: 86870 | T98: 86870 | V98: =VALUE(LEFT(BalanceN1[[#This Row],[Compte]]&"00000000",5)) -> 61600 | W98: {=IF(BalanceN1[[#This Row],[Compte]]="",0,_xlfn.IFNA(INDEX(Plan_Comptable[[Table de Compte]:[Sens]],MATCH(VALUE(LEFT(BalanceN1[[#This Row],[Table]],4)),VALUE(Plan_Comptable[Table de Compte]),0),2),"A"))} -> 0 | X98: =IF(AND(BalanceN1[[#This Row],[Vérif]]="D",BalanceN1[[#This Row],[BS_Credit]]>0),"A",IF(AND(BalanceN1[[#This Row],[Vérif]]="C",BalanceN1[[#This Row],[BS_Debit]]>0),"A","")) | Y98: =IF(AND(BalanceN1[[#This Row],[Vérif]]="D",BalanceN1[[#This Row],[BE_Credit]]>0),"A",IF(AND(BalanceN1[[#This Row],[Vérif]]="C",BalanceN1[[#This Row],[BE_Debit]]>0),"A",""))
A99: 605400 | B99: Fourniture entretien non stockables | E99: 4268103 | F99: 285000 | G99: 3983103 | I99: =VALUE(LEFT(BalanceN[[#This Row],[Compte]]&"00000000",5)) -> 60540 | J99: {=IF(BalanceN[[#This Row],[Compte]]="",0,_xlfn.IFNA(INDEX(Plan_Comptable[[Table de Compte]:[Sens]],MATCH(VALUE(LEFT(BalanceN[[#This Row],[Table]],4)),VALUE(Plan_Comptable[Table de Compte]),0),2),"A"))} -> 0 | K99: =IF(AND(BalanceN[[#This Row],[Vérif]]="D",BalanceN[[#This Row],[BS_Credit]]>0),"A",IF(AND(BalanceN[[#This Row],[Vérif]]="C",BalanceN[[#This Row],[BS_Debit]]>0),"A","")) | L99: =IF(AND(BalanceN[[#This Row],[Vérif]]="D",BalanceN[[#This Row],[BE_Credit]]>0),"A",IF(AND(BalanceN[[#This Row],[Vérif]]="C",BalanceN[[#This Row],[BE_Debit]]>0),"A","")) | N99: 618100 | O99: Voyages et déplacements | R99: 306500 | T99: 306500 | V99: =VALUE(LEFT(BalanceN1[[#This Row],[Compte]]&"00000000",5)) -> 61810 | W99: {=IF(BalanceN1[[#This Row],[Compte]]="",0,_xlfn.IFNA(INDEX(Plan_Comptable[[Table de Compte]:[Sens]],MATCH(VALUE(LEFT(BalanceN1[[#This Row],[Table]],4)),VALUE(Plan_Comptable[Table de Compte]),0),2),"A"))} -> 0 | X99: =IF(AND(BalanceN1[[#This Row],[Vérif]]="D",BalanceN1[[#This Row],[BS_Credit]]>0),"A",IF(AND(BalanceN1[[#This Row],[Vérif]]="C",BalanceN1[[#This Row],[BS_Debit]]>0),"A","")) | Y99: =IF(AND(BalanceN1[[#This Row],[Vérif]]="D",BalanceN1[[#This Row],[BE_Credit]]>0),"A",IF(AND(BalanceN1[[#This Row],[Vérif]]="C",BalanceN1[[#This Row],[BE_Debit]]>0),"A",""))
A100: 605500 | B100: Fourniture de bureau | E100: 4480500 | F100: 207000 | G100: 4273500 | I100: =VALUE(LEFT(BalanceN[[#This Row],[Compte]]&"00000000",5)) -> 60550 | J100: {=IF(BalanceN[[#This Row],[Compte]]="",0,_xlfn.IFNA(INDEX(Plan_Comptable[[Table de Compte]:[Sens]],MATCH(VALUE(LEFT(BalanceN[[#This Row],[Table]],4)),VALUE(Plan_Comptable[Table de Compte]),0),2),"A"))} -> 0 | K100: =IF(AND(BalanceN[[#This Row],[Vérif]]="D",BalanceN[[#This Row],[BS_Credit]]>0),"A",IF(AND(BalanceN[[#This Row],[Vérif]]="C",BalanceN[[#This Row],[BS_Debit]]>0),"A","")) | L100: =IF(AND(BalanceN[[#This Row],[Vérif]]="D",BalanceN[[#This Row],[BE_Credit]]>0),"A",IF(AND(BalanceN[[#This Row],[Vérif]]="C",BalanceN[[#This Row],[BE_Debit]]>0),"A","")) | N100: 618300 | O100: Transports administratifs | R100: 685825 | T100: 685825 | V100: =VALUE(LEFT(BalanceN1[[#This Row],[Compte]]&"00000000",5)) -> 61830 | W100: {=IF(BalanceN1[[#This Row],[Compte]]="",0,_xlfn.IFNA(INDEX(Plan_Comptable[[Table de Compte]:[Sens]],MATCH(VALUE(LEFT(BalanceN1[[#This Row],[Table]],4)),VALUE(Plan_Comptable[Table de Compte]),0),2),"A"))} -> 0 | X100: =IF(AND(BalanceN1[[#This Row],[Vérif]]="D",BalanceN1[[#This Row],[BS_Credit]]>0),"A",IF(AND(BalanceN1[[#This Row],[Vérif]]="C",BalanceN1[[#This Row],[BS_Debit]]>0),"A","")) | Y100: =IF(AND(BalanceN1[[#This Row],[Vérif]]="D",BalanceN1[[#This Row],[BE_Credit]]>0),"A",IF(AND(BalanceN1[[#This Row],[Vérif]]="C",BalanceN1[[#This Row],[BE_Debit]]>0),"A",""))
...

Sheet Table TFT
A1: ="COMPTE A ECLATER DE L'EXERCICE "&TEXT(Sommaire!Q35,"yyyy") -> COMPTE A ECLATER DE L'EXERCICE 1900 | J1: ="COMPTE A ECLATER DE L'EXERCICE "&TEXT(Sommaire!Q37,"yyyy") -> COMPTE A ECLATER DE L'EXERCICE 1900
A2: ="Veuillez subdiviser les comptes 106; 154; 1984; 4781; 48161;4817; 4818 figurant dans votre balance à 6 colonnes de l'exercice "&TEXT(Sommaire!Q35,"yyyy") -> Veuillez subdiviser les comptes 106; 154; 1984; 4781; 48161;4817; 4818 figurant dans votre balance à 6 colonnes de l'exercice 1900 | J2: ="Veuillez subdiviser les comptes 106; 154; 1984; 4781; 48161;4817; 4818 figurant dans votre balance à 6 colonnes de l'exercice "&TEXT(Sommaire!Q37,"yyyy") -> Veuillez subdiviser les comptes 106; 154; 1984; 4781; 48161;4817; 4818 figurant dans votre balance à 6 colonnes de l'exercice 1900
B4: =IF(OR(C4<>0,D4<>0,E4<>0,F4<>0,G4<>0,H4<>0),"Attention détail compte 106 non conforme","") | C4: =SUMIFS(BalanceN[BE_Debit],BalanceN[Table],">=10600",BalanceN[Table],"<10700")-SUMIFS(TFTN[BE_Debit],TFTN[Compte],">=10600",TFTN[Compte],"<10700") -> 0 | D4: =SUMIFS(BalanceN[BE_Credit],BalanceN[Table],">=10600",BalanceN[Table],"<10700")-SUMIFS(TFTN[BE_Credit],TFTN[Compte],">=10600",TFTN[Compte],"<10700") -> 0 | E4: =SUMIFS(BalanceN[Mvt_Debit],BalanceN[Table],">=10600",BalanceN[Table],"<10700")-SUMIFS(TFTN[Mvt_Debit],TFTN[Compte],">=10600",TFTN[Compte],"<10700") -> 0 | F4: =SUMIFS(BalanceN[Mvt_Credit],BalanceN[Table],">=10600",BalanceN[Table],"<10700")-SUMIFS(TFTN[Mvt_Credit],TFTN[Compte],">=10600",TFTN[Compte],"<10700") -> 0 | G4: =SUMIFS(BalanceN[BS_Debit],BalanceN[Table],">=10600",BalanceN[Table],"<10700")-SUMIFS(TFTN[BS_Debit],TFTN[Compte],">=10600",TFTN[Compte],"<10700") -> 0 | H4: =SUMIFS(BalanceN[BS_Credit],BalanceN[Table],">=10600",BalanceN[Table],"<10700")-SUMIFS(TFTN[BS_Credit],TFTN[Compte],">=10600",TFTN[Compte],"<10700") -> 0 | K4: =IF(OR(L4<>0,M4<>0,N4<>0,O4<>0,P4<>0,Q4<>0),"Attention détail compte 106 non conforme","") | L4: =SUMIFS(BalanceN1[BE_Debit],BalanceN1[Table],">=10600",BalanceN1[Table],"<10700")-SUMIFS(TFTN1[BE_Debit],TFTN1[Compte],">=10600",TFTN1[Compte],"<10700") -> 0 | M4: =SUMIFS(BalanceN1[BE_Credit],BalanceN1[Table],">=10600",BalanceN1[Table],"<10700")-SUMIFS(TFTN1[BE_Credit],TFTN1[Compte],">=10600",TFTN1[Compte],"<10700") -> 0 | N4: =SUMIFS(BalanceN1[Mvt_Debit],BalanceN1[Table],">=10600",BalanceN1[Table],"<10700")-SUMIFS(TFTN1[Mvt_Debit],TFTN1[Compte],">=10600",TFTN1[Compte],"<10700") -> 0 | O4: =SUMIFS(BalanceN1[Mvt_Credit],BalanceN1[Table],">=10600",BalanceN1[Table],"<10700")-SUMIFS(TFTN1[Mvt_Credit],TFTN1[Compte],">=10600",TFTN1[Compte],"<10700") -> 0 | P4: =SUMIFS(BalanceN1[BS_Debit],BalanceN1[Table],">=10600",BalanceN1[Table],"<10700")-SUMIFS(TFTN1[BS_Debit],TFTN1[Compte],">=10600",TFTN1[Compte],"<10700") -> 0 | Q4: =SUMIFS(BalanceN1[BS_Credit],BalanceN1[Table],">=10600",BalanceN1[Table],"<10700")-SUMIFS(TFTN1[BS_Credit],TFTN1[Compte],">=10600",TFTN1[Compte],"<10700") -> 0
B5: =IF(OR(C5<>0,D5<>0,E5<>0,F5<>0,G5<>0,H5<>0),"Attention détail compte 154 non conforme","") | C5: =SUMIFS(BalanceN[BE_Debit],BalanceN[Table],">=15400",BalanceN[Table],"<15500")-SUMIFS(TFTN[BE_Debit],TFTN[Compte],">=15400",TFTN[Compte],"<15500") -> 0 | D5: =SUMIFS(BalanceN[BE_Credit],BalanceN[Table],">=15400",BalanceN[Table],"<15500")-SUMIFS(TFTN[BE_Credit],TFTN[Compte],">=15400",TFTN[Compte],"<15500") -> 0 | E5: =SUMIFS(BalanceN[Mvt_Debit],BalanceN[Table],">=15400",BalanceN[Table],"<15500")-SUMIFS(TFTN[Mvt_Debit],TFTN[Compte],">=15400",TFTN[Compte],"<15500") -> 0 | F5: =SUMIFS(BalanceN[Mvt_Credit],BalanceN[Table],">=15400",BalanceN[Table],"<15500")-SUMIFS(TFTN[Mvt_Credit],TFTN[Compte],">=15400",TFTN[Compte],"<15500") -> 0 | G5: =SUMIFS(BalanceN[BS_Debit],BalanceN[Table],">=15400",BalanceN[Table],"<15500")-SUMIFS(TFTN[BS_Debit],TFTN[Compte],">=15400",TFTN[Compte],"<15500") -> 0 | H5: =SUMIFS(BalanceN[BS_Credit],BalanceN[Table],">=15400",BalanceN[Table],"<15500")-SUMIFS(TFTN[BS_Credit],TFTN[Compte],">=15400",TFTN[Compte],"<15500") -> 0 | K5: =IF(OR(L5<>0,M5<>0,N5<>0,O5<>0,P5<>0,Q5<>0),"Attention détail compte 154 non conforme","") | L5: =SUMIFS(BalanceN1[BE_Debit],BalanceN1[Table],">=15400",BalanceN1[Table],"<15500")-SUMIFS(TFTN1[BE_Debit],TFTN1[Compte],">=15400",TFTN1[Compte],"<15500") -> 0 | M5: =SUMIFS(BalanceN1[BE_Credit],BalanceN1[Table],">=15400",BalanceN1[Table],"<15500")-SUMIFS(TFTN1[BE_Credit],TFTN1[Compte],">=15400",TFTN1[Compte],"<15500") -> 0 | N5: =SUMIFS(BalanceN1[Mvt_Debit],BalanceN1[Table],">=15400",BalanceN1[Table],"<15500")-SUMIFS(TFTN1[Mvt_Debit],TFTN1[Compte],">=15400",TFTN1[Compte],"<15500") -> 0 | O5: =SUMIFS(BalanceN1[Mvt_Credit],BalanceN1[Table],">=15400",BalanceN1[Table],"<15500")-SUMIFS(TFTN1[Mvt_Credit],TFTN1[Compte],">=15400",TFTN1[Compte],"<15500") -> 0 | P5: =SUMIFS(BalanceN1[BS_Debit],BalanceN1[Table],">=15400",BalanceN1[Table],"<15500")-SUMIFS(TFTN1[BS_Debit],TFTN1[Compte],">=15400",TFTN1[Compte],"<15500") -> 0 | Q5: =SUMIFS(BalanceN1[BS_Credit],BalanceN1[Table],">=15400",BalanceN1[Table],"<15500")-SUMIFS(TFTN1[BS_Credit],TFTN1[Compte],">=15400",TFTN1[Compte],"<15500") -> 0
B6: =IF(OR(C6<>0,D6<>0,E6<>0,F6<>0,G6<>0,H6<>0),"Attention détail compte 1984 non conforme","") | C6: =SUMIFS(BalanceN[BE_Debit],BalanceN[Table],">=19840",BalanceN[Table],"<19850")-SUMIFS(TFTN[BE_Debit],TFTN[Compte],">=19840",TFTN[Compte],"<19850") -> 0 | D6: =SUMIFS(BalanceN[BE_Credit],BalanceN[Table],">=19840",BalanceN[Table],"<19850")-SUMIFS(TFTN[BE_Credit],TFTN[Compte],">=19840",TFTN[Compte],"<19850") -> 0 | E6: =SUMIFS(BalanceN[Mvt_Debit],BalanceN[Table],">=19840",BalanceN[Table],"<19850")-SUMIFS(TFTN[Mvt_Debit],TFTN[Compte],">=19840",TFTN[Compte],"<19850") -> 0 | F6: =SUMIFS(BalanceN[Mvt_Credit],BalanceN[Table],">=19840",BalanceN[Table],"<19850")-SUMIFS(TFTN[Mvt_Credit],TFTN[Compte],">=19840",TFTN[Compte],"<19850") -> 0 | G6: =SUMIFS(BalanceN[BS_Debit],BalanceN[Table],">=19840",BalanceN[Table],"<19850")-SUMIFS(TFTN[BS_Debit],TFTN[Compte],">=19840",TFTN[Compte],"<19850") -> 0 | H6: =SUMIFS(BalanceN[BS_Credit],BalanceN[Table],">=19840",BalanceN[Table],"<19850")-SUMIFS(TFTN[BS_Credit],TFTN[Compte],">=19840",TFTN[Compte],"<19850") -> 0 | K6: =IF(OR(L6<>0,M6<>0,N6<>0,O6<>0,P6<>0,Q6<>0),"Attention détail compte 1984 non conforme","") | L6: =SUMIFS(BalanceN1[BE_Debit],BalanceN1[Table],">=19840",BalanceN1[Table],"<19850")-SUMIFS(TFTN1[BE_Debit],TFTN1[Compte],">=19840",TFTN1[Compte],"<19850") -> 0 | M6: =SUMIFS(BalanceN1[BE_Credit],BalanceN1[Table],">=19840",BalanceN1[Table],"<19850")-SUMIFS(TFTN1[BE_Credit],TFTN1[Compte],">=19840",TFTN1[Compte],"<19850") -> 0 | N6: =SUMIFS(BalanceN1[Mvt_Debit],BalanceN1[Table],">=19840",BalanceN1[Table],"<19850")-SUMIFS(TFTN1[Mvt_Debit],TFTN1[Compte],">=19840",TFTN1[Compte],"<19850") -> 0 | O6: =SUMIFS(BalanceN1[Mvt_Credit],BalanceN1[Table],">=19840",BalanceN1[Table],"<19850")-SUMIFS(TFTN1[Mvt_Credit],TFTN1[Compte],">=19840",TFTN1[Compte],"<19850") -> 0 | P6: =SUMIFS(BalanceN1[BS_Debit],BalanceN1[Table],">=19840",BalanceN1[Table],"<19850")-SUMIFS(TFTN1[BS_Debit],TFTN1[Compte],">=19840",TFTN1[Compte],"<19850") -> 0 | Q6: =SUMIFS(BalanceN1[BS_Credit],BalanceN1[Table],">=19840",BalanceN1[Table],"<19850")-SUMIFS(TFTN1[BS_Credit],TFTN1[Compte],">=19840",TFTN1[Compte],"<19850") -> 0
B7: =IF(OR(C7<>0,D7<>0,E7<>0,F7<>0,G7<>0,H7<>0),"Attention détail compte 4781 non conforme","") | C7: =SUMIFS(BalanceN[BE_Debit],BalanceN[Table],">=47810",BalanceN[Table],"<47820")-SUMIFS(TFTN[BE_Debit],TFTN[Compte],">=47810",TFTN[Compte],"<47820") -> 0 | D7: =SUMIFS(BalanceN[BE_Credit],BalanceN[Table],">=47810",BalanceN[Table],"<47820")-SUMIFS(TFTN[BE_Credit],TFTN[Compte],">=47810",TFTN[Compte],"<47820") -> 0 | E7: =SUMIFS(BalanceN[Mvt_Debit],BalanceN[Table],">=47810",BalanceN[Table],"<47820")-SUMIFS(TFTN[Mvt_Debit],TFTN[Compte],">=47810",TFTN[Compte],"<47820") -> 0 | F7: =SUMIFS(BalanceN[Mvt_Credit],BalanceN[Table],">=47810",BalanceN[Table],"<47820")-SUMIFS(TFTN[Mvt_Credit],TFTN[Compte],">=47810",TFTN[Compte],"<47820") -> 0 | G7: =SUMIFS(BalanceN[BS_Debit],BalanceN[Table],">=47810",BalanceN[Table],"<47820")-SUMIFS(TFTN[BS_Debit],TFTN[Compte],">=47810",TFTN[Compte],"<47820") -> 0 | H7: =SUMIFS(BalanceN[BS_Credit],BalanceN[Table],">=47810",BalanceN[Table],"<47820")-SUMIFS(TFTN[BS_Credit],TFTN[Compte],">=47810",TFTN[Compte],"<47820") -> 0 | K7: =IF(OR(L7<>0,M7<>0,N7<>0,O7<>0,P7<>0,Q7<>0),"Attention détail compte 4781 non conforme","") | L7: =SUMIFS(BalanceN1[BE_Debit],BalanceN1[Table],">=47810",BalanceN1[Table],"<47820")-SUMIFS(TFTN1[BE_Debit],TFTN1[Compte],">=47810",TFTN1[Compte],"<47820") -> 0 | M7: =SUMIFS(BalanceN1[BE_Credit],BalanceN1[Table],">=47810",BalanceN1[Table],"<47820")-SUMIFS(TFTN1[BE_Credit],TFTN1[Compte],">=47810",TFTN1[Compte],"<47820") -> 0 | N7: =SUMIFS(BalanceN1[Mvt_Debit],BalanceN1[Table],">=47810",BalanceN1[Table],"<47820")-SUMIFS(TFTN1[Mvt_Debit],TFTN1[Compte],">=47810",TFTN1[Compte],"<47820") -> 0 | O7: =SUMIFS(BalanceN1[Mvt_Credit],BalanceN1[Table],">=47810",BalanceN1[Table],"<47820")-SUMIFS(TFTN1[Mvt_Credit],TFTN1[Compte],">=47810",TFTN1[Compte],"<47820") -> 0 | P7: =SUMIFS(BalanceN1[BS_Debit],BalanceN1[Table],">=47810",BalanceN1[Table],"<47820")-SUMIFS(TFTN1[BS_Debit],TFTN1[Compte],">=47810",TFTN1[Compte],"<47820") -> 0 | Q7: =SUMIFS(BalanceN1[BS_Credit],BalanceN1[Table],">=47810",BalanceN1[Table],"<47820")-SUMIFS(TFTN1[BS_Credit],TFTN1[Compte],">=47810",TFTN1[Compte],"<47820") -> 0
B8: =IF(OR(C8<>0,D8<>0,E8<>0,F8<>0,G8<>0,H8<>0),"Attention détail compte 4791 non conforme","") | C8: =SUMIFS(BalanceN[BE_Debit],BalanceN[Table],">=47910",BalanceN[Table],"<47920")-SUMIFS(TFTN[BE_Debit],TFTN[Compte],">=47910",TFTN[Compte],"<47920") -> 0 | D8: =SUMIFS(BalanceN[BE_Credit],BalanceN[Table],">=47910",BalanceN[Table],"<47920")-SUMIFS(TFTN[BE_Credit],TFTN[Compte],">=47910",TFTN[Compte],"<47920") -> 0 | E8: =SUMIFS(BalanceN[Mvt_Debit],BalanceN[Table],">=47910",BalanceN[Table],"<47920")-SUMIFS(TFTN[Mvt_Debit],TFTN[Compte],">=47910",TFTN[Compte],"<47920") -> 0 | F8: =SUMIFS(BalanceN[Mvt_Credit],BalanceN[Table],">=47910",BalanceN[Table],"<47920")-SUMIFS(TFTN[Mvt_Credit],TFTN[Compte],">=47910",TFTN[Compte],"<47920") -> 0 | G8: =SUMIFS(BalanceN[BS_Debit],BalanceN[Table],">=47910",BalanceN[Table],"<47920")-SUMIFS(TFTN[BS_Debit],TFTN[Compte],">=47910",TFTN[Compte],"<47920") -> 0 | H8: =SUMIFS(BalanceN[BS_Credit],BalanceN[Table],">=47910",BalanceN[Table],"<47920")-SUMIFS(TFTN[BS_Credit],TFTN[Compte],">=47910",TFTN[Compte],"<47920") -> 0 | K8: =IF(OR(L8<>0,M8<>0,N8<>0,O8<>0,P8<>0,Q8<>0),"Attention détail compte 4791 non conforme","") | L8: =SUMIFS(BalanceN1[BE_Debit],BalanceN1[Table],">=47910",BalanceN1[Table],"<47920")-SUMIFS(TFTN1[BE_Debit],TFTN1[Compte],">=47910",TFTN1[Compte],"<47920") -> 0 | M8: =SUMIFS(BalanceN1[BE_Credit],BalanceN1[Table],">=47910",BalanceN1[Table],"<47920")-SUMIFS(TFTN1[BE_Credit],TFTN1[Compte],">=47910",TFTN1[Compte],"<47920") -> 0 | N8: =SUMIFS(BalanceN1[Mvt_Debit],BalanceN1[Table],">=47910",BalanceN1[Table],"<47920")-SUMIFS(TFTN1[Mvt_Debit],TFTN1[Compte],">=47910",TFTN1[Compte],"<47920") -> 0 | O8: =SUMIFS(BalanceN1[Mvt_Credit],BalanceN1[Table],">=47910",BalanceN1[Table],"<47920")-SUMIFS(TFTN1[Mvt_Credit],TFTN1[Compte],">=47910",TFTN1[Compte],"<47920") -> 0 | P8: =SUMIFS(BalanceN1[BS_Debit],BalanceN1[Table],">=47910",BalanceN1[Table],"<47920")-SUMIFS(TFTN1[BS_Debit],TFTN1[Compte],">=47910",TFTN1[Compte],"<47920") -> 0 | Q8: =SUMIFS(BalanceN1[BS_Credit],BalanceN1[Table],">=47910",BalanceN1[Table],"<47920")-SUMIFS(TFTN1[BS_Credit],TFTN1[Compte],">=47910",TFTN1[Compte],"<47920") -> 0
B9: =IF(OR(C9<>0,D9<>0,E9<>0,F9<>0,G9<>0,H9<>0),"Attention détail compte 4816 non conforme","") | C9: =SUMIFS(BalanceN[BE_Debit],BalanceN[Table],">=48160",BalanceN[Table],"<48170")-SUMIFS(TFTN[BE_Debit],TFTN[Compte],">=48160",TFTN[Compte],"<48170") -> 0 | D9: =SUMIFS(BalanceN[BE_Credit],BalanceN[Table],">=48160",BalanceN[Table],"<48170")-SUMIFS(TFTN[BE_Credit],TFTN[Compte],">=48160",TFTN[Compte],"<48170") -> 0 | E9: =SUMIFS(BalanceN[Mvt_Debit],BalanceN[Table],">=48160",BalanceN[Table],"<48170")-SUMIFS(TFTN[Mvt_Debit],TFTN[Compte],">=48160",TFTN[Compte],"<48170") -> 0 | F9: =SUMIFS(BalanceN[Mvt_Credit],BalanceN[Table],">=48160",BalanceN[Table],"<48170")-SUMIFS(TFTN[Mvt_Credit],TFTN[Compte],">=48160",TFTN[Compte],"<48170") -> 0 | G9: =SUMIFS(BalanceN[BS_Debit],BalanceN[Table],">=48160",BalanceN[Table],"<48170")-SUMIFS(TFTN[BS_Debit],TFTN[Compte],">=48160",TFTN[Compte],"<48170") -> 0 | H9: =SUMIFS(BalanceN[BS_Credit],BalanceN[Table],">=48160",BalanceN[Table],"<48170")-SUMIFS(TFTN[BS_Credit],TFTN[Compte],">=48160",TFTN[Compte],"<48170") -> 0 | K9: =IF(OR(L9<>0,M9<>0,N9<>0,O9<>0,P9<>0,Q9<>0),"Attention détail compte 4816 non conforme","") | L9: =SUMIFS(BalanceN1[BE_Debit],BalanceN1[Table],">=48160",BalanceN1[Table],"<48170")-SUMIFS(TFTN1[BE_Debit],TFTN1[Compte],">=48160",TFTN1[Compte],"<48170") -> 0 | M9: =SUMIFS(BalanceN1[BE_Credit],BalanceN1[Table],">=48160",BalanceN1[Table],"<48170")-SUMIFS(TFTN1[BE_Credit],TFTN1[Compte],">=48160",TFTN1[Compte],"<48170") -> 0 | N9: =SUMIFS(BalanceN1[Mvt_Debit],BalanceN1[Table],">=48160",BalanceN1[Table],"<48170")-SUMIFS(TFTN1[Mvt_Debit],TFTN1[Compte],">=48160",TFTN1[Compte],"<48170") -> 0 | O9: =SUMIFS(BalanceN1[Mvt_Credit],BalanceN1[Table],">=48160",BalanceN1[Table],"<48170")-SUMIFS(TFTN1[Mvt_Credit],TFTN1[Compte],">=48160",TFTN1[Compte],"<48170") -> 0 | P9: =SUMIFS(BalanceN1[BS_Debit],BalanceN1[Table],">=48160",BalanceN1[Table],"<48170")-SUMIFS(TFTN1[BS_Debit],TFTN1[Compte],">=48160",TFTN1[Compte],"<48170") -> 0 | Q9: =SUMIFS(BalanceN1[BS_Credit],BalanceN1[Table],">=48160",BalanceN1[Table],"<48170")-SUMIFS(TFTN1[BS_Credit],TFTN1[Compte],">=48160",TFTN1[Compte],"<48170") -> 0
B10: =IF(OR(C10<>0,D10<>0,E10<>0,F10<>0,G10<>0,H10<>0),"Attention détail compte 4817 non conforme","") | C10: =SUMIFS(BalanceN[BE_Debit],BalanceN[Table],">=48170",BalanceN[Table],"<48180")-SUMIFS(TFTN[BE_Debit],TFTN[Compte],">=48170",TFTN[Compte],"<48180") -> 0 | D10: =SUMIFS(BalanceN[BE_Credit],BalanceN[Table],">=48170",BalanceN[Table],"<48180")-SUMIFS(TFTN[BE_Credit],TFTN[Compte],">=48170",TFTN[Compte],"<48180") -> 0 | E10: =SUMIFS(BalanceN[Mvt_Debit],BalanceN[Table],">=48170",BalanceN[Table],"<48180")-SUMIFS(TFTN[Mvt_Debit],TFTN[Compte],">=48170",TFTN[Compte],"<48180") -> 0 | F10: =SUMIFS(BalanceN[Mvt_Credit],BalanceN[Table],">=48170",BalanceN[Table],"<48180")-SUMIFS(TFTN[Mvt_Credit],TFTN[Compte],">=48170",TFTN[Compte],"<48180") -> 0 | G10: =SUMIFS(BalanceN[BS_Debit],BalanceN[Table],">=48170",BalanceN[Table],"<48180")-SUMIFS(TFTN[BS_Debit],TFTN[Compte],">=48170",TFTN[Compte],"<48180") -> 0 | H10: =SUMIFS(BalanceN[BS_Credit],BalanceN[Table],">=48170",BalanceN[Table],"<48180")-SUMIFS(TFTN[BS_Credit],TFTN[Compte],">=48170",TFTN[Compte],"<48180") -> 0 | K10: =IF(OR(L10<>0,M10<>0,N10<>0,O10<>0,P10<>0,Q10<>0),"Attention détail compte 4817 non conforme","") | L10: =SUMIFS(BalanceN1[BE_Debit],BalanceN1[Table],">=48170",BalanceN1[Table],"<48180")-SUMIFS(TFTN1[BE_Debit],TFTN1[Compte],">=48170",TFTN1[Compte],"<48180") -> 0 | M10: =SUMIFS(BalanceN1[BE_Credit],BalanceN1[Table],">=48170",BalanceN1[Table],"<48180")-SUMIFS(TFTN1[BE_Credit],TFTN1[Compte],">=48170",TFTN1[Compte],"<48180") -> 0 | N10: =SUMIFS(BalanceN1[Mvt_Debit],BalanceN1[Table],">=48170",BalanceN1[Table],"<48180")-SUMIFS(TFTN1[Mvt_Debit],TFTN1[Compte],">=48170",TFTN1[Compte],"<48180") -> 0 | O10: =SUMIFS(BalanceN1[Mvt_Credit],BalanceN1[Table],">=48170",BalanceN1[Table],"<48180")-SUMIFS(TFTN1[Mvt_Credit],TFTN1[Compte],">=48170",TFTN1[Compte],"<48180") -> 0 | P10: =SUMIFS(BalanceN1[BS_Debit],BalanceN1[Table],">=48170",BalanceN1[Table],"<48180")-SUMIFS(TFTN1[BS_Debit],TFTN1[Compte],">=48170",TFTN1[Compte],"<48180") -> 0 | Q10: =SUMIFS(BalanceN1[BS_Credit],BalanceN1[Table],">=48170",BalanceN1[Table],"<48180")-SUMIFS(TFTN1[BS_Credit],TFTN1[Compte],">=48170",TFTN1[Compte],"<48180") -> 0
